Workbook

Sheet Cover
B2: Super Micro Forensic Analysis: Earnings Quality and Accounting Red Flags
B3: Forensic screen · Prepared by Alessandro Radice · Educational project, not investment advice · June 2025
B6: Question | C6: On 30 June 2025, after Super Micro filed its delayed fiscal 2024 10-K (clean opinion on the numbers, adverse on internal controls): do the financial statements carry red flags, would a systematic screen have seen trouble before the August 2024 short report, and how reliable is such a screen?
B7: Inputs | C7: Choose any quarter (yellow cell). The trailing-twelve-month financials for that quarter, the year before and two years before are pulled from the Timeline sheet. Thresholds are switches too.
B8: Beneish | C8: The eight Beneish (1999) indices and the M-score for the chosen quarter, with each index's contribution from a neutral company.
B9: Dechow | C9: The Dechow, Ge, Larson and Sloan (2011) F-score, model 1, for the chosen quarter, with RSST accruals.
B10: Timeline | C10: Every quarter from June 2013 to March 2025, with the financials as first filed (SEC XBRL, point in time) and every score recomputed by formula.
B11: Validation | C11: 16 companies the SEC charged or that restated inflated earnings. Each misstated year as first filed, scored by formula; hit rates at the thresholds on Inputs.
B12: Universe | C12: M-score and F-score for 1,235 US operating companies (2023 against 2022, SEC frames API), used for false-alarm rates and percentiles.
B13: Market | C13: Daily closes of Super Micro and the Nasdaq-100 (QQQ), split-adjusted; beta and abnormal returns on the event days by formula.
B14: Checks | C14: Reconciliation of this workbook with the Python engine (Super_Micro_Forensic_Analysis.ipynb).
B15: Units | C15: Financial items in $ millions. Missing XBRL items show "n/a": the formulas then set that index to neutral (1 for Beneish indices, 0 for F-score inputs), as the Python engine does.
B16: Colour code | C16: Blue = hard-coded input · Black = formula · Green = link to another sheet · Yellow fill = switch · Red fill = flag.
B17: Sources | C17: SEC EDGAR XBRL company facts, frames and submissions APIs; DoltHub post-no-preference/stocks; SEC press releases and orders for the validation cases. Beneish (1999); Dechow et al. (2011); Richardson et al. (2005).

Sheet Inputs
B2: Inputs
B3: Switches, model coefficients and the financials of the selected quarter ($ millions)
B5: Switches
B6: Quarter end to analyse | C6: 45382 | F6: Any quarter end on the Timeline sheet. 31 Mar 2024 = the 10-Q of 6 May 2024, before the short report
B7: M-score threshold | C7: -1.78 | F7: Beneish (1999); −2.22 is a common stricter screen
B8: F-score threshold | C8: 1.85 | F8: Dechow et al. (2011): above 1 elevated, above 1.85 substantial, above 2.45 high risk
B9: Row on the Timeline sheet | C9: =MATCH(C6,Timeline!$B$6:$B$50,0)+5 -> 46 | F9: Looked up from the date above
B10: Filed | C10: =INDEX(Timeline!C:C,C9) -> 45418
B12: Beneish M-score coefficients | C12: Value | F12: Source
B13: Intercept | C13: -4.84 | F13: Beneish (1999), Financial Analysts Journal 55(5), unweighted probit
B14: DSRI · Days sales in receivables index | C14: 0.92
B15: GMI · Gross margin index | C15: 0.528
B16: AQI · Asset quality index | C16: 0.404
B17: SGI · Sales growth index | C17: 0.892
B18: DEPI · Depreciation index | C18: 0.115
B19: SGAI · SG&A index | C19: -0.172
B20: TATA · Total accruals to total assets | C20: 4.679
B21: LVGI · Leverage index | C21: -0.327
B23: Dechow F-score coefficients (model 1) | C23: Value | F23: Source
B24: Intercept | C24: -7.893 | F24: Dechow, Ge, Larson and Sloan (2011), Contemporary Accounting Research 28(1)
B25: RSST accruals | C25: 0.79
B26: Change in receivables | C26: 2.518
B27: Change in inventory | C27: 1.191
B28: Soft assets | C28: 1.979
B29: Change in cash sales | C29: 0.171
B30: Change in ROA | C30: -0.932
B31: Securities issued (0/1) | C31: 1.029
B32: Unconditional misstatement probability | C32: 0.0037
B34: Selected quarter, trailing twelve months ($M) | C34: This year (t) | D34: Year before (t−1) | E34: Two years before (t−2) | F34: Note
B35: Sales | C35: =INDEX(Timeline!AD:AD,$C$9) -> 11819.523 | D35: =INDEX(Timeline!AW:AW,$C$9) -> 6574.081 | E35: =INDEX(Timeline!BQ:BQ,$C$9) -> 4629.624 | F35: Flows are trailing twelve months; balances at the quarter end
B36: Cost of sales | C36: =INDEX(Timeline!AE:AE,$C$9) -> 9932.446 | D36: =INDEX(Timeline!AX:AX,$C$9) -> 5375.421
B37: SG&A | C37: =INDEX(Timeline!AF:AF,$C$9) -> 317.155 | D37: =INDEX(Timeline!AY:AY,$C$9) -> 205.812
B38: Depreciation | C38: =INDEX(Timeline!AG:AG,$C$9) -> 38.146 | D38: =INDEX(Timeline!AZ:AZ,$C$9) -> 34.354
B39: Net income | C39: =INDEX(Timeline!AH:AH,$C$9) -> 1048.991 | D39: =INDEX(Timeline!BA:BA,$C$9) -> 587.251 | E39: =INDEX(Timeline!BS:BS,$C$9) -> 183.503
B40: Operating cash flow | C40: =INDEX(Timeline!AI:AI,$C$9) -> -1853.497 | D40: =INDEX(Timeline!BB:BB,$C$9) -> 647.776
B41: Debt/equity issued | C41: =INDEX(Timeline!AJ:AJ,$C$9) -> 2748.384 | D41: =INDEX(Timeline!BC:BC,$C$9) -> 379.568 | F41: Proceeds from debt or equity issued in the period (F-score issuance dummy)
B42: Receivables | C42: =INDEX(Timeline!AK:AK,$C$9) -> 1650.153 | D42: =INDEX(Timeline!BD:BD,$C$9) -> 672.055 | E42: =INDEX(Timeline!BP:BP,$C$9) -> 679.785
B43: Inventory | C43: =INDEX(Timeline!AL:AL,$C$9) -> 4124.587 | D43: =INDEX(Timeline!BE:BE,$C$9) -> 1540.419
B44: Current assets | C44: =INDEX(Timeline!AM:AM,$C$9) -> 8063.932 | D44: =INDEX(Timeline!BF:BF,$C$9) -> 2715.175
B45: Total assets | C45: =INDEX(Timeline!AN:AN,$C$9) -> 8862.781 | D45: =INDEX(Timeline!BG:BG,$C$9) -> 3192.604 | E45: =INDEX(Timeline!BR:BR,$C$9) -> 3071.177
B46: Net PP&E | C46: =INDEX(Timeline!AO:AO,$C$9) -> 385.566 | D46: =INDEX(Timeline!BH:BH,$C$9) -> 290.038
B47: Cash | C47: =INDEX(Timeline!AP:AP,$C$9) -> 2115.476 | D47: =INDEX(Timeline!BI:BI,$C$9) -> 362.801
B48: Short-term investments | C48: =INDEX(Timeline!AQ:AQ,$C$9) -> n/a | D48: =INDEX(Timeline!BJ:BJ,$C$9) -> n/a
B49: Long-term investments | C49: =INDEX(Timeline!AR:AR,$C$9) -> n/a | D49: =INDEX(Timeline!BK:BK,$C$9) -> 1.59
B50: Current liabilities | C50: =INDEX(Timeline!AS:AS,$C$9) -> 1717.695 | D50: =INDEX(Timeline!BL:BL,$C$9) -> 1092.38
B51: Total liabilities | C51: =INDEX(Timeline!AT:AT,$C$9) -> 3768.625 | D51: =INDEX(Timeline!BM:BM,$C$9) -> 1424.031
B52: Long-term debt | C52: =INDEX(Timeline!AU:AU,$C$9) -> 85.646 | D52: =INDEX(Timeline!BN:BN,$C$9) -> 133.235
B53: Current debt | C53: =INDEX(Timeline!AV:AV,$C$9) -> n/a | D53: =INDEX(Timeline!BO:BO,$C$9) -> n/a

Sheet Beneish
B2: Beneish M-score
B3: Selected quarter on Inputs!C6 · each index against the year before · contribution = coefficient × (index − neutral)
B5: Quarter end | C5: =Inputs!C6 -> 45382
B6: Filed | C6: =Inputs!C10 -> 45418
B8: Index | C8: Value | D8: Coefficient | E8: Neutral | F8: Contribution | G8: What a high value means
B9: DSRI · Days sales in receivables index | C9: =IFERROR((Inputs!$C$42/Inputs!$C$35)/(Inputs!$D$42/Inputs!$D$35),1) -> 1.3656974 | D9: =Inputs!$C$14 -> 0.92 | E9: 1 | F9: =D9*(C9-E9) -> 0.33644165 | G9: Receivables growing faster than sales
B10: GMI · Gross margin index | C10: =IFERROR(((Inputs!$D$35-Inputs!$D$36)/Inputs!$D$35)/((Inputs!$C$35-Inputs!$C$36)/Inputs!$C$35),1) -> 1.1420136 | D10: =Inputs!$C$15 -> 0.528 | E10: 1 | F10: =D10*(C10-E10) -> 0.074983202 | G10: Gross margin shrinking
B11: AQI · Asset quality index | C11: =IFERROR((1-(Inputs!$C$44+Inputs!$C$46)/Inputs!$C$45)/(1-(Inputs!$D$44+Inputs!$D$46)/Inputs!$D$45),1) -> 0.79446331 | D11: =Inputs!$C$16 -> 0.404 | E11: 1 | F11: =D11*(C11-E11) -> -0.083036821 | G11: More costs capitalised as intangible or other assets
B12: SGI · Sales growth index | C12: =IFERROR(Inputs!$C$35/Inputs!$D$35,1) -> 1.7978974 | D12: =Inputs!$C$17 -> 0.892 | E12: 1 | F12: =D12*(C12-E12) -> 0.71172446 | G12: Fast growth, which raises pressure and opportunity
B13: DEPI · Depreciation index | C13: =IFERROR((Inputs!$D$38/(Inputs!$D$38+Inputs!$D$46))/(Inputs!$C$38/(Inputs!$C$38+Inputs!$C$46)),1) -> 1.1763294 | D13: =Inputs!$C$18 -> 0.115 | E13: 1 | F13: =D13*(C13-E13) -> 0.020277876 | G13: Depreciating more slowly
B14: SGAI · SG&A index | C14: =IFERROR((Inputs!$C$37/Inputs!$C$35)/(Inputs!$D$37/Inputs!$D$35),1) -> 0.85710883 | D14: =Inputs!$C$19 -> -0.172 | E14: 1 | F14: =D14*(C14-E14) -> 0.024577281 | G14: Overheads growing faster than sales (negative weight)
B15: TATA · Total accruals to total assets | C15: =IFERROR((Inputs!$C$39-Inputs!$C$40)/Inputs!$C$45,0) -> 0.32749179 | D15: =Inputs!$C$20 -> 4.679 | E15: 0 | F15: =D15*(C15-E15) -> 1.5323341 | G15: Profit not backed by operating cash flow
B16: LVGI · Leverage index | C16: =IFERROR(((Inputs!$C$50+N(Inputs!$C$52))/Inputs!$C$45)/((Inputs!$D$50+N(Inputs!$D$52))/Inputs!$D$45),1) -> 0.53002801 | D16: =Inputs!$C$21 -> -0.327 | E16: 1 | F16: =D16*(C16-E16) -> 0.15368084 | G16: More leverage (negative weight in the model)
B18: Neutral company (all indices at 1, no accruals) | F18: =Inputs!$C$13+SUMPRODUCT(D9:D16,E9:E16) -> -2.48
B19: M-score | F19: =Inputs!$C$13+SUMPRODUCT(D9:D16,C9:C16) -> 0.29098257
B20: Check: neutral + contributions | F20: =F18+SUM(F9:F16)-F19 -> 0
B21: Flag (above the threshold on Inputs) | F21: =IF(F19>Inputs!C7,"RED FLAG","below threshold") -> RED FLAG
B22: Same quarter on the Timeline sheet | F22: =INDEX(Timeline!E:E,Inputs!C9) -> 0.29098257
B24: Beneish (1999) estimated the model on 74 manipulators and 2,332 controls (1982 to 1992). Above −1.78 a company looks more like the manipulators; the threshold is a convention, not a probability.

Sheet Dechow
B2: Dechow F-score
B3: Selected quarter on Inputs!C6 · model 1 of Dechow, Ge, Larson and Sloan (2011)
B5: Quarter end | C5: =Inputs!C6 -> 45382
B7: Variable | C7: Value | D7: Coefficient | E7: Contribution | F7: Definition
B8: RSST accruals | C8: =IFERROR((((Inputs!$C$44-Inputs!$C$47-N(Inputs!$C$48))-(Inputs!$C$50-N(Inputs!$C$53))+(Inputs!$C$45-Inputs!$C$44-N(Inputs!$C$49))-(Inputs!$C$51-Inputs!$C$50-N(Inputs!$C$52))+(N(Inputs!$C$48)+N(Inputs!$C$49))-(N(Inputs!$C$52)+N(Inputs!$C$53)))-((Inputs!$D$44-Inputs!$D$47-N(Inputs!$D$48))-(Inputs!$D$50-N(Inputs!$D$53))+(Inputs!$D$45-Inputs!$D$44-N(Inputs!$D$49))-(Inputs!$D$51-Inputs!$D$50-N(Inputs!$D$52))+(N(Inputs!$D$48)+N(Inputs!$D$49))-(N(Inputs!$D$52)+N(Inputs!$D$53))))/((Inputs!$C$45+Inputs!$D$45)/2),0) -> 0.26094695 | D8: =Inputs!$C$25 -> 0.79 | E8: =C8*D8 -> 0.20614809 | F8: Change in (working capital + net non-current operating assets + net financial assets), over average total assets (Richardson et al., 2005)
B9: Change in receivables | C9: =IFERROR((Inputs!$C$42-Inputs!$D$42)/((Inputs!$C$45+Inputs!$D$45)/2),0) -> 0.1622674 | D9: =Inputs!$C$26 -> 2.518 | E9: =C9*D9 -> 0.40858932 | F9: Change in receivables over average total assets
B10: Change in inventory | C10: =IFERROR((N(Inputs!$C$43)-N(Inputs!$D$43))/((Inputs!$C$45+Inputs!$D$45)/2),0) -> 0.42871596 | D10: =Inputs!$C$27 -> 1.191 | E10: =C10*D10 -> 0.51060071 | F10: Change in inventory over average total assets
B11: Soft assets | C11: =IFERROR((Inputs!$C$45-N(Inputs!$C$46)-Inputs!$C$47)/Inputs!$C$45,0) -> 0.71780393 | D11: =Inputs!$C$28 -> 1.979 | E11: =C11*D11 -> 1.420534 | F11: (Total assets − net PP&E − cash) / total assets
B12: Change in cash sales | C12: =IF(COUNT(Inputs!$E$42,Inputs!$E$35,Inputs!$E$45,Inputs!$E$39)=4,IFERROR((Inputs!$C$35-(Inputs!$C$42-Inputs!$D$42))/(Inputs!$D$35-(Inputs!$D$42-Inputs!$E$42))-1,0),0) -> 0.64717963 | D12: =Inputs!$C$29 -> 0.171 | E12: =C12*D12 -> 0.11066772 | F12: Growth in cash sales (sales minus the change in receivables)
B13: Change in ROA | C13: =IF(COUNT(Inputs!$E$42,Inputs!$E$35,Inputs!$E$45,Inputs!$E$39)=4,IFERROR(Inputs!$C$39/((Inputs!$C$45+Inputs!$D$45)/2)-Inputs!$D$39/((Inputs!$D$45+Inputs!$E$45)/2),0),0) -> -0.013478256 | D13: =Inputs!$C$30 -> -0.932 | E13: =C13*D13 -> 0.012561735 | F13: Change in return on average assets
B14: Securities issued (0/1) | C14: =IF(N(Inputs!$C$41)>0,1,0) -> 1 | D14: =Inputs!$C$31 -> 1.029 | E14: =C14*D14 -> 1.029 | F14: 1 if debt or equity was issued in the period
B16: Intercept | E16: =Inputs!$C$24 -> -7.893
B17: Predicted value (logit) | E17: =SUM(E8:E14)+E16 -> -4.1948985
B18: Probability of misstatement | E18: =EXP(E17)/(1+EXP(E17)) -> 0.014848473
B19: F-score (probability / 0.37% base rate) | E19: =E18/Inputs!$C$32 -> 4.0131007
B20: Risk band | E20: =IF(E19>2.45,"high",IF(E19>1.85,"substantial",IF(E19>1,"above normal","normal"))) -> high
B21: Same quarter on the Timeline sheet | E21: =INDEX(Timeline!F:F,Inputs!C9) -> 4.0131007
B23: Change in cash sales and change in ROA need the year t−2; when it is missing both are set to 0, as in the Python engine.

Sheet Timeline
B2: Timeline
B3: Super Micro, trailing twelve months at each quarter end, as first filed · $ millions · scores by formula
B5: Quarter end | C5: Filed | D5: Complete | E5: M-score | F5: F-score | G5: Accruals / assets | H5: CFO / net income | I5: Receivable days | J5: Inventory days | K5: M flag | L5: F flag | M5: DSRI | N5: GMI | O5: AQI | P5: SGI | Q5: DEPI | R5: SGAI | S5: TATA | T5: LVGI | U5: RSST accruals | V5: Change in receivables | W5: Change in inventory | X5: Soft assets | Y5: Change in cash sales | Z5: Change in ROA | AA5: Securities issued (0/1) | AB5: F-score logit | AD5: t: Sales | AE5: t: Cost of sales | AF5: t: SG&A | AG5: t: Depreciation | AH5: t: Net income | AI5: t: Operating cash flow | AJ5: t: Debt/equity issued | AK5: t: Receivables | AL5: t: Inventory | AM5: t: Current assets | AN5: t: Total assets | AO5: t: Net PP&E | AP5: t: Cash | AQ5: t: Short-term investments | AR5: t: Long-term investments | AS5: t: Current liabilities | AT5: t: Total liabilities | AU5: t: Long-term debt | AV5: t: Current debt | AW5: t−1: Sales | AX5: t−1: Cost of sales | AY5: t−1: SG&A | AZ5: t−1: Depreciation | BA5: t−1: Net income | BB5: t−1: Operating cash flow | BC5: t−1: Debt/equity issued | BD5: t−1: Receivables | BE5: t−1: Inventory | BF5: t−1: Current assets | BG5: t−1: Total assets | BH5: t−1: Net PP&E | BI5: t−1: Cash | BJ5: t−1: Short-term investments | BK5: t−1: Long-term investments | BL5: t−1: Current liabilities | BM5: t−1: Total liabilities | BN5: t−1: Long-term debt | BO5: t−1: Current debt | BP5: t−2: Receivables | BQ5: t−2: Sales | BR5: t−2: Total assets | BS5: t−2: Net income
B6: 41455 | C6: 41528 | D6: yes | E6: =Inputs!$C$13+Inputs!$C$14*M6+Inputs!$C$15*N6+Inputs!$C$16*O6+Inputs!$C$17*P6+Inputs!$C$18*Q6+Inputs!$C$19*R6+Inputs!$C$20*S6+Inputs!$C$21*T6 -> -1.8222756 | F6: =EXP(AB6)/(1+EXP(AB6))/Inputs!$C$32 -> 0.50365119 | G6: =IFERROR((AH6-AI6)/((AN6+BG6)/2),"n/a") -> 0.012602345 | H6: =IFERROR(AI6/AH6,"n/a") -> 0.63832887 | I6: =IFERROR(AK6/AD6*365,"n/a") -> 46.887088 | J6: =IFERROR(N(AL6)/AE6*365,"n/a") -> 92.53996 | K6: =IF(E6>Inputs!$C$7,1,0) -> 0 | L6: =IF(F6>Inputs!$C$8,1,0) -> 0 | M6: =IFERROR((AK6/AD6)/(BD6/AW6),1) -> 1.2766875 | N6: =IFERROR(((AW6-AX6)/AW6)/((AD6-AE6)/AD6),1) -> 1.1850811 | O6: =IFERROR((1-(AM6+AO6)/AN6)/(1-(BF6+BH6)/BG6),1) -> 1.2541196 | P6: =IFERROR(AD6/AW6,1) -> 1.1466523 | Q6: =IFERROR((AZ6/(AZ6+BH6))/(AG6/(AG6+AO6)),1) -> 0.89607148 | R6: =IFERROR((AF6/AD6)/(AY6/AW6),1) -> 0.91172632 | S6: =IFERROR((AH6-AI6)/AN6,0) -> 0.012172265 | T6: =IFERROR(((AS6+N(AU6))/AN6)/((BL6+N(BN6))/BG6),1) -> 0.96395872 | U6: =IFERROR((((AM6-AP6-N(AQ6))-(AS6-N(AV6))+(AN6-AM6-N(AR6))-(AT6-AS6-N(AU6))+(N(AQ6)+N(AR6))-(N(AU6)+N(AV6)))-((BF6-BI6-N(BJ6))-(BL6-N(BO6))+(BG6-BF6-N(BK6))-(BM6-BL6-N(BN6))+(N(BJ6)+N(BK6))-(N(BN6)+N(BO6))))/((AN6+BG6)/2),0) -> 0.037926574 | V6: =IFERROR((AK6-BD6)/((AN6+BG6)/2),0) -> 0.077497216 | W6: =IFERROR((N(AL6)-N(BE6))/((AN6+BG6)/2),0) -> -0.03672791 | X6: =IFERROR((AN6-N(AO6)-AP6)/AN6,0) -> 0.70115001 | Y6: =IF(COUNT(BP6,BQ6,BR6,BS6)=4,IFERROR((AD6-(AK6-BD6))/(AW6-(BD6-BP6))-1,0),0) -> 0.11874226 | Z6: =IF(COUNT(BP6,BQ6,BR6,BS6)=4,IFERROR(AH6/((AN6+BG6)/2)-BA6/((BG6+BR6)/2),0),0) -> -0.021817187 | AA6: =IF(N(AJ6)>0,1,0) -> 0 | AB6: =Inputs!$C$24+Inputs!$C$25*U6+Inputs!$C$26*V6+Inputs!$C$27*W6+Inputs!$C$28*X6+Inputs!$C$29*Y6+Inputs!$C$30*Z6+Inputs!$C$31*AA6 -> -6.2834285 | AD6: 1162.561 | AE6: 1002.508 | AF6: 57.687 | AG6: 7.835 | AH6: 21.279 | AI6: 13.583 | AJ6: n/a | AK6: 149.34 | AL6: 254.17 | AM6: 523.192 | AN6: 632.257 | AO6: 95.912 | AP6: 93.038 | AQ6: n/a | AR6: 2.637 | AS6: 241.664 | AT6: 258.533 | AU6: 6.533 | AV6: 28.638 | AW6: 1013.874 | AX6: 848.457 | AY6: 55.18 | AZ6: 7.071 | BA6: 29.853 | BB6: 16.467 | BC6: n/a | BD6: 102.014 | BE6: 276.599 | BF6: 481.912 | BG6: 589.103 | BH6: 97.419 | BI6: 80.826 | BJ6: n/a | BK6: 2.923 | BL6: 220.508 | BM6: 250.752 | BN6: 19.395 | BO6: 13.362 | BP6: 85.005 | BQ6: 942.582 | BR6: 464.62 | BS6: 40.213
B7: 41547 | C7: 41585 | D7: yes | E7: =Inputs!$C$13+Inputs!$C$14*M7+Inputs!$C$15*N7+Inputs!$C$16*O7+Inputs!$C$17*P7+Inputs!$C$18*Q7+Inputs!$C$19*R7+Inputs!$C$20*S7+Inputs!$C$21*T7 -> -2.40065 | F7: =EXP(AB7)/(1+EXP(AB7))/Inputs!$C$32 -> 0.41430176 | G7: =IFERROR((AH7-AI7)/((AN7+BG7)/2),"n/a") -> -0.050509671 | H7: =IFERROR(AI7/AH7,"n/a") -> 2.0814132 | I7: =IFERROR(AK7/AD7*365,"n/a") -> 40.745826 | J7: =IFERROR(N(AL7)/AE7*365,"n/a") -> 90.203636 | K7: =IF(E7>Inputs!$C$7,1,0) -> 0 | L7: =IF(F7>Inputs!$C$8,1,0) -> 0 | M7: =IFERROR((AK7/AD7)/(BD7/AW7),1) -> 1.0260833 | N7: =IFERROR(((AW7-AX7)/AW7)/((AD7-AE7)/AD7),1) -> 1.0840463 | O7: =IFERROR((1-(AM7+AO7)/AN7)/(1-(BF7+BH7)/BG7),1) -> 1.160467 | P7: =IFERROR(AD7/AW7,1) -> 1.1583627 | Q7: =IFERROR((AZ7/(AZ7+BH7))/(AG7/(AG7+AO7)),1) -> 1.0243422 | R7: =IFERROR((AF7/AD7)/(AY7/AW7),1) -> 0.8496544 | S7: =IFERROR((AH7-AI7)/AN7,0) -> -0.047758804 | T7: =IFERROR(((AS7+N(AU7))/AN7)/((BL7+N(BN7))/BG7),1) -> 1.0009378 | U7: =IFERROR((((AM7-AP7-N(AQ7))-(AS7-N(AV7))+(AN7-AM7-N(AR7))-(AT7-AS7-N(AU7))+(N(AQ7)+N(AR7))-(N(AU7)+N(AV7)))-((BF7-BI7-N(BJ7))-(BL7-N(BO7))+(BG7-BF7-N(BK7))-(BM7-BL7-N(BN7))+(N(BJ7)+N(BK7))-(N(BN7)+N(BO7))))/((AN7+BG7)/2),0) -> -0.016045325 | V7: =IFERROR((AK7-BD7)/((AN7+BG7)/2),0) -> 0.035379226 | W7: =IFERROR((N(AL7)-N(BE7))/((AN7+BG7)/2),0) -> -0.014707937 | X7: =IFERROR((AN7-N(AO7)-AP7)/AN7,0) -> 0.6724987 | Y7: =IF(COUNT(BP7,BQ7,BR7,BS7)=4,IFERROR((AD7-(AK7-BD7))/(AW7-(BD7-BP7))-1,0),0) -> 0.16593738 | Z7: =IF(COUNT(BP7,BQ7,BR7,BS7)=4,IFERROR(AH7/((AN7+BG7)/2)-BA7/((BG7+BR7)/2),0),0) -> 0.004497004 | AA7: =IF(N(AJ7)>0,1,0) -> 0 | AB7: =Inputs!$C$24+Inputs!$C$25*U7+Inputs!$C$26*V7+Inputs!$C$27*W7+Inputs!$C$28*X7+Inputs!$C$29*Y7+Inputs!$C$30*Z7+Inputs!$C$31*AA7 -> -6.4790491 | AD7: 1200.87 | AE7: 1029.04 | AF7: 57.088 | AG7: 7.273 | AH7: 28.079 | AI7: 58.444 | AJ7: n/a | AK7: 134.056 | AL7: 254.31 | AM7: 524.222 | AN7: 635.799 | AO7: 96.767 | AP7: 111.458 | AQ7: n/a | AR7: 2.637 | AS7: 218.283 | AT7: 249.835 | AU7: 21.05 | AV7: 13.699 | AW7: 1036.696 | AX7: 875.89 | AY7: 58.004 | AZ7: 7.491 | BA7: 22.26 | BB7: -35.224 | BC7: n/a | BD7: 112.787 | BE7: 263.152 | BF7: 458.052 | BG7: 566.545 | BH7: 97.121 | BI7: 58.323 | BJ7: n/a | BK7: 2.923 | BL7: 204.431 | BM7: 224.07 | BN7: 8.633 | BO7: 18.124 | BP7: 87.81 | BQ7: 983.289 | BR7: 488.179 | BS7: 41.488
B8: 41639 | C8: 41677 | D8: yes | E8: =Inputs!$C$13+Inputs!$C$14*M8+Inputs!$C$15*N8+Inputs!$C$16*O8+Inputs!$C$17*P8+Inputs!$C$18*Q8+Inputs!$C$19*R8+Inputs!$C$20*S8+Inputs!$C$21*T8 -> -2.0828242 | F8: =EXP(AB8)/(1+EXP(AB8))/Inputs!$C$32 -> 0.54917185 | G8: =IFERROR((AH8-AI8)/((AN8+BG8)/2),"n/a") -> 0.01566976 | H8: =IFERROR(AI8/AH8,"n/a") -> 0.72260274 | I8: =IFERROR(AK8/AD8*365,"n/a") -> 46.477379 | J8: =IFERROR(N(AL8)/AE8*365,"n/a") -> 98.418691 | K8: =IF(E8>Inputs!$C$7,1,0) -> 0 | L8: =IF(F8>Inputs!$C$8,1,0) -> 0 | M8: =IFERROR((AK8/AD8)/(BD8/AW8),1) -> 1.1546485 | N8: =IFERROR(((AW8-AX8)/AW8)/((AD8-AE8)/AD8),1) -> 0.99485996 | O8: =IFERROR((1-(AM8+AO8)/AN8)/(1-(BF8+BH8)/BG8),1) -> 0.94777637 | P8: =IFERROR(AD8/AW8,1) -> 1.1738686 | Q8: =IFERROR((AZ8/(AZ8+BH8))/(AG8/(AG8+AO8)),1) -> 1.5014497 | R8: =IFERROR((AF8/AD8)/(AY8/AW8),1) -> 0.84318379 | S8: =IFERROR((AH8-AI8)/AN8,0) -> 0.014286097 | T8: =IFERROR(((AS8+N(AU8))/AN8)/((BL8+N(BN8))/BG8),1) -> 1.0852083 | U8: =IFERROR((((AM8-AP8-N(AQ8))-(AS8-N(AV8))+(AN8-AM8-N(AR8))-(AT8-AS8-N(AU8))+(N(AQ8)+N(AR8))-(N(AU8)+N(AV8)))-((BF8-BI8-N(BJ8))-(BL8-N(BO8))+(BG8-BF8-N(BK8))-(BM8-BL8-N(BN8))+(N(BJ8)+N(BK8))-(N(BN8)+N(BO8))))/((AN8+BG8)/2),0) -> 0.081841804 | V8: =IFERROR((AK8-BD8)/((AN8+BG8)/2),0) -> 0.065405967 | W8: =IFERROR((N(AL8)-N(BE8))/((AN8+BG8)/2),0) -> 0.073249359 | X8: =IFERROR((AN8-N(AO8)-AP8)/AN8,0) -> 0.69247147 | Y8: =IF(COUNT(BP8,BQ8,BR8,BS8)=4,IFERROR((AD8-(AK8-BD8))/(AW8-(BD8-BP8))-1,0),0) -> 0.17704164 | Z8: =IF(COUNT(BP8,BQ8,BR8,BS8)=4,IFERROR(AH8/((AN8+BG8)/2)-BA8/((BG8+BR8)/2),0),0) -> 0.022526519 | AA8: =IF(N(AJ8)>0,1,0) -> 0 | AB8: =Inputs!$C$24+Inputs!$C$25*U8+Inputs!$C$26*V8+Inputs!$C$27*W8+Inputs!$C$28*X8+Inputs!$C$29*Y8+Inputs!$C$30*Z8+Inputs!$C$31*AA8 -> -6.1967323 | AD8: 1265.745 | AE8: 1078.945 | AF8: 57.858 | AG8: 6.781 | AH8: 36.5 | AI8: 26.375 | AJ8: n/a | AK8: 161.174 | AL8: 290.927 | AM8: 567.583 | AN8: 708.731 | AO8: 128.072 | AP8: 89.883 | AQ8: n/a | AR8: 2.637 | AS8: 286.642 | AT8: 302.944 | AU8: 5.133 | AV8: 37.208 | AW8: 1078.268 | AX8: 919.954 | AY8: 58.455 | AZ8: 7.898 | BA8: 18.4 | BB8: -14.82 | BC8: n/a | BD8: 118.912 | BE8: 243.597 | BF8: 475.495 | BG8: 583.567 | BH8: 96.712 | BI8: 88.398 | BJ8: n/a | BK8: 2.65 | BL8: 213.45 | BM8: 232.147 | BN8: 7.933 | BO8: 29.195 | BP8: 80.1 | BQ8: 992.391 | BR8: 499.997 | BS8: 38.693
B9: 41729 | C9: 41766 | D9: yes | E9: =Inputs!$C$13+Inputs!$C$14*M9+Inputs!$C$15*N9+Inputs!$C$16*O9+Inputs!$C$17*P9+Inputs!$C$18*Q9+Inputs!$C$19*R9+Inputs!$C$20*S9+Inputs!$C$21*T9 -> -1.9335395 | F9: =EXP(AB9)/(1+EXP(AB9))/Inputs!$C$32 -> 0.5751915 | G9: =IFERROR((AH9-AI9)/((AN9+BG9)/2),"n/a") -> 0.049383443 | H9: =IFERROR(AI9/AH9,"n/a") -> 0.27127775 | I9: =IFERROR(AK9/AD9*365,"n/a") -> 48.800499 | J9: =IFERROR(N(AL9)/AE9*365,"n/a") -> 93.148794 | K9: =IF(E9>Inputs!$C$7,1,0) -> 0 | L9: =IF(F9>Inputs!$C$8,1,0) -> 0 | M9: =IFERROR((AK9/AD9)/(BD9/AW9),1) -> 1.2197727 | N9: =IFERROR(((AW9-AX9)/AW9)/((AD9-AE9)/AD9),1) -> 0.93031852 | O9: =IFERROR((1-(AM9+AO9)/AN9)/(1-(BF9+BH9)/BG9),1) -> 0.70809971 | P9: =IFERROR(AD9/AW9,1) -> 1.2198161 | Q9: =IFERROR((AZ9/(AZ9+BH9))/(AG9/(AG9+AO9)),1) -> 1.5740089 | R9: =IFERROR((AF9/AD9)/(AY9/AW9),1) -> 0.80470568 | S9: =IFERROR((AH9-AI9)/AN9,0) -> 0.044695759 | T9: =IFERROR(((AS9+N(AU9))/AN9)/((BL9+N(BN9))/BG9),1) -> 1.017798 | U9: =IFERROR((((AM9-AP9-N(AQ9))-(AS9-N(AV9))+(AN9-AM9-N(AR9))-(AT9-AS9-N(AU9))+(N(AQ9)+N(AR9))-(N(AU9)+N(AV9)))-((BF9-BI9-N(BJ9))-(BL9-N(BO9))+(BG9-BF9-N(BK9))-(BM9-BL9-N(BN9))+(N(BJ9)+N(BK9))-(N(BN9)+N(BO9))))/((AN9+BG9)/2),0) -> 0.10692238 | V9: =IFERROR((AK9-BD9)/((AN9+BG9)/2),0) -> 0.087868847 | W9: =IFERROR((N(AL9)-N(BE9))/((AN9+BG9)/2),0) -> 0.055569254 | X9: =IFERROR((AN9-N(AO9)-AP9)/AN9,0) -> 0.69326393 | Y9: =IF(COUNT(BP9,BQ9,BR9,BS9)=4,IFERROR((AD9-(AK9-BD9))/(AW9-(BD9-BP9))-1,0),0) -> 0.18909264 | Z9: =IF(COUNT(BP9,BQ9,BR9,BS9)=4,IFERROR(AH9/((AN9+BG9)/2)-BA9/((BG9+BR9)/2),0),0) -> 0.036001943 | AA9: =IF(N(AJ9)>0,1,0) -> 0 | AB9: =Inputs!$C$24+Inputs!$C$25*U9+Inputs!$C$26*V9+Inputs!$C$27*W9+Inputs!$C$28*X9+Inputs!$C$29*Y9+Inputs!$C$30*Z9+Inputs!$C$31*AA9 -> -6.1503442 | AD9: 1361.466 | AE9: 1156.295 | AF9: 58.233 | AG9: 6.525 | AH9: 46.034 | AI9: 12.488 | AJ9: n/a | AK9: 182.028 | AL9: 295.089 | AM9: 610.845 | AN9: 750.541 | AO9: 128.504 | AP9: 101.714 | AQ9: n/a | AR9: 2.637 | AS9: 292.53 | AT9: 308.002 | AU9: 4.433 | AV9: 42.13 | AW9: 1116.124 | AX9: 959.646 | AY9: 59.325 | AZ9: 7.857 | BA9: 18.363 | BB9: 11.008 | BC9: n/a | BD9: 122.339 | BE9: 257.341 | BF9: 499.805 | BG9: 608.052 | BH9: 95.442 | BI9: 93.974 | BJ9: n/a | BK9: 2.65 | BL9: 229.145 | BM9: 245.885 | BN9: 7.233 | BO9: 28.745 | BP9: 100.98 | BQ9: 998.281 | BR9: 548.118 | BS9: 35.074
B10: 41820 | C10: 41897 | D10: yes | E10: =Inputs!$C$13+Inputs!$C$14*M10+Inputs!$C$15*N10+Inputs!$C$16*O10+Inputs!$C$17*P10+Inputs!$C$18*Q10+Inputs!$C$19*R10+Inputs!$C$20*S10+Inputs!$C$21*T10 -> -1.9253139 | F10: =EXP(AB10)/(1+EXP(AB10))/Inputs!$C$32 -> 1.7794389 | G10: =IFERROR((AH10-AI10)/((AN10+BG10)/2),"n/a") -> 0.066666107 | H10: =IFERROR(AI10/AH10,"n/a") -> 0.12072308 | I10: =IFERROR(AK10/AD10*365,"n/a") -> 52.923435 | J10: =IFERROR(N(AL10)/AE10*365,"n/a") -> 92.844083 | K10: =IF(E10>Inputs!$C$7,1,0) -> 0 | L10: =IF(F10>Inputs!$C$8,1,0) -> 0 | M10: =IFERROR((AK10/AD10)/(BD10/AW10),1) -> 1.1287422 | N10: =IFERROR(((AW10-AX10)/AW10)/((AD10-AE10)/AD10),1) -> 0.8955808 | O10: =IFERROR((1-(AM10+AO10)/AN10)/(1-(BF10+BH10)/BG10),1) -> 0.70354317 | P10: =IFERROR(AD10/AW10,1) -> 1.262043 | Q10: =IFERROR((AZ10/(AZ10+BH10))/(AG10/(AG10+AO10)),1) -> 1.6251926 | R10: =IFERROR((AF10/AD10)/(AY10/AW10),1) -> 0.83827042 | S10: =IFERROR((AH10-AI10)/AN10,0) -> 0.059798449 | T10: =IFERROR(((AS10+N(AU10))/AN10)/((BL10+N(BN10))/BG10),1) -> 1.0064489 | U10: =IFERROR((((AM10-AP10-N(AQ10))-(AS10-N(AV10))+(AN10-AM10-N(AR10))-(AT10-AS10-N(AU10))+(N(AQ10)+N(AR10))-(N(AU10)+N(AV10)))-((BF10-BI10-N(BJ10))-(BL10-N(BO10))+(BG10-BF10-N(BK10))-(BM10-BL10-N(BN10))+(N(BJ10)+N(BK10))-(N(BN10)+N(BO10))))/((AN10+BG10)/2),0) -> 0.12834125 | V10: =IFERROR((AK10-BD10)/((AN10+BG10)/2),0) -> 0.088756543 | W10: =IFERROR((N(AL10)-N(BE10))/((AN10+BG10)/2),0) -> 0.086333161 | X10: =IFERROR((AN10-N(AO10)-AP10)/AN10,0) -> 0.7143616 | Y10: =IF(COUNT(BP10,BQ10,BR10,BS10)=4,IFERROR((AD10-(AK10-BD10))/(AW10-(BD10-BP10))-1,0),0) -> 0.25875174 | Z10: =IF(COUNT(BP10,BQ10,BR10,BS10)=4,IFERROR(AH10/((AN10+BG10)/2)-BA10/((BG10+BR10)/2),0),0) -> 0.040974476 | AA10: =IF(N(AJ10)>0,1,0) -> 1 | AB10: =Inputs!$C$24+Inputs!$C$25*U10+Inputs!$C$26*V10+Inputs!$C$27*W10+Inputs!$C$28*X10+Inputs!$C$29*Y10+Inputs!$C$30*Z10+Inputs!$C$31*AA10 -> -5.0165187 | AD10: 1467.202 | AE10: 1241.657 | AF10: 61.029 | AG10: 6.364 | AH10: 54.157 | AI10: 6.538 | AJ10: 17.354 | AK10: 212.738 | AL10: 315.837 | AM10: 654.081 | AN10: 796.325 | AO10: 130.589 | AP10: 96.872 | AQ10: n/a | AR10: 2.647 | AS10: 310.886 | AT10: 327.094 | AU10: 3.733 | AV10: 42.554 | AW10: 1162.561 | AX10: 1002.508 | AY10: 57.687 | AZ10: 7.835 | BA10: 21.279 | BB10: 13.583 | BC10: 20.641 | BD10: 149.34 | BE10: 254.17 | BF10: 523.192 | BG10: 632.257 | BH10: 95.912 | BI10: 93.038 | BJ10: n/a | BK10: 2.637 | BL10: 241.664 | BM10: 258.533 | BN10: 6.533 | BO10: 28.638 | BP10: 102.014 | BQ10: 1013.874 | BR10: 589.103 | BS10: 29.853
B11: 41912 | C11: 41949 | D11: yes | E11: =Inputs!$C$13+Inputs!$C$14*M11+Inputs!$C$15*N11+Inputs!$C$16*O11+Inputs!$C$17*P11+Inputs!$C$18*Q11+Inputs!$C$19*R11+Inputs!$C$20*S11+Inputs!$C$21*T11 -> -1.9654574 | F11: =EXP(AB11)/(1+EXP(AB11))/Inputs!$C$32 -> 0.64328928 | G11: =IFERROR((AH11-AI11)/((AN11+BG11)/2),"n/a") -> 0.071094767 | H11: =IFERROR(AI11/AH11,"n/a") -> 0.2269277 | I11: =IFERROR(AK11/AD11*365,"n/a") -> 44.298905 | J11: =IFERROR(N(AL11)/AE11*365,"n/a") -> 92.09956 | K11: =IF(E11>Inputs!$C$7,1,0) -> 0 | L11: =IF(F11>Inputs!$C$8,1,0) -> 0 | M11: =IFERROR((AK11/AD11)/(BD11/AW11),1) -> 1.087201 | N11: =IFERROR(((AW11-AX11)/AW11)/((AD11-AE11)/AD11),1) -> 0.92421923 | O11: =IFERROR((1-(AM11+AO11)/AN11)/(1-(BF11+BH11)/BG11),1) -> 0.52380486 | P11: =IFERROR(AD11/AW11,1) -> 1.3336231 | Q11: =IFERROR((AZ11/(AZ11+BH11))/(AG11/(AG11+AO11)),1) -> 1.4342584 | R11: =IFERROR((AF11/AD11)/(AY11/AW11),1) -> 0.82189431 | S11: =IFERROR((AH11-AI11)/AN11,0) -> 0.062834204 | T11: =IFERROR(((AS11+N(AU11))/AN11)/((BL11+N(BN11))/BG11),1) -> 1.0166797 | U11: =IFERROR((((AM11-AP11-N(AQ11))-(AS11-N(AV11))+(AN11-AM11-N(AR11))-(AT11-AS11-N(AU11))+(N(AQ11)+N(AR11))-(N(AU11)+N(AV11)))-((BF11-BI11-N(BJ11))-(BL11-N(BO11))+(BG11-BF11-N(BK11))-(BM11-BL11-N(BN11))+(N(BJ11)+N(BK11))-(N(BN11)+N(BO11))))/((AN11+BG11)/2),0) -> 0.14542434 | V11: =IFERROR((AK11-BD11)/((AN11+BG11)/2),0) -> 0.08239201 | W11: =IFERROR((N(AL11)-N(BE11))/((AN11+BG11)/2),0) -> 0.11916201 | X11: =IFERROR((AN11-N(AO11)-AP11)/AN11,0) -> 0.69746884 | Y11: =IF(COUNT(BP11,BQ11,BR11,BS11)=4,IFERROR((AD11-(AK11-BD11))/(AW11-(BD11-BP11))-1,0),0) -> 0.3065384 | Z11: =IF(COUNT(BP11,BQ11,BR11,BS11)=4,IFERROR(AH11/((AN11+BG11)/2)-BA11/((BG11+BR11)/2),0),0) -> 0.045256832 | AA11: =IF(N(AJ11)>0,1,0) -> 0 | AB11: =Inputs!$C$24+Inputs!$C$25*U11+Inputs!$C$26*V11+Inputs!$C$27*W11+Inputs!$C$28*X11+Inputs!$C$29*Y11+Inputs!$C$30*Z11+Inputs!$C$31*AA11 -> -6.0382002 | AD11: 1601.508 | AE11: 1353.562 | AF11: 62.574 | AG11: 6.818 | AH11: 67.321 | AI11: 15.277 | AJ11: n/a | AK11: 194.37 | AL11: 341.541 | AM11: 685.102 | AN11: 828.275 | AO11: 133.067 | AP11: 117.512 | AQ11: n/a | AR11: 2.647 | AS11: 313.954 | AT11: 329.801 | AU11: 3.033 | AV11: 34.446 | AW11: 1200.87 | AX11: 1029.04 | AY11: 57.088 | AZ11: 7.273 | BA11: 28.079 | BB11: 58.444 | BC11: n/a | BD11: 134.056 | BE11: 254.31 | BF11: 524.222 | BG11: 635.799 | BH11: 96.767 | BI11: 111.458 | BJ11: n/a | BK11: 2.637 | BL11: 218.283 | BM11: 249.835 | BN11: 21.05 | BO11: 13.699 | BP11: 112.787 | BQ11: 1036.696 | BR11: 566.545 | BS11: 22.26
B12: 42004 | C12: 42044 | D12: yes | E12: =Inputs!$C$13+Inputs!$C$14*M12+Inputs!$C$15*N12+Inputs!$C$16*O12+Inputs!$C$17*P12+Inputs!$C$18*Q12+Inputs!$C$19*R12+Inputs!$C$20*S12+Inputs!$C$21*T12 -> -1.6070338 | F12: =EXP(AB12)/(1+EXP(AB12))/Inputs!$C$32 -> 0.84437683 | G12: =IFERROR((AH12-AI12)/((AN12+BG12)/2),"n/a") -> 0.12869425 | H12: =IFERROR(AI12/AH12,"n/a") -> -0.24104754 | I12: =IFERROR(AK12/AD12*365,"n/a") -> 54.031759 | J12: =IFERROR(N(AL12)/AE12*365,"n/a") -> 101.54633 | K12: =IF(E12>Inputs!$C$7,1,0) -> 1 | L12: =IF(F12>Inputs!$C$8,1,0) -> 0 | M12: =IFERROR((AK12/AD12)/(BD12/AW12),1) -> 1.1625389 | N12: =IFERROR(((AW12-AX12)/AW12)/((AD12-AE12)/AD12),1) -> 0.93036329 | O12: =IFERROR((1-(AM12+AO12)/AN12)/(1-(BF12+BH12)/BG12),1) -> 0.61670387 | P12: =IFERROR(AD12/AW12,1) -> 1.3811313 | Q12: =IFERROR((AZ12/(AZ12+BH12))/(AG12/(AG12+AO12)),1) -> 1.0344482 | R12: =IFERROR((AF12/AD12)/(AY12/AW12),1) -> 0.80360915 | S12: =IFERROR((AH12-AI12)/AN12,0) -> 0.11312017 | T12: =IFERROR(((AS12+N(AU12))/AN12)/((BL12+N(BN12))/BG12),1) -> 0.9753788 | U12: =IFERROR((((AM12-AP12-N(AQ12))-(AS12-N(AV12))+(AN12-AM12-N(AR12))-(AT12-AS12-N(AU12))+(N(AQ12)+N(AR12))-(N(AU12)+N(AV12)))-((BF12-BI12-N(BJ12))-(BL12-N(BO12))+(BG12-BF12-N(BK12))-(BM12-BL12-N(BN12))+(N(BJ12)+N(BK12))-(N(BN12)+N(BO12))))/((AN12+BG12)/2),0) -> 0.17778256 | V12: =IFERROR((AK12-BD12)/((AN12+BG12)/2),0) -> 0.11876343 | W12: =IFERROR((N(AL12)-N(BE12))/((AN12+BG12)/2),0) -> 0.14391047 | X12: =IFERROR((AN12-N(AO12)-AP12)/AN12,0) -> 0.75844803 | Y12: =IF(COUNT(BP12,BQ12,BR12,BS12)=4,IFERROR((AD12-(AK12-BD12))/(AW12-(BD12-BP12))-1,0),0) -> 0.34905838 | Z12: =IF(COUNT(BP12,BQ12,BR12,BS12)=4,IFERROR(AH12/((AN12+BG12)/2)-BA12/((BG12+BR12)/2),0),0) -> 0.047209561 | AA12: =IF(N(AJ12)>0,1,0) -> 0 | AB12: =Inputs!$C$24+Inputs!$C$25*U12+Inputs!$C$26*V12+Inputs!$C$27*W12+Inputs!$C$28*X12+Inputs!$C$29*Y12+Inputs!$C$30*Z12+Inputs!$C$31*AA12 -> -5.7654498 | AD12: 1748.16 | AE12: 1470.854 | AF12: 64.216 | AG12: 7.289 | AH12: 85.228 | AI12: -20.544 | AJ12: n/a | AK12: 258.784 | AL12: 409.205 | AM12: 781.742 | AN12: 935.041 | AO12: 142.66 | AP12: 83.201 | AQ12: n/a | AR12: 2.647 | AS12: 373.133 | AT12: 389.819 | AU12: 2.333 | AV12: 33.459 | AW12: 1265.745 | AX12: 1078.945 | AY12: 57.858 | AZ12: 6.781 | BA12: 36.5 | BB12: 26.375 | BC12: n/a | BD12: 161.174 | BE12: 290.927 | BF12: 567.583 | BG12: 708.731 | BH12: 128.072 | BI12: 89.883 | BJ12: n/a | BK12: 2.637 | BL12: 286.642 | BM12: 302.944 | BN12: 5.133 | BO12: 37.208 | BP12: 118.912 | BQ12: 1078.268 | BR12: 583.567 | BS12: 18.4
B13: 42094 | C13: 42131 | D13: yes | E13: =Inputs!$C$13+Inputs!$C$14*M13+Inputs!$C$15*N13+Inputs!$C$16*O13+Inputs!$C$17*P13+Inputs!$C$18*Q13+Inputs!$C$19*R13+Inputs!$C$20*S13+Inputs!$C$21*T13 -> -1.8738848 | F13: =EXP(AB13)/(1+EXP(AB13))/Inputs!$C$32 -> 0.67138426 | G13: =IFERROR((AH13-AI13)/((AN13+BG13)/2),"n/a") -> 0.10351376 | H13: =IFERROR(AI13/AH13,"n/a") -> 0.034107513 | I13: =IFERROR(AK13/AD13*365,"n/a") -> 43.816889 | J13: =IFERROR(N(AL13)/AE13*365,"n/a") -> 101.42864 | K13: =IF(E13>Inputs!$C$7,1,0) -> 0 | L13: =IF(F13>Inputs!$C$8,1,0) -> 0 | M13: =IFERROR((AK13/AD13)/(BD13/AW13),1) -> 0.89787789 | N13: =IFERROR(((AW13-AX13)/AW13)/((AD13-AE13)/AD13),1) -> 0.93691287 | O13: =IFERROR((1-(AM13+AO13)/AN13)/(1-(BF13+BH13)/BG13),1) -> 0.86372671 | P13: =IFERROR(AD13/AW13,1) -> 1.3556196 | Q13: =IFERROR((AZ13/(AZ13+BH13))/(AG13/(AG13+AO13)),1) -> 1.0100902 | R13: =IFERROR((AF13/AD13)/(AY13/AW13),1) -> 0.8718322 | S13: =IFERROR((AH13-AI13)/AN13,0) -> 0.09218064 | T13: =IFERROR(((AS13+N(AU13))/AN13)/((BL13+N(BN13))/BG13),1) -> 0.94892709 | U13: =IFERROR((((AM13-AP13-N(AQ13))-(AS13-N(AV13))+(AN13-AM13-N(AR13))-(AT13-AS13-N(AU13))+(N(AQ13)+N(AR13))-(N(AU13)+N(AV13)))-((BF13-BI13-N(BJ13))-(BL13-N(BO13))+(BG13-BF13-N(BK13))-(BM13-BL13-N(BN13))+(N(BJ13)+N(BK13))-(N(BN13)+N(BO13))))/((AN13+BG13)/2),0) -> 0.1585543 | V13: =IFERROR((AK13-BD13)/((AN13+BG13)/2),0) -> 0.046196849 | W13: =IFERROR((N(AL13)-N(BE13))/((AN13+BG13)/2),0) -> 0.15809856 | X13: =IFERROR((AN13-N(AO13)-AP13)/AN13,0) -> 0.72675582 | Y13: =IF(COUNT(BP13,BQ13,BR13,BS13)=4,IFERROR((AD13-(AK13-BD13))/(AW13-(BD13-BP13))-1,0),0) -> 0.3874089 | Z13: =IF(COUNT(BP13,BQ13,BR13,BS13)=4,IFERROR(AH13/((AN13+BG13)/2)-BA13/((BG13+BR13)/2),0),0) -> 0.039401857 | AA13: =IF(N(AJ13)>0,1,0) -> 0 | AB13: =Inputs!$C$24+Inputs!$C$25*U13+Inputs!$C$26*V13+Inputs!$C$27*W13+Inputs!$C$28*X13+Inputs!$C$29*Y13+Inputs!$C$30*Z13+Inputs!$C$31*AA13 -> -5.9953489 | AD13: 1845.63 | AE13: 1548.768 | AF13: 68.824 | AG13: 7.704 | AH13: 91.71 | AI13: 3.128 | AJ13: n/a | AK13: 221.561 | AL13: 430.382 | AM13: 795.252 | AN13: 960.961 | AO13: 153.332 | AP13: 109.245 | AQ13: n/a | AR13: 2.647 | AS13: 359.167 | AT13: 375.208 | AU13: 1.633 | AV13: 44.836 | AW13: 1361.466 | AX13: 1156.295 | AY13: 58.233 | AZ13: 6.525 | BA13: 46.034 | BB13: 12.488 | BC13: n/a | BD13: 182.028 | BE13: 295.089 | BF13: 610.845 | BG13: 750.541 | BH13: 128.504 | BI13: 101.714 | BJ13: n/a | BK13: 2.637 | BL13: 292.53 | BM13: 308.002 | BN13: 4.433 | BO13: 42.13 | BP13: 122.339 | BQ13: 1116.124 | BR13: 608.052 | BS13: 18.363
B14: 42185 | C14: 42257 | D14: yes | E14: =Inputs!$C$13+Inputs!$C$14*M14+Inputs!$C$15*N14+Inputs!$C$16*O14+Inputs!$C$17*P14+Inputs!$C$18*Q14+Inputs!$C$19*R14+Inputs!$C$20*S14+Inputs!$C$21*T14 -> -1.5400437 | F14: =EXP(AB14)/(1+EXP(AB14))/Inputs!$C$32 -> 2.3889361 | G14: =IFERROR((AH14-AI14)/((AN14+BG14)/2),"n/a") -> 0.15534315 | H14: =IFERROR(AI14/AH14,"n/a") -> -0.4381964 | I14: =IFERROR(AK14/AD14*365,"n/a") -> 59.134929 | J14: =IFERROR(N(AL14)/AE14*365,"n/a") -> 101.24634 | K14: =IF(E14>Inputs!$C$7,1,0) -> 1 | L14: =IF(F14>Inputs!$C$8,1,0) -> 1 | M14: =IFERROR((AK14/AD14)/(BD14/AW14),1) -> 1.1173676 | N14: =IFERROR(((AW14-AX14)/AW14)/((AD14-AE14)/AD14),1) -> 0.95583954 | O14: =IFERROR((1-(AM14+AO14)/AN14)/(1-(BF14+BH14)/BG14),1) -> 0.7746501 | P14: =IFERROR(AD14/AW14,1) -> 1.3571103 | Q14: =IFERROR((AZ14/(AZ14+BH14))/(AG14/(AG14+AO14)),1) -> 0.97799816 | R14: =IFERROR((AF14/AD14)/(AY14/AW14),1) -> 0.88414961 | S14: =IFERROR((AH14-AI14)/AN14,0) -> 0.13442631 | T14: =IFERROR(((AS14+N(AU14))/AN14)/((BL14+N(BN14))/BG14),1) -> 1.0568287 | U14: =IFERROR((((AM14-AP14-N(AQ14))-(AS14-N(AV14))+(AN14-AM14-N(AR14))-(AT14-AS14-N(AU14))+(N(AQ14)+N(AR14))-(N(AU14)+N(AV14)))-((BF14-BI14-N(BJ14))-(BL14-N(BO14))+(BG14-BF14-N(BK14))-(BM14-BL14-N(BN14))+(N(BJ14)+N(BK14))-(N(BN14)+N(BO14))))/((AN14+BG14)/2),0) -> 0.16041702 | V14: =IFERROR((AK14-BD14)/((AN14+BG14)/2),0) -> 0.11648801 | W14: =IFERROR((N(AL14)-N(BE14))/((AN14+BG14)/2),0) -> 0.15657 | X14: =IFERROR((AN14-N(AO14)-AP14)/AN14,0) -> 0.76282082 | Y14: =IF(COUNT(BP14,BQ14,BR14,BS14)=4,IFERROR((AD14-(AK14-BD14))/(AW14-(BD14-BP14))-1,0),0) -> 0.34014364 | Z14: =IF(COUNT(BP14,BQ14,BR14,BS14)=4,IFERROR(AH14/((AN14+BG14)/2)-BA14/((BG14+BR14)/2),0),0) -> 0.032193235 | AA14: =IF(N(AJ14)>0,1,0) -> 1 | AB14: =Inputs!$C$24+Inputs!$C$25*U14+Inputs!$C$26*V14+Inputs!$C$27*W14+Inputs!$C$28*X14+Inputs!$C$29*Y14+Inputs!$C$30*Z14+Inputs!$C$31*AA14 -> -4.719696 | AD14: 1991.155 | AE14: 1670.924 | AF14: 73.228 | AG14: 8.133 | AH14: 101.863 | AI14: -44.636 | AJ14: 84.9 | AK14: 322.594 | AL14: 463.493 | AM14: 914.415 | AN14: 1089.809 | AO14: 163.038 | AP14: 95.442 | AQ14: n/a | AR14: 2.633 | AS14: 454.107 | AT14: 470.724 | AU14: 0.933 | AV14: 93.479 | AW14: 1467.202 | AX14: 1241.657 | AY14: 61.029 | AZ14: 6.364 | BA14: 54.157 | BB14: 6.538 | BC14: 17.354 | BD14: 212.738 | BE14: 315.837 | BF14: 654.081 | BG14: 796.325 | BH14: 130.589 | BI14: 96.872 | BJ14: n/a | BK14: 2.647 | BL14: 310.886 | BM14: 327.094 | BN14: 3.733 | BO14: 42.554 | BP14: 149.34 | BQ14: 1162.561 | BR14: 632.257 | BS14: 21.279
B15: 42277 | C15: 42324 | D15: yes | E15: =Inputs!$C$13+Inputs!$C$14*M15+Inputs!$C$15*N15+Inputs!$C$16*O15+Inputs!$C$17*P15+Inputs!$C$18*Q15+Inputs!$C$19*R15+Inputs!$C$20*S15+Inputs!$C$21*T15 -> -1.3881632 | F15: =EXP(AB15)/(1+EXP(AB15))/Inputs!$C$32 -> 2.1719029 | G15: =IFERROR((AH15-AI15)/((AN15+BG15)/2),"n/a") -> 0.15293714 | H15: =IFERROR(AI15/AH15,"n/a") -> -0.54251893 | I15: =IFERROR(AK15/AD15*365,"n/a") -> 52.447903 | J15: =IFERROR(N(AL15)/AE15*365,"n/a") -> 96.54891 | K15: =IF(E15>Inputs!$C$7,1,0) -> 1 | L15: =IF(F15>Inputs!$C$8,1,0) -> 1 | M15: =IFERROR((AK15/AD15)/(BD15/AW15),1) -> 1.1839549 | N15: =IFERROR(((AW15-AX15)/AW15)/((AD15-AE15)/AD15),1) -> 0.99019483 | O15: =IFERROR((1-(AM15+AO15)/AN15)/(1-(BF15+BH15)/BG15),1) -> 1.105623 | P15: =IFERROR(AD15/AW15,1) -> 1.2909402 | Q15: =IFERROR((AZ15/(AZ15+BH15))/(AG15/(AG15+AO15)),1) -> 0.96082416 | R15: =IFERROR((AF15/AD15)/(AY15/AW15),1) -> 0.9856363 | S15: =IFERROR((AH15-AI15)/AN15,0) -> 0.13500624 | T15: =IFERROR(((AS15+N(AU15))/AN15)/((BL15+N(BN15))/BG15),1) -> 1.0124601 | U15: =IFERROR((((AM15-AP15-N(AQ15))-(AS15-N(AV15))+(AN15-AM15-N(AR15))-(AT15-AS15-N(AU15))+(N(AQ15)+N(AR15))-(N(AU15)+N(AV15)))-((BF15-BI15-N(BJ15))-(BL15-N(BO15))+(BG15-BF15-N(BK15))-(BM15-BL15-N(BN15))+(N(BJ15)+N(BK15))-(N(BN15)+N(BO15))))/((AN15+BG15)/2),0) -> 0.15312873 | V15: =IFERROR((AK15-BD15)/((AN15+BG15)/2),0) -> 0.10753289 | W15: =IFERROR((N(AL15)-N(BE15))/((AN15+BG15)/2),0) -> 0.12545923 | X15: =IFERROR((AN15-N(AO15)-AP15)/AN15,0) -> 0.74117711 | Y15: =IF(COUNT(BP15,BQ15,BR15,BS15)=4,IFERROR((AD15-(AK15-BD15))/(AW15-(BD15-BP15))-1,0),0) -> 0.27481874 | Z15: =IF(COUNT(BP15,BQ15,BR15,BS15)=4,IFERROR(AH15/((AN15+BG15)/2)-BA15/((BG15+BR15)/2),0),0) -> 0.0071837254 | AA15: =IF(N(AJ15)>0,1,0) -> 1 | AB15: =Inputs!$C$24+Inputs!$C$25*U15+Inputs!$C$26*V15+Inputs!$C$27*W15+Inputs!$C$28*X15+Inputs!$C$29*Y15+Inputs!$C$30*Z15+Inputs!$C$31*AA15 -> -4.8157503 | AD15: 2067.451 | AE15: 1744.198 | AF15: 79.619 | AG15: 9.039 | AH15: 94.699 | AI15: -51.376 | AJ15: 89.6 | AK15: 297.078 | AL15: 461.371 | AM15: 898.242 | AN15: 1081.987 | AO15: 169.149 | AP15: 110.894 | AQ15: n/a | AR15: 2.633 | AS15: 419.011 | AT15: 443.873 | AU15: 0.233 | AV15: 94.574 | AW15: 1601.508 | AX15: 1353.562 | AY15: 62.574 | AZ15: 6.818 | BA15: 67.321 | BB15: 15.277 | BC15: n/a | BD15: 194.37 | BE15: 341.541 | BF15: 685.102 | BG15: 828.275 | BH15: 133.067 | BI15: 117.512 | BJ15: n/a | BK15: 2.647 | BL15: 313.954 | BM15: 329.801 | BN15: 3.033 | BO15: 34.446 | BP15: 134.056 | BQ15: 1200.87 | BR15: 635.799 | BS15: 28.079
B16: 42369 | C16: 42404 | D16: yes | E16: =Inputs!$C$13+Inputs!$C$14*M16+Inputs!$C$15*N16+Inputs!$C$16*O16+Inputs!$C$17*P16+Inputs!$C$18*Q16+Inputs!$C$19*R16+Inputs!$C$20*S16+Inputs!$C$21*T16 -> -1.9403519 | F16: =EXP(AB16)/(1+EXP(AB16))/Inputs!$C$32 -> 1.573808 | G16: =IFERROR((AH16-AI16)/((AN16+BG16)/2),"n/a") -> 0.044342215 | H16: =IFERROR(AI16/AH16,"n/a") -> 0.51935891 | I16: =IFERROR(AK16/AD16*365,"n/a") -> 52.044199 | J16: =IFERROR(N(AL16)/AE16*365,"n/a") -> 95.5657 | K16: =IF(E16>Inputs!$C$7,1,0) -> 0 | L16: =IF(F16>Inputs!$C$8,1,0) -> 0 | M16: =IFERROR((AK16/AD16)/(BD16/AW16),1) -> 0.96321496 | N16: =IFERROR(((AW16-AX16)/AW16)/((AD16-AE16)/AD16),1) -> 1.0126221 | O16: =IFERROR((1-(AM16+AO16)/AN16)/(1-(BF16+BH16)/BG16),1) -> 1.4589571 | P16: =IFERROR(AD16/AW16,1) -> 1.2604115 | Q16: =IFERROR((AZ16/(AZ16+BH16))/(AG16/(AG16+AO16)),1) -> 0.87068183 | R16: =IFERROR((AF16/AD16)/(AY16/AW16),1) -> 1.1179958 | S16: =IFERROR((AH16-AI16)/AN16,0) -> 0.039553494 | T16: =IFERROR(((AS16+N(AU16))/AN16)/((BL16+N(BN16))/BG16),1) -> 1.0023968 | U16: =IFERROR((((AM16-AP16-N(AQ16))-(AS16-N(AV16))+(AN16-AM16-N(AR16))-(AT16-AS16-N(AU16))+(N(AQ16)+N(AR16))-(N(AU16)+N(AV16)))-((BF16-BI16-N(BJ16))-(BL16-N(BO16))+(BG16-BF16-N(BK16))-(BM16-BL16-N(BN16))+(N(BJ16)+N(BK16))-(N(BN16)+N(BO16))))/((AN16+BG16)/2),0) -> 0.043460503 | V16: =IFERROR((AK16-BD16)/((AN16+BG16)/2),0) -> 0.052068005 | W16: =IFERROR((N(AL16)-N(BE16))/((AN16+BG16)/2),0) -> 0.072685776 | X16: =IFERROR((AN16-N(AO16)-AP16)/AN16,0) -> 0.71233182 | Y16: =IF(COUNT(BP16,BQ16,BR16,BS16)=4,IFERROR((AD16-(AK16-BD16))/(AW16-(BD16-BP16))-1,0),0) -> 0.30138984 | Z16: =IF(COUNT(BP16,BQ16,BR16,BS16)=4,IFERROR(AH16/((AN16+BG16)/2)-BA16/((BG16+BR16)/2),0),0) -> -0.011441682 | AA16: =IF(N(AJ16)>0,1,0) -> 1 | AB16: =Inputs!$C$24+Inputs!$C$25*U16+Inputs!$C$26*V16+Inputs!$C$27*W16+Inputs!$C$28*X16+Inputs!$C$29*Y16+Inputs!$C$30*Z16+Inputs!$C$31*AA16 -> -5.1400842 | AD16: 2203.401 | AE16: 1858.238 | AF16: 90.489 | AG16: 10.241 | AH16: 98.146 | AI16: 50.973 | AJ16: 94.1 | AK16: 314.176 | AL16: 486.531 | AM16: 999.648 | AN16: 1192.638 | AO16: 173.192 | AP16: 169.892 | AQ16: n/a | AR16: 2.633 | AS16: 480.052 | AT16: 514.49 | AU16: 0 | AV16: 94.233 | AW16: 1748.16 | AX16: 1470.854 | AY16: 64.216 | AZ16: 7.289 | BA16: 85.228 | BB16: -20.544 | BC16: n/a | BD16: 258.784 | BE16: 409.205 | BF16: 781.742 | BG16: 935.041 | BH16: 142.66 | BI16: 83.201 | BJ16: n/a | BK16: 2.647 | BL16: 373.133 | BM16: 389.819 | BN16: 2.333 | BO16: 33.459 | BP16: 161.174 | BQ16: 1265.745 | BR16: 708.731 | BS16: 36.5
B17: 42460 | C17: 42496 | D17: yes | E17: =Inputs!$C$13+Inputs!$C$14*M17+Inputs!$C$15*N17+Inputs!$C$16*O17+Inputs!$C$17*P17+Inputs!$C$18*Q17+Inputs!$C$19*R17+Inputs!$C$20*S17+Inputs!$C$21*T17 -> -1.9641548 | F17: =EXP(AB17)/(1+EXP(AB17))/Inputs!$C$32 -> 1.5161993 | G17: =IFERROR((AH17-AI17)/((AN17+BG17)/2),"n/a") -> 0.049135557 | H17: =IFERROR(AI17/AH17,"n/a") -> 0.42643212 | I17: =IFERROR(AK17/AD17*365,"n/a") -> 46.042855 | J17: =IFERROR(N(AL17)/AE17*365,"n/a") -> 91.235818 | K17: =IF(E17>Inputs!$C$7,1,0) -> 0 | L17: =IF(F17>Inputs!$C$8,1,0) -> 0 | M17: =IFERROR((AK17/AD17)/(BD17/AW17),1) -> 1.0508016 | N17: =IFERROR(((AW17-AX17)/AW17)/((AD17-AE17)/AD17),1) -> 1.0483586 | O17: =IFERROR((1-(AM17+AO17)/AN17)/(1-(BF17+BH17)/BG17),1) -> 1.1753479 | P17: =IFERROR(AD17/AW17,1) -> 1.2271674 | Q17: =IFERROR((AZ17/(AZ17+BH17))/(AG17/(AG17+AO17)),1) -> 0.77973348 | R17: =IFERROR((AF17/AD17)/(AY17/AW17),1) -> 1.1142741 | S17: =IFERROR((AH17-AI17)/AN17,0) -> 0.044556279 | T17: =IFERROR(((AS17+N(AU17))/AN17)/((BL17+N(BN17))/BG17),1) -> 0.97979353 | U17: =IFERROR((((AM17-AP17-N(AQ17))-(AS17-N(AV17))+(AN17-AM17-N(AR17))-(AT17-AS17-N(AU17))+(N(AQ17)+N(AR17))-(N(AU17)+N(AV17)))-((BF17-BI17-N(BJ17))-(BL17-N(BO17))+(BG17-BF17-N(BK17))-(BM17-BL17-N(BN17))+(N(BJ17)+N(BK17))-(N(BN17)+N(BO17))))/((AN17+BG17)/2),0) -> 0.052367005 | V17: =IFERROR((AK17-BD17)/((AN17+BG17)/2),0) -> 0.059889621 | W17: =IFERROR((N(AL17)-N(BE17))/((AN17+BG17)/2),0) -> 0.045651084 | X17: =IFERROR((AN17-N(AO17)-AP17)/AN17,0) -> 0.69856567 | Y17: =IF(COUNT(BP17,BQ17,BR17,BS17)=4,IFERROR((AD17-(AK17-BD17))/(AW17-(BD17-BP17))-1,0),0) -> 0.21851318 | Z17: =IF(COUNT(BP17,BQ17,BR17,BS17)=4,IFERROR(AH17/((AN17+BG17)/2)-BA17/((BG17+BR17)/2),0),0) -> -0.021502516 | AA17: =IF(N(AJ17)>0,1,0) -> 1 | AB17: =Inputs!$C$24+Inputs!$C$25*U17+Inputs!$C$26*V17+Inputs!$C$27*W17+Inputs!$C$28*X17+Inputs!$C$29*Y17+Inputs!$C$30*Z17+Inputs!$C$31*AA17 -> -5.17759 | AD17: 2264.897 | AE17: 1917.402 | AF17: 94.11 | AG17: 11.741 | AH17: 91.752 | AI17: 39.126 | AJ17: 72.6 | AK17: 285.705 | AL17: 479.276 | AM17: 983.611 | AN17: 1181.113 | AO17: 179.622 | AP17: 176.406 | AQ17: n/a | AR17: 2.633 | AS17: 434.497 | AT17: 472.112 | AU17: 0 | AV17: 93.795 | AW17: 1845.63 | AX17: 1548.768 | AY17: 68.824 | AZ17: 7.704 | BA17: 91.71 | BB17: 3.128 | BC17: n/a | BD17: 221.561 | BE17: 430.382 | BF17: 795.252 | BG17: 960.961 | BH17: 153.332 | BI17: 109.245 | BJ17: n/a | BK17: 2.647 | BL17: 359.167 | BM17: 375.208 | BN17: 1.633 | BO17: 44.836 | BP17: 182.028 | BQ17: 1361.466 | BR17: 750.541 | BS17: 46.034
B18: 42551 | C18: 42608 | D18: yes | E18: =Inputs!$C$13+Inputs!$C$14*M18+Inputs!$C$15*N18+Inputs!$C$16*O18+Inputs!$C$17*P18+Inputs!$C$18*Q18+Inputs!$C$19*R18+Inputs!$C$20*S18+Inputs!$C$21*T18 -> -1.8707052 | F18: =EXP(AB18)/(1+EXP(AB18))/Inputs!$C$32 -> 1.0831999 | G18: =IFERROR((AH18-AI18)/((AN18+BG18)/2),"n/a") -> -0.031469237 | H18: =IFERROR(AI18/AH18,"n/a") -> 1.4927452 | I18: =IFERROR(AK18/AD18*365,"n/a") -> 47.600989 | J18: =IFERROR(N(AL18)/AE18*365,"n/a") -> 86.981701 | K18: =IF(E18>Inputs!$C$7,1,0) -> 0 | L18: =IF(F18>Inputs!$C$8,1,0) -> 0 | M18: =IFERROR((AK18/AD18)/(BD18/AW18),1) -> 0.80495553 | N18: =IFERROR(((AW18-AX18)/AW18)/((AD18-AE18)/AD18),1) -> 1.0748011 | O18: =IFERROR((1-(AM18+AO18)/AN18)/(1-(BF18+BH18)/BG18),1) -> 3.0002344 | P18: =IFERROR(AD18/AW18,1) -> 1.1127074 | Q18: =IFERROR((AZ18/(AZ18+BH18))/(AG18/(AG18+AO18)),1) -> 0.71986655 | R18: =IFERROR((AF18/AD18)/(AY18/AW18),1) -> 1.2356326 | S18: =IFERROR((AH18-AI18)/AN18,0) -> -0.030446122 | T18: =IFERROR(((AS18+N(AU18))/AN18)/((BL18+N(BN18))/BG18),1) -> 0.82931936 | U18: =IFERROR((((AM18-AP18-N(AQ18))-(AS18-N(AV18))+(AN18-AM18-N(AR18))-(AT18-AS18-N(AU18))+(N(AQ18)+N(AR18))-(N(AU18)+N(AV18)))-((BF18-BI18-N(BJ18))-(BL18-N(BO18))+(BG18-BF18-N(BK18))-(BM18-BL18-N(BN18))+(N(BJ18)+N(BK18))-(N(BN18)+N(BO18))))/((AN18+BG18)/2),0) -> 0.01487269 | V18: =IFERROR((AK18-BD18)/((AN18+BG18)/2),0) -> -0.029842038 | W18: =IFERROR((N(AL18)-N(BE18))/((AN18+BG18)/2),0) -> -0.012869506 | X18: =IFERROR((AN18-N(AO18)-AP18)/AN18,0) -> 0.68349949 | Y18: =IF(COUNT(BP18,BQ18,BR18,BS18)=4,IFERROR((AD18-(AK18-BD18))/(AW18-(BD18-BP18))-1,0),0) -> 0.19557072 | Z18: =IF(COUNT(BP18,BQ18,BR18,BS18)=4,IFERROR(AH18/((AN18+BG18)/2)-BA18/((BG18+BR18)/2),0),0) -> -0.044147339 | AA18: =IF(N(AJ18)>0,1,0) -> 1 | AB18: =Inputs!$C$24+Inputs!$C$25*U18+Inputs!$C$26*V18+Inputs!$C$27*W18+Inputs!$C$28*X18+Inputs!$C$29*Y18+Inputs!$C$30*Z18+Inputs!$C$31*AA18 -> -5.515487 | AD18: 2215.573 | AE18: 1884.048 | AF18: 100.681 | AG18: 13.282 | AH18: 72.021 | AI18: 107.509 | AJ18: 34.2 | AK18: 288.941 | AL18: 448.98 | AM18: 938.002 | AN18: 1165.6 | AO18: 187.949 | AP18: 180.964 | AQ18: n/a | AR18: 2.643 | AS18: 363.618 | AT18: 444.221 | AU18: 40 | AV18: 53.589 | AW18: 1991.155 | AX18: 1670.924 | AY18: 73.228 | AZ18: 8.133 | BA18: 101.863 | BB18: -44.636 | BC18: 84.9 | BD18: 322.594 | BE18: 463.493 | BF18: 914.415 | BG18: 1089.809 | BH18: 163.038 | BI18: 95.442 | BJ18: n/a | BK18: 2.633 | BL18: 454.107 | BM18: 470.724 | BN18: 0.933 | BO18: 93.479 | BP18: 212.738 | BQ18: 1467.202 | BR18: 796.325 | BS18: 54.157
B19: 42643 | C19: 42681 | D19: yes | E19: =Inputs!$C$13+Inputs!$C$14*M19+Inputs!$C$15*N19+Inputs!$C$16*O19+Inputs!$C$17*P19+Inputs!$C$18*Q19+Inputs!$C$19*R19+Inputs!$C$20*S19+Inputs!$C$21*T19 -> -1.8604494 | F19: =EXP(AB19)/(1+EXP(AB19))/Inputs!$C$32 -> 1.4304573 | G19: =IFERROR((AH19-AI19)/((AN19+BG19)/2),"n/a") -> -0.0037401718 | H19: =IFERROR(AI19/AH19,"n/a") -> 1.0599271 | I19: =IFERROR(AK19/AD19*365,"n/a") -> 53.852405 | J19: =IFERROR(N(AL19)/AE19*365,"n/a") -> 96.78627 | K19: =IF(E19>Inputs!$C$7,1,0) -> 0 | L19: =IF(F19>Inputs!$C$8,1,0) -> 0 | M19: =IFERROR((AK19/AD19)/(BD19/AW19),1) -> 1.026779 | N19: =IFERROR(((AW19-AX19)/AW19)/((AD19-AE19)/AD19),1) -> 1.0250469 | O19: =IFERROR((1-(AM19+AO19)/AN19)/(1-(BF19+BH19)/BG19),1) -> 2.4512876 | P19: =IFERROR(AD19/AW19,1) -> 1.0761672 | Q19: =IFERROR((AZ19/(AZ19+BH19))/(AG19/(AG19+AO19)),1) -> 0.7262704 | R19: =IFERROR((AF19/AD19)/(AY19/AW19),1) -> 1.2243101 | S19: =IFERROR((AH19-AI19)/AN19,0) -> -0.0035278281 | T19: =IFERROR(((AS19+N(AU19))/AN19)/((BL19+N(BN19))/BG19),1) -> 0.95720261 | U19: =IFERROR((((AM19-AP19-N(AQ19))-(AS19-N(AV19))+(AN19-AM19-N(AR19))-(AT19-AS19-N(AU19))+(N(AQ19)+N(AR19))-(N(AU19)+N(AV19)))-((BF19-BI19-N(BJ19))-(BL19-N(BO19))+(BG19-BF19-N(BK19))-(BM19-BL19-N(BN19))+(N(BJ19)+N(BK19))-(N(BN19)+N(BO19))))/((AN19+BG19)/2),0) -> 0.042820885 | V19: =IFERROR((AK19-BD19)/((AN19+BG19)/2),0) -> 0.027090622 | W19: =IFERROR((N(AL19)-N(BE19))/((AN19+BG19)/2),0) -> 0.03354168 | X19: =IFERROR((AN19-N(AO19)-AP19)/AN19,0) -> 0.72345629 | Y19: =IF(COUNT(BP19,BQ19,BR19,BS19)=4,IFERROR((AD19-(AK19-BD19))/(AW19-(BD19-BP19))-1,0),0) -> 0.1165501 | Z19: =IF(COUNT(BP19,BQ19,BR19,BS19)=4,IFERROR(AH19/((AN19+BG19)/2)-BA19/((BG19+BR19)/2),0),0) -> -0.036735601 | AA19: =IF(N(AJ19)>0,1,0) -> 1 | AB19: =Inputs!$C$24+Inputs!$C$25*U19+Inputs!$C$26*V19+Inputs!$C$27*W19+Inputs!$C$28*X19+Inputs!$C$29*Y19+Inputs!$C$30*Z19+Inputs!$C$31*AA19 -> -5.2361215 | AD19: 2224.923 | AE19: 1885.549 | AF19: 104.903 | AG19: 14.331 | AH19: 71.854 | AI19: 76.16 | AJ19: 103.416 | AK19: 328.267 | AL19: 499.987 | AM19: 989.371 | AN19: 1220.581 | AO19: 190.848 | AP19: 146.696 | AQ19: n/a | AR19: 2.643 | AS19: 415.493 | AT19: 497.366 | AU19: 37.212 | AV19: 60.983 | AW19: 2067.451 | AX19: 1744.198 | AY19: 79.619 | AZ19: 9.039 | BA19: 94.699 | BB19: -51.376 | BC19: 89.6 | BD19: 297.078 | BE19: 461.371 | BF19: 898.242 | BG19: 1081.987 | BH19: 169.149 | BI19: 110.894 | BJ19: n/a | BK19: 2.633 | BL19: 419.011 | BM19: 443.873 | BN19: 0.233 | BO19: 94.574 | BP19: 194.37 | BQ19: 1601.508 | BR19: 828.275 | BS19: 67.321
B20: 42735 | C20: 42773 | D20: yes | E20: =Inputs!$C$13+Inputs!$C$14*M20+Inputs!$C$15*N20+Inputs!$C$16*O20+Inputs!$C$17*P20+Inputs!$C$18*Q20+Inputs!$C$19*R20+Inputs!$C$20*S20+Inputs!$C$21*T20 -> -1.6572464 | F20: =EXP(AB20)/(1+EXP(AB20))/Inputs!$C$32 -> 1.7550367 | G20: =IFERROR((AH20-AI20)/((AN20+BG20)/2),"n/a") -> 0.073505778 | H20: =IFERROR(AI20/AH20,"n/a") -> -0.57948649 | I20: =IFERROR(AK20/AD20*365,"n/a") -> 59.838352 | J20: =IFERROR(N(AL20)/AE20*365,"n/a") -> 114.42875 | K20: =IF(E20>Inputs!$C$7,1,0) -> 1 | L20: =IF(F20>Inputs!$C$8,1,0) -> 0 | M20: =IFERROR((AK20/AD20)/(BD20/AW20),1) -> 1.1497603 | N20: =IFERROR(((AW20-AX20)/AW20)/((AD20-AE20)/AD20),1) -> 1.074081 | O20: =IFERROR((1-(AM20+AO20)/AN20)/(1-(BF20+BH20)/BG20),1) -> 1.8912125 | P20: =IFERROR(AD20/AW20,1) -> 1.0156631 | Q20: =IFERROR((AZ20/(AZ20+BH20))/(AG20/(AG20+AO20)),1) -> 0.77474774 | R20: =IFERROR((AF20/AD20)/(AY20/AW20),1) -> 1.1480493 | S20: =IFERROR((AH20-AI20)/AN20,0) -> 0.069225162 | T20: =IFERROR(((AS20+N(AU20))/AN20)/((BL20+N(BN20))/BG20),1) -> 1.0021345 | U20: =IFERROR((((AM20-AP20-N(AQ20))-(AS20-N(AV20))+(AN20-AM20-N(AR20))-(AT20-AS20-N(AU20))+(N(AQ20)+N(AR20))-(N(AU20)+N(AV20)))-((BF20-BI20-N(BJ20))-(BL20-N(BO20))+(BG20-BF20-N(BK20))-(BM20-BL20-N(BN20))+(N(BJ20)+N(BK20))-(N(BN20)+N(BO20))))/((AN20+BG20)/2),0) -> 0.090740037 | V20: =IFERROR((AK20-BD20)/((AN20+BG20)/2),0) -> 0.041462438 | W20: =IFERROR((N(AL20)-N(BE20))/((AN20+BG20)/2),0) -> 0.088683002 | X20: =IFERROR((AN20-N(AO20)-AP20)/AN20,0) -> 0.76114341 | Y20: =IF(COUNT(BP20,BQ20,BR20,BS20)=4,IFERROR((AD20-(AK20-BD20))/(AW20-(BD20-BP20))-1,0),0) -> 0.017316035 | Z20: =IF(COUNT(BP20,BQ20,BR20,BS20)=4,IFERROR(AH20/((AN20+BG20)/2)-BA20/((BG20+BR20)/2),0),0) -> -0.045718628 | AA20: =IF(N(AJ20)>0,1,0) -> 1 | AB20: =Inputs!$C$24+Inputs!$C$25*U20+Inputs!$C$26*V20+Inputs!$C$27*W20+Inputs!$C$28*X20+Inputs!$C$29*Y20+Inputs!$C$30*Z20+Inputs!$C$31*AA20 -> -5.0304179 | AD20: 2237.913 | AE20: 1911.523 | AF20: 105.513 | AG20: 15.04 | AH20: 59.161 | AI20: -34.283 | AJ20: 149.916 | AK20: 366.885 | AL20: 599.269 | AM20: 1113.808 | AN20: 1349.856 | AO20: 193.67 | AP20: 128.752 | AQ20: n/a | AR20: 2.643 | AS20: 509.762 | AT20: 597.495 | AU20: 34.732 | AV20: 92.443 | AW20: 2203.401 | AX20: 1858.238 | AY20: 90.489 | AZ20: 10.241 | BA20: 98.146 | BB20: 50.973 | BC20: 94.1 | BD20: 314.176 | BE20: 486.531 | BF20: 999.648 | BG20: 1192.638 | BH20: 173.192 | BI20: 169.892 | BJ20: n/a | BK20: 2.633 | BL20: 480.052 | BM20: 514.49 | BN20: 0 | BO20: 94.233 | BP20: 258.784 | BQ20: 1748.16 | BR20: 935.041 | BS20: 85.228
B21: 42825 | C21: 42865 | D21: yes | E21: =Inputs!$C$13+Inputs!$C$14*M21+Inputs!$C$15*N21+Inputs!$C$16*O21+Inputs!$C$17*P21+Inputs!$C$18*Q21+Inputs!$C$19*R21+Inputs!$C$20*S21+Inputs!$C$21*T21 -> -1.1548226 | F21: =EXP(AB21)/(1+EXP(AB21))/Inputs!$C$32 -> 2.1340727 | G21: =IFERROR((AH21-AI21)/((AN21+BG21)/2),"n/a") -> 0.10423547 | H21: =IFERROR(AI21/AH21,"n/a") -> -1.2775966 | I21: =IFERROR(AK21/AD21*365,"n/a") -> 61.137667 | J21: =IFERROR(N(AL21)/AE21*365,"n/a") -> 117.17825 | K21: =IF(E21>Inputs!$C$7,1,0) -> 1 | L21: =IF(F21>Inputs!$C$8,1,0) -> 1 | M21: =IFERROR((AK21/AD21)/(BD21/AW21),1) -> 1.3278427 | N21: =IFERROR(((AW21-AX21)/AW21)/((AD21-AE21)/AD21),1) -> 1.0682092 | O21: =IFERROR((1-(AM21+AO21)/AN21)/(1-(BF21+BH21)/BG21),1) -> 2.4550086 | P21: =IFERROR(AD21/AW21,1) -> 1.031533 | Q21: =IFERROR((AZ21/(AZ21+BH21))/(AG21/(AG21+AO21)),1) -> 0.83482519 | R21: =IFERROR((AF21/AD21)/(AY21/AW21),1) -> 1.1547776 | S21: =IFERROR((AH21-AI21)/AN21,0) -> 0.09594747 | T21: =IFERROR(((AS21+N(AU21))/AN21)/((BL21+N(BN21))/BG21),1) -> 1.097017 | U21: =IFERROR((((AM21-AP21-N(AQ21))-(AS21-N(AV21))+(AN21-AM21-N(AR21))-(AT21-AS21-N(AU21))+(N(AQ21)+N(AR21))-(N(AU21)+N(AV21)))-((BF21-BI21-N(BJ21))-(BL21-N(BO21))+(BG21-BF21-N(BK21))-(BM21-BL21-N(BN21))+(N(BJ21)+N(BK21))-(N(BN21)+N(BO21))))/((AN21+BG21)/2),0) -> 0.10570362 | V21: =IFERROR((AK21-BD21)/((AN21+BG21)/2),0) -> 0.08170658 | W21: =IFERROR((N(AL21)-N(BE21))/((AN21+BG21)/2),0) -> 0.12611383 | X21: =IFERROR((AN21-N(AO21)-AP21)/AN21,0) -> 0.78402171 | Y21: =IF(COUNT(BP21,BQ21,BR21,BS21)=4,IFERROR((AD21-(AK21-BD21))/(AW21-(BD21-BP21))-1,0),0) -> 0.013601708 | Z21: =IF(COUNT(BP21,BQ21,BR21,BS21)=4,IFERROR(AH21/((AN21+BG21)/2)-BA21/((BG21+BR21)/2),0),0) -> -0.039900953 | AA21: =IF(N(AJ21)>0,1,0) -> 1 | AB21: =Inputs!$C$24+Inputs!$C$25*U21+Inputs!$C$26*V21+Inputs!$C$27*W21+Inputs!$C$28*X21+Inputs!$C$29*Y21+Inputs!$C$30*Z21+Inputs!$C$31*AA21 -> -4.8334629 | AD21: 2336.316 | AE21: 2000.752 | AF21: 112.103 | AG21: 15.512 | AH21: 59.165 | AI21: -75.589 | AJ21: 180.516 | AK21: 391.334 | AL21: 642.314 | AM21: 1156.707 | AN21: 1404.456 | AO21: 195.553 | AP21: 107.779 | AQ21: n/a | AR21: 2.643 | AS21: 534.532 | AT21: 627.43 | AU21: 32.251 | AV21: 113.26 | AW21: 2264.897 | AX21: 1917.402 | AY21: 94.11 | AZ21: 11.741 | BA21: 91.752 | BB21: 39.126 | BC21: 72.6 | BD21: 285.705 | BE21: 479.276 | BF21: 983.611 | BG21: 1181.113 | BH21: 179.622 | BI21: 176.406 | BJ21: n/a | BK21: 2.633 | BL21: 434.497 | BM21: 472.112 | BN21: 0 | BO21: 93.795 | BP21: 221.561 | BQ21: 1845.63 | BR21: 960.961 | BS21: 91.71
B22: 42916 | C22: 43602 | D22: yes | E22: =Inputs!$C$13+Inputs!$C$14*M22+Inputs!$C$15*N22+Inputs!$C$16*O22+Inputs!$C$17*P22+Inputs!$C$18*Q22+Inputs!$C$19*R22+Inputs!$C$20*S22+Inputs!$C$21*T22 -> -1.340136 | F22: =EXP(AB22)/(1+EXP(AB22))/Inputs!$C$32 -> 2.3906289 | G22: =IFERROR((AH22-AI22)/((AN22+BG22)/2),"n/a") -> 0.12047677 | H22: =IFERROR(AI22/AH22,"n/a") -> -1.438777 | I22: =IFERROR(AK22/AD22*365,"n/a") -> 47.591485 | J22: =IFERROR(N(AL22)/AE22*365,"n/a") -> 125.94261 | K22: =IF(E22>Inputs!$C$7,1,0) -> 1 | L22: =IF(F22>Inputs!$C$8,1,0) -> 1 | M22: =IFERROR((AK22/AD22)/(BD22/AW22),1) -> 1.6584369 | N22: =IFERROR(((AW22-AX22)/AW22)/((AD22-AE22)/AD22),1) -> 1.0547184 | O22: =IFERROR((1-(AM22+AO22)/AN22)/(1-(BF22+BH22)/BG22),1) -> 0.93313287 | P22: =IFERROR(AD22/AW22,1) -> 1.116811 | Q22: =IFERROR((AZ22/(AZ22+BH22))/(AG22/(AG22+AO22)),1) -> 0.85519179 | R22: =IFERROR((AF22/AD22)/(AY22/AW22),1) -> 1.0069303 | S22: =IFERROR((AH22-AI22)/AN22,0) -> 0.10760925 | T22: =IFERROR(((AS22+N(AU22))/AN22)/((BL22+N(BN22))/BG22),1) -> 1.1762356 | U22: =IFERROR((((AM22-AP22-N(AQ22))-(AS22-N(AV22))+(AN22-AM22-N(AR22))-(AT22-AS22-N(AU22))+(N(AQ22)+N(AR22))-(N(AU22)+N(AV22)))-((BF22-BI22-N(BJ22))-(BL22-N(BO22))+(BG22-BF22-N(BK22))-(BM22-BL22-N(BN22))+(N(BJ22)+N(BK22))-(N(BN22)+N(BO22))))/((AN22+BG22)/2),0) -> 0.10744573 | V22: =IFERROR((AK22-BD22)/((AN22+BG22)/2),0) -> 0.11015317 | W22: =IFERROR((N(AL22)-N(BE22))/((AN22+BG22)/2),0) -> 0.16246209 | X22: =IFERROR((AN22-N(AO22)-AP22)/AN22,0) -> 0.79791701 | Y22: =IF(COUNT(BP22,BQ22,BR22,BS22)=4,IFERROR((AD22-(AK22-BD22))/(AW22-(BD22-BP22))-1,0),0) -> -0.015520405 | Z22: =IF(COUNT(BP22,BQ22,BR22,BS22)=4,IFERROR(AH22/((AN22+BG22)/2)-BA22/((BG22+BR22)/2),0),0) -> -0.013792651 | AA22: =IF(N(AJ22)>0,1,0) -> 1 | AB22: =Inputs!$C$24+Inputs!$C$25*U22+Inputs!$C$26*V22+Inputs!$C$27*W22+Inputs!$C$28*X22+Inputs!$C$29*Y22+Inputs!$C$30*Z22+Inputs!$C$31*AA22 -> -4.7189813 | AD22: 2484.929 | AE22: 2134.971 | AF22: 111.091 | AG22: 16.357 | AH22: 66.854 | AI22: -96.188 | AJ22: 207.029 | AK22: 324.004 | AL22: 736.668 | AM22: 1261.166 | AN22: 1515.13 | AO22: 195.576 | AP22: 110.606 | AQ22: n/a | AR22: 2.625 | AS22: 672.53 | AT22: 741.284 | AU22: 0 | AV22: 161.447 | AW22: 2225.022 | AX22: 1894.521 | AY22: 98.787 | AZ22: 13.282 | BA22: 72.081 | BB22: 107.987 | BC22: 34.2 | BD22: 174.933 | BE22: 516.807 | BF22: 954.328 | BG22: 1191.483 | BH22: 187.949 | BI22: 178.82 | BJ22: n/a | BK22: 2.643 | BL22: 409.63 | BM22: 494.83 | BN22: 40 | BO22: 53.589 | BP22: 322.594 | BQ22: 1954.353 | BR22: 1089.809 | BS22: 92.555
B23: 43281 | C23: 43818 | D23: yes | E23: =Inputs!$C$13+Inputs!$C$14*M23+Inputs!$C$15*N23+Inputs!$C$16*O23+Inputs!$C$17*P23+Inputs!$C$18*Q23+Inputs!$C$19*R23+Inputs!$C$20*S23+Inputs!$C$21*T23 -> -2.4008944 | F23: =EXP(AB23)/(1+EXP(AB23))/Inputs!$C$32 -> 2.1260113 | G23: =IFERROR((AH23-AI23)/((AN23+BG23)/2),"n/a") -> -0.023248854 | H23: =IFERROR(AI23/AH23,"n/a") -> 1.8270768 | I23: =IFERROR(AK23/AD23*365,"n/a") -> 49.028072 | J23: =IFERROR(N(AL23)/AE23*365,"n/a") -> 106.27442 | K23: =IF(E23>Inputs!$C$7,1,0) -> 0 | L23: =IF(F23>Inputs!$C$8,1,0) -> 1 | M23: =IFERROR((AK23/AD23)/(BD23/AW23),1) -> 1.0301858 | N23: =IFERROR(((AW23-AX23)/AW23)/((AD23-AE23)/AD23),1) -> 1.1006327 | O23: =IFERROR((1-(AM23+AO23)/AN23)/(1-(BF23+BH23)/BG23),1) -> 0.61586061 | P23: =IFERROR(AD23/AW23,1) -> 1.3523493 | Q23: =IFERROR((AZ23/(AZ23+BH23))/(AG23/(AG23+AO23)),1) -> 0.77186058 | R23: =IFERROR((AF23/AD23)/(AY23/AW23),1) -> 1.1327408 | S23: =IFERROR((AH23-AI23)/AN23,0) -> -0.021577786 | T23: =IFERROR(((AS23+N(AU23))/AN23)/((BL23+N(BN23))/BG23),1) -> 1.0332501 | U23: =IFERROR((((AM23-AP23-N(AQ23))-(AS23-N(AV23))+(AN23-AM23-N(AR23))-(AT23-AS23-N(AU23))+(N(AQ23)+N(AR23))-(N(AU23)+N(AV23)))-((BF23-BI23-N(BJ23))-(BL23-N(BO23))+(BG23-BF23-N(BK23))-(BM23-BL23-N(BN23))+(N(BJ23)+N(BK23))-(N(BN23)+N(BO23))))/((AN23+BG23)/2),0) -> 0.039599529 | V23: =IFERROR((AK23-BD23)/((AN23+BG23)/2),0) -> 0.077566609 | W23: =IFERROR((N(AL23)-N(BE23))/((AN23+BG23)/2),0) -> 0.070987492 | X23: =IFERROR((AN23-N(AO23)-AP23)/AN23,0) -> 0.82367498 | Y23: =IF(COUNT(BP23,BQ23,BR23,BS23)=4,IFERROR((AD23-(AK23-BD23))/(AW23-(BD23-BP23))-1,0),0) -> 0.38411796 | Z23: =IF(COUNT(BP23,BQ23,BR23,BS23)=4,IFERROR(AH23/((AN23+BG23)/2)-BA23/((BG23+BR23)/2),0),0) -> -0.021290819 | AA23: =IF(N(AJ23)>0,1,0) -> 1 | AB23: =Inputs!$C$24+Inputs!$C$25*U23+Inputs!$C$26*V23+Inputs!$C$27*W23+Inputs!$C$28*X23+Inputs!$C$29*Y23+Inputs!$C$30*Z23+Inputs!$C$31*AA23 -> -4.8372775 | AD23: 3360.492 | AE23: 2930.498 | AF23: 170.176 | AG23: 21.846 | AH23: 46.165 | AI23: 84.347 | AJ23: 107.337 | AK23: 451.393 | AL23: 853.252 | AM23: 1530.878 | AN23: 1769.505 | AO23: 196.631 | AP23: 115.377 | AQ23: n/a | AR23: 1.571 | AS23: 811.557 | AT23: 925.853 | AU23: n/a | AV23: 116.181 | AW23: 2484.929 | AX23: 2134.971 | AY23: 111.091 | AZ23: 16.357 | BA23: 66.854 | BB23: -96.188 | BC23: 207.029 | BD23: 324.004 | BE23: 736.668 | BF23: 1261.166 | BG23: 1515.13 | BH23: 195.576 | BI23: 110.606 | BJ23: n/a | BK23: 2.625 | BL23: 672.53 | BM23: 741.284 | BN23: 0 | BO23: 161.447 | BP23: 174.933 | BQ23: 2225.022 | BR23: 1191.483 | BS23: 72.081
B24: 43373 | C24: 43818 | D24: no | E24: =Inputs!$C$13+Inputs!$C$14*M24+Inputs!$C$15*N24+Inputs!$C$16*O24+Inputs!$C$17*P24+Inputs!$C$18*Q24+Inputs!$C$19*R24+Inputs!$C$20*S24+Inputs!$C$21*T24 -> -2.3129745 | F24: =EXP(AB24)/(1+EXP(AB24))/Inputs!$C$32 -> 1.4379947 | G24: =IFERROR((AH24-AI24)/((AN24+BG24)/2),"n/a") -> n/a | H24: =IFERROR(AI24/AH24,"n/a") -> 1.8538568 | I24: =IFERROR(AK24/AD24*365,"n/a") -> 45.57955 | J24: =IFERROR(N(AL24)/AE24*365,"n/a") -> 95.198309 | K24: =IF(E24>Inputs!$C$7,1,0) -> 0 | L24: =IF(F24>Inputs!$C$8,1,0) -> 0 | M24: =IFERROR((AK24/AD24)/(BD24/AW24),1) -> 1 | N24: =IFERROR(((AW24-AX24)/AW24)/((AD24-AE24)/AD24),1) -> 1.0232148 | O24: =IFERROR((1-(AM24+AO24)/AN24)/(1-(BF24+BH24)/BG24),1) -> 1 | P24: =IFERROR(AD24/AW24,1) -> 1.3524146 | Q24: =IFERROR((AZ24/(AZ24+BH24))/(AG24/(AG24+AO24)),1) -> 1 | R24: =IFERROR((AF24/AD24)/(AY24/AW24),1) -> 1.1340992 | S24: =IFERROR((AH24-AI24)/AN24,0) -> -0.029177316 | T24: =IFERROR(((AS24+N(AU24))/AN24)/((BL24+N(BN24))/BG24),1) -> 1 | U24: =IFERROR((((AM24-AP24-N(AQ24))-(AS24-N(AV24))+(AN24-AM24-N(AR24))-(AT24-AS24-N(AU24))+(N(AQ24)+N(AR24))-(N(AU24)+N(AV24)))-((BF24-BI24-N(BJ24))-(BL24-N(BO24))+(BG24-BF24-N(BK24))-(BM24-BL24-N(BN24))+(N(BJ24)+N(BK24))-(N(BN24)+N(BO24))))/((AN24+BG24)/2),0) -> 0 | V24: =IFERROR((AK24-BD24)/((AN24+BG24)/2),0) -> 0 | W24: =IFERROR((N(AL24)-N(BE24))/((AN24+BG24)/2),0) -> 0 | X24: =IFERROR((AN24-N(AO24)-AP24)/AN24,0) -> 0.82524603 | Y24: =IF(COUNT(BP24,BQ24,BR24,BS24)=4,IFERROR((AD24-(AK24-BD24))/(AW24-(BD24-BP24))-1,0),0) -> 0 | Z24: =IF(COUNT(BP24,BQ24,BR24,BS24)=4,IFERROR(AH24/((AN24+BG24)/2)-BA24/((BG24+BR24)/2),0),0) -> 0 | AA24: =IF(N(AJ24)>0,1,0) -> 1 | AB24: =Inputs!$C$24+Inputs!$C$25*U24+Inputs!$C$26*V24+Inputs!$C$27*W24+Inputs!$C$28*X24+Inputs!$C$29*Y24+Inputs!$C$30*Z24+Inputs!$C$31*AA24 -> -5.2308381 | AD24: 3614.873 | AE24: 3147.694 | AF24: 185.861 | AG24: 23.19 | AH24: 59.428 | AI24: 110.171 | AJ24: 88.437 | AK24: 451.409 | AL24: 820.973 | AM24: 1495.69 | AN24: 1739.125 | AO24: 198.158 | AP24: 105.761 | AQ24: n/a | AR24: 1.571 | AS24: 738.882 | AT24: 863.833 | AU24: n/a | AV24: 79.299 | AW24: 2672.903 | AX24: 2319.443 | AY24: 121.179 | AZ24: 17.157 | BA24: 57.56 | BB24: -73.509 | BC24: 177.913 | BD24: n/a | BE24: n/a | BF24: n/a | BG24: n/a | BH24: n/a | BI24: n/a | BJ24: n/a | BK24: n/a | BL24: n/a | BM24: n/a | BN24: n/a | BO24: n/a | BP24: 216.165 | BQ24: 2214.681 | BR24: 1265.575 | BS24: 70.103
B25: 43465 | C25: 43818 | D25: no | E25: =Inputs!$C$13+Inputs!$C$14*M25+Inputs!$C$15*N25+Inputs!$C$16*O25+Inputs!$C$17*P25+Inputs!$C$18*Q25+Inputs!$C$19*R25+Inputs!$C$20*S25+Inputs!$C$21*T25 -> -2.425296 | F25: =EXP(AB25)/(1+EXP(AB25))/Inputs!$C$32 -> 1.4304522 | G25: =IFERROR((AH25-AI25)/((AN25+BG25)/2),"n/a") -> n/a | H25: =IFERROR(AI25/AH25,"n/a") -> 1.9027425 | I25: =IFERROR(AK25/AD25*365,"n/a") -> 42.155872 | J25: =IFERROR(N(AL25)/AE25*365,"n/a") -> 93.698557 | K25: =IF(E25>Inputs!$C$7,1,0) -> 0 | L25: =IF(F25>Inputs!$C$8,1,0) -> 0 | M25: =IFERROR((AK25/AD25)/(BD25/AW25),1) -> 1 | N25: =IFERROR(((AW25-AX25)/AW25)/((AD25-AE25)/AD25),1) -> 0.97256691 | O25: =IFERROR((1-(AM25+AO25)/AN25)/(1-(BF25+BH25)/BG25),1) -> 1 | P25: =IFERROR(AD25/AW25,1) -> 1.3111776 | Q25: =IFERROR((AZ25/(AZ25+BH25))/(AG25/(AG25+AO25)),1) -> 1 | R25: =IFERROR((AF25/AD25)/(AY25/AW25),1) -> 1.1021113 | S25: =IFERROR((AH25-AI25)/AN25,0) -> -0.04078192 | T25: =IFERROR(((AS25+N(AU25))/AN25)/((BL25+N(BN25))/BG25),1) -> 1 | U25: =IFERROR((((AM25-AP25-N(AQ25))-(AS25-N(AV25))+(AN25-AM25-N(AR25))-(AT25-AS25-N(AU25))+(N(AQ25)+N(AR25))-(N(AU25)+N(AV25)))-((BF25-BI25-N(BJ25))-(BL25-N(BO25))+(BG25-BF25-N(BK25))-(BM25-BL25-N(BN25))+(N(BJ25)+N(BK25))-(N(BN25)+N(BO25))))/((AN25+BG25)/2),0) -> 0 | V25: =IFERROR((AK25-BD25)/((AN25+BG25)/2),0) -> 0 | W25: =IFERROR((N(AL25)-N(BE25))/((AN25+BG25)/2),0) -> 0 | X25: =IFERROR((AN25-N(AO25)-AP25)/AN25,0) -> 0.82257449 | Y25: =IF(COUNT(BP25,BQ25,BR25,BS25)=4,IFERROR((AD25-(AK25-BD25))/(AW25-(BD25-BP25))-1,0),0) -> 0 | Z25: =IF(COUNT(BP25,BQ25,BR25,BS25)=4,IFERROR(AH25/((AN25+BG25)/2)-BA25/((BG25+BR25)/2),0),0) -> 0 | AA25: =IF(N(AJ25)>0,1,0) -> 1 | AB25: =Inputs!$C$24+Inputs!$C$25*U25+Inputs!$C$26*V25+Inputs!$C$27*W25+Inputs!$C$28*X25+Inputs!$C$29*Y25+Inputs!$C$30*Z25+Inputs!$C$31*AA25 -> -5.2361251 | AD25: 3719.399 | AE25: 3229.992 | AF25: 198.663 | AG25: 23.751 | AH25: 78.431 | AI25: 149.234 | AJ25: 81.997 | AK25: 429.574 | AL25: 829.166 | AM25: 1490.633 | AN25: 1736.137 | AO25: 198.252 | AP25: 109.783 | AQ25: n/a | AR25: 1.571 | AS25: 708.194 | AT25: 837.926 | AU25: n/a | AV25: 48.172 | AW25: 2836.686 | AX25: 2473.668 | AY25: 137.477 | AZ25: 18.85 | BA25: 33.901 | BB25: -24.772 | BC25: 144.013 | BD25: n/a | BE25: n/a | BF25: n/a | BG25: n/a | BH25: n/a | BI25: n/a | BJ25: n/a | BK25: n/a | BL25: n/a | BM25: n/a | BN25: n/a | BO25: n/a | BP25: 249.614 | BQ25: 2236.646 | BR25: 1398.061 | BS25: 59.775
B26: 43555 | C26: 43818 | D26: no | E26: =Inputs!$C$13+Inputs!$C$14*M26+Inputs!$C$15*N26+Inputs!$C$16*O26+Inputs!$C$17*P26+Inputs!$C$18*Q26+Inputs!$C$19*R26+Inputs!$C$20*S26+Inputs!$C$21*T26 -> -2.8839286 | F26: =EXP(AB26)/(1+EXP(AB26))/Inputs!$C$32 -> 1.2842421 | G26: =IFERROR((AH26-AI26)/((AN26+BG26)/2),"n/a") -> n/a | H26: =IFERROR(AI26/AH26,"n/a") -> 3.2982734 | I26: =IFERROR(AK26/AD26*365,"n/a") -> 32.937038 | J26: =IFERROR(N(AL26)/AE26*365,"n/a") -> 88.700133 | K26: =IF(E26>Inputs!$C$7,1,0) -> 0 | L26: =IF(F26>Inputs!$C$8,1,0) -> 0 | M26: =IFERROR((AK26/AD26)/(BD26/AW26),1) -> 1 | N26: =IFERROR(((AW26-AX26)/AW26)/((AD26-AE26)/AD26),1) -> 0.91812469 | O26: =IFERROR((1-(AM26+AO26)/AN26)/(1-(BF26+BH26)/BG26),1) -> 1 | P26: =IFERROR(AD26/AW26,1) -> 1.1867159 | Q26: =IFERROR((AZ26/(AZ26+BH26))/(AG26/(AG26+AO26)),1) -> 1 | R26: =IFERROR((AF26/AD26)/(AY26/AW26),1) -> 1.1680998 | S26: =IFERROR((AH26-AI26)/AN26,0) -> -0.10650477 | T26: =IFERROR(((AS26+N(AU26))/AN26)/((BL26+N(BN26))/BG26),1) -> 1 | U26: =IFERROR((((AM26-AP26-N(AQ26))-(AS26-N(AV26))+(AN26-AM26-N(AR26))-(AT26-AS26-N(AU26))+(N(AQ26)+N(AR26))-(N(AU26)+N(AV26)))-((BF26-BI26-N(BJ26))-(BL26-N(BO26))+(BG26-BF26-N(BK26))-(BM26-BL26-N(BN26))+(N(BJ26)+N(BK26))-(N(BN26)+N(BO26))))/((AN26+BG26)/2),0) -> 0 | V26: =IFERROR((AK26-BD26)/((AN26+BG26)/2),0) -> 0 | W26: =IFERROR((N(AL26)-N(BE26))/((AN26+BG26)/2),0) -> 0 | X26: =IFERROR((AN26-N(AO26)-AP26)/AN26,0) -> 0.76781675 | Y26: =IF(COUNT(BP26,BQ26,BR26,BS26)=4,IFERROR((AD26-(AK26-BD26))/(AW26-(BD26-BP26))-1,0),0) -> 0 | Z26: =IF(COUNT(BP26,BQ26,BR26,BS26)=4,IFERROR(AH26/((AN26+BG26)/2)-BA26/((BG26+BR26)/2),0),0) -> 0 | AA26: =IF(N(AJ26)>0,1,0) -> 1 | AB26: =Inputs!$C$24+Inputs!$C$25*U26+Inputs!$C$26*V26+Inputs!$C$27*W26+Inputs!$C$28*X26+Inputs!$C$29*Y26+Inputs!$C$30*Z26+Inputs!$C$31*AA26 -> -5.3444907 | AD26: 3627.788 | AE26: 3131.971 | AF26: 210.883 | AG26: 23.845 | AH26: 74.482 | AI26: 245.662 | AJ26: 41.76 | AK26: 327.366 | AL26: 761.113 | AM26: 1356.071 | AN26: 1607.252 | AO26: 203.442 | AP26: 169.735 | AQ26: n/a | AR26: n/a | AS26: 564.069 | AT26: 694.094 | AU26: n/a | AV26: 22.66 | AW26: 3056.998 | AX26: 2673.4 | AY26: 152.13 | AZ26: 20.775 | BA26: 33.146 | BB26: 13.684 | BC26: 143.95 | BD26: n/a | BE26: n/a | BF26: n/a | BG26: n/a | BH26: n/a | BI26: n/a | BJ26: n/a | BK26: n/a | BL26: n/a | BM26: n/a | BN26: n/a | BO26: n/a | BP26: 270.736 | BQ26: 2337.976 | BR26: 1455.132 | BS26: 59.079
B27: 43646 | C27: 43818 | D27: yes | E27: =Inputs!$C$13+Inputs!$C$14*M27+Inputs!$C$15*N27+Inputs!$C$16*O27+Inputs!$C$17*P27+Inputs!$C$18*Q27+Inputs!$C$19*R27+Inputs!$C$20*S27+Inputs!$C$21*T27 -> -3.0111056 | F27: =EXP(AB27)/(1+EXP(AB27))/Inputs!$C$32 -> 0.95405769 | G27: =IFERROR((AH27-AI27)/((AN27+BG27)/2),"n/a") -> -0.11044643 | H27: =IFERROR(AI27/AH27,"n/a") -> 3.6507411 | I27: =IFERROR(AK27/AD27*365,"n/a") -> 41.045138 | J27: =IFERROR(N(AL27)/AE27*365,"n/a") -> 81.408256 | K27: =IF(E27>Inputs!$C$7,1,0) -> 0 | L27: =IF(F27>Inputs!$C$8,1,0) -> 0 | M27: =IFERROR((AK27/AD27)/(BD27/AW27),1) -> 0.83717626 | N27: =IFERROR(((AW27-AX27)/AW27)/((AD27-AE27)/AD27),1) -> 0.90387693 | O27: =IFERROR((1-(AM27+AO27)/AN27)/(1-(BF27+BH27)/BG27),1) -> 1.3393826 | P27: =IFERROR(AD27/AW27,1) -> 1.0416213 | Q27: =IFERROR((AZ27/(AZ27+BH27))/(AG27/(AG27+AO27)),1) -> 0.95661922 | R27: =IFERROR((AF27/AD27)/(AY27/AW27),1) -> 1.2319943 | S27: =IFERROR((AH27-AI27)/AN27,0) -> -0.11329887 | T27: =IFERROR(((AS27+N(AU27))/AN27)/((BL27+N(BN27))/BG27),1) -> 0.78524257 | U27: =IFERROR((((AM27-AP27-N(AQ27))-(AS27-N(AV27))+(AN27-AM27-N(AR27))-(AT27-AS27-N(AU27))+(N(AQ27)+N(AR27))-(N(AU27)+N(AV27)))-((BF27-BI27-N(BJ27))-(BL27-N(BO27))+(BG27-BF27-N(BK27))-(BM27-BL27-N(BN27))+(N(BJ27)+N(BK27))-(N(BN27)+N(BO27))))/((AN27+BG27)/2),0) -> -0.020429889 | V27: =IFERROR((AK27-BD27)/((AN27+BG27)/2),0) -> -0.033468913 | W27: =IFERROR((N(AL27)-N(BE27))/((AN27+BG27)/2),0) -> -0.10605953 | X27: =IFERROR((AN27-N(AO27)-AP27)/AN27,0) -> 0.72928645 | Y27: =IF(COUNT(BP27,BQ27,BR27,BS27)=4,IFERROR((AD27-(AK27-BD27))/(AW27-(BD27-BP27))-1,0),0) -> 0.10053067 | Z27: =IF(COUNT(BP27,BQ27,BR27,BS27)=4,IFERROR(AH27/((AN27+BG27)/2)-BA27/((BG27+BR27)/2),0),0) -> 0.013556576 | AA27: =IF(N(AJ27)>0,1,0) -> 1 | AB27: =Inputs!$C$24+Inputs!$C$25*U27+Inputs!$C$26*V27+Inputs!$C$27*W27+Inputs!$C$28*X27+Inputs!$C$29*Y27+Inputs!$C$30*Z27+Inputs!$C$31*AA27 -> -5.6429173 | AD27: 3500.36 | AE27: 3004.838 | AF27: 218.382 | AG27: 24.202 | AH27: 71.918 | AI27: 262.554 | AJ27: 41.76 | AK27: 393.624 | AL27: 670.188 | AM27: 1421.771 | AN27: 1682.594 | AO27: 207.337 | AP27: 248.164 | AQ27: n/a | AR27: 1.571 | AS27: 605.969 | AT27: 741.418 | AU27: n/a | AV27: 23.647 | AW27: 3360.492 | AX27: 2930.498 | AY27: 170.176 | AZ27: 21.846 | BA27: 46.165 | BB27: 84.347 | BC27: 107.337 | BD27: 451.393 | BE27: 853.252 | BF27: 1530.878 | BG27: 1769.505 | BH27: 196.631 | BI27: 115.377 | BJ27: n/a | BK27: 1.571 | BL27: 811.557 | BM27: 925.853 | BN27: n/a | BO27: 116.181 | BP27: 324.004 | BQ27: 2484.929 | BR27: 1515.13 | BS27: 66.854
B28: 43738 | C28: 43819 | D28: yes | E28: =Inputs!$C$13+Inputs!$C$14*M28+Inputs!$C$15*N28+Inputs!$C$16*O28+Inputs!$C$17*P28+Inputs!$C$18*Q28+Inputs!$C$19*R28+Inputs!$C$20*S28+Inputs!$C$21*T28 -> -2.9393675 | F28: =EXP(AB28)/(1+EXP(AB28))/Inputs!$C$32 -> 0.93718182 | G28: =IFERROR((AH28-AI28)/((AN28+BG28)/2),"n/a") -> -0.088089227 | H28: =IFERROR(AI28/AH28,"n/a") -> 2.920034 | I28: =IFERROR(AK28/AD28*365,"n/a") -> 39.057421 | J28: =IFERROR(N(AL28)/AE28*365,"n/a") -> 88.508141 | K28: =IF(E28>Inputs!$C$7,1,0) -> 0 | L28: =IF(F28>Inputs!$C$8,1,0) -> 0 | M28: =IFERROR((AK28/AD28)/(BD28/AW28),1) -> 0.85690667 | N28: =IFERROR(((AW28-AX28)/AW28)/((AD28-AE28)/AD28),1) -> 0.85498614 | O28: =IFERROR((1-(AM28+AO28)/AN28)/(1-(BF28+BH28)/BG28),1) -> 1.5455093 | P28: =IFERROR(AD28/AW28,1) -> 0.92093028 | Q28: =IFERROR((AZ28/(AZ28+BH28))/(AG28/(AG28+AO28)),1) -> 0.99233066 | R28: =IFERROR((AF28/AD28)/(AY28/AW28),1) -> 1.2568105 | S28: =IFERROR((AH28-AI28)/AN28,0) -> -0.089069185 | T28: =IFERROR(((AS28+N(AU28))/AN28)/((BL28+N(BN28))/BG28),1) -> 0.81407276 | U28: =IFERROR((((AM28-AP28-N(AQ28))-(AS28-N(AV28))+(AN28-AM28-N(AR28))-(AT28-AS28-N(AU28))+(N(AQ28)+N(AR28))-(N(AU28)+N(AV28)))-((BF28-BI28-N(BJ28))-(BL28-N(BO28))+(BG28-BF28-N(BK28))-(BM28-BL28-N(BN28))+(N(BJ28)+N(BK28))-(N(BN28)+N(BO28))))/((AN28+BG28)/2),0) -> -0.021494606 | V28: =IFERROR((AK28-BD28)/((AN28+BG28)/2),0) -> -0.055330226 | W28: =IFERROR((N(AL28)-N(BE28))/((AN28+BG28)/2),0) -> -0.078910638 | X28: =IFERROR((AN28-N(AO28)-AP28)/AN28,0) -> 0.73444062 | Y28: =IF(COUNT(BP28,BQ28,BR28,BS28)=4,IFERROR((AD28-(AK28-BD28))/(AW28-(BD28-BP28))-1,0),0) -> 0 | Z28: =IF(COUNT(BP28,BQ28,BR28,BS28)=4,IFERROR(AH28/((AN28+BG28)/2)-BA28/((BG28+BR28)/2),0),0) -> 0 | AA28: =IF(N(AJ28)>0,1,0) -> 1 | AB28: =Inputs!$C$24+Inputs!$C$25*U28+Inputs!$C$26*V28+Inputs!$C$27*W28+Inputs!$C$28*X28+Inputs!$C$29*Y28+Inputs!$C$30*Z28+Inputs!$C$31*AA28 -> -5.6608268 | AD28: 3329.046 | AE28: 2825.834 | AF28: 215.122 | AG28: 25.082 | AH28: 78.921 | AI28: 230.452 | AJ28: 15.86 | AK28: 356.23 | AL28: 685.231 | AM28: 1420.331 | AN28: 1701.273 | AO28: 212.489 | AP28: 239.3 | AQ28: n/a | AR28: 1.571 | AS28: 588.412 | AT28: 729.417 | AU28: n/a | AV28: 22.544 | AW28: 3614.873 | AX28: 3147.694 | AY28: 185.861 | AZ28: 23.19 | BA28: 59.428 | BB28: 110.171 | BC28: 88.437 | BD28: 451.409 | BE28: 820.973 | BF28: 1495.69 | BG28: 1739.125 | BH28: 198.158 | BI28: 105.761 | BJ28: n/a | BK28: 1.571 | BL28: 738.882 | BM28: 863.833 | BN28: n/a | BO28: 79.299 | BP28: n/a | BQ28: 2672.903 | BR28: n/a | BS28: 57.56
B29: 43830 | C29: 43868 | D29: yes | E29: =Inputs!$C$13+Inputs!$C$14*M29+Inputs!$C$15*N29+Inputs!$C$16*O29+Inputs!$C$17*P29+Inputs!$C$18*Q29+Inputs!$C$19*R29+Inputs!$C$20*S29+Inputs!$C$21*T29 -> -3.064783 | F29: =EXP(AB29)/(1+EXP(AB29))/Inputs!$C$32 -> 0.3259406 | G29: =IFERROR((AH29-AI29)/((AN29+BG29)/2),"n/a") -> -0.10397338 | H29: =IFERROR(AI29/AH29,"n/a") -> 3.1822598 | I29: =IFERROR(AK29/AD29*365,"n/a") -> 40.221381 | J29: =IFERROR(N(AL29)/AE29*365,"n/a") -> 93.334637 | K29: =IF(E29>Inputs!$C$7,1,0) -> 0 | L29: =IF(F29>Inputs!$C$8,1,0) -> 0 | M29: =IFERROR((AK29/AD29)/(BD29/AW29),1) -> 0.95411099 | N29: =IFERROR(((AW29-AX29)/AW29)/((AD29-AE29)/AD29),1) -> 0.83721836 | O29: =IFERROR((1-(AM29+AO29)/AN29)/(1-(BF29+BH29)/BG29),1) -> 1.3377531 | P29: =IFERROR(AD29/AW29,1) -> 0.87876563 | Q29: =IFERROR((AZ29/(AZ29+BH29))/(AG29/(AG29+AO29)),1) -> 1.0151391 | R29: =IFERROR((AF29/AD29)/(AY29/AW29),1) -> 1.2251357 | S29: =IFERROR((AH29-AI29)/AN29,0) -> -0.10193361 | T29: =IFERROR(((AS29+N(AU29))/AN29)/((BL29+N(BN29))/BG29),1) -> 0.91130853 | U29: =IFERROR((((AM29-AP29-N(AQ29))-(AS29-N(AV29))+(AN29-AM29-N(AR29))-(AT29-AS29-N(AU29))+(N(AQ29)+N(AR29))-(N(AU29)+N(AV29)))-((BF29-BI29-N(BJ29))-(BL29-N(BO29))+(BG29-BF29-N(BK29))-(BM29-BL29-N(BN29))+(N(BJ29)+N(BK29))-(N(BN29)+N(BO29))))/((AN29+BG29)/2),0) -> -0.054139563 | V29: =IFERROR((AK29-BD29)/((AN29+BG29)/2),0) -> -0.039175023 | W29: =IFERROR((N(AL29)-N(BE29))/((AN29+BG29)/2),0) -> -0.070409147 | X29: =IFERROR((AN29-N(AO29)-AP29)/AN29,0) -> 0.70692996 | Y29: =IF(COUNT(BP29,BQ29,BR29,BS29)=4,IFERROR((AD29-(AK29-BD29))/(AW29-(BD29-BP29))-1,0),0) -> 0 | Z29: =IF(COUNT(BP29,BQ29,BR29,BS29)=4,IFERROR(AH29/((AN29+BG29)/2)-BA29/((BG29+BR29)/2),0),0) -> 0 | AA29: =IF(N(AJ29)>0,1,0) -> 0 | AB29: =Inputs!$C$24+Inputs!$C$25*U29+Inputs!$C$26*V29+Inputs!$C$27*W29+Inputs!$C$28*X29+Inputs!$C$29*Y29+Inputs!$C$30*Z29+Inputs!$C$31*AA29 -> -6.7192559 | AD29: 3268.48 | AE29: 2754.786 | AF29: 213.882 | AG29: 25.982 | AH29: 84.407 | AI29: 268.605 | AJ29: 0 | AK29: 360.172 | AL29: 704.43 | AM29: 1520.695 | AN29: 1807.039 | AO29: 220.551 | AP29: 309.038 | AQ29: n/a | AR29: 1.571 | AS29: 671.74 | AT29: 805.486 | AU29: n/a | AV29: 23.25 | AW29: 3719.399 | AX29: 3229.992 | AY29: 198.663 | AZ29: 23.751 | BA29: 78.431 | BB29: 149.234 | BC29: 81.997 | BD29: 429.574 | BE29: 829.166 | BF29: 1490.633 | BG29: 1736.137 | BH29: 198.252 | BI29: 109.783 | BJ29: n/a | BK29: 1.571 | BL29: 708.194 | BM29: 837.926 | BN29: n/a | BO29: 48.172 | BP29: n/a | BQ29: 2836.686 | BR29: n/a | BS29: 33.901
B30: 43921 | C30: 43962 | D30: yes | E30: =Inputs!$C$13+Inputs!$C$14*M30+Inputs!$C$15*N30+Inputs!$C$16*O30+Inputs!$C$17*P30+Inputs!$C$18*Q30+Inputs!$C$19*R30+Inputs!$C$20*S30+Inputs!$C$21*T30 -> -2.589788 | F30: =EXP(AB30)/(1+EXP(AB30))/Inputs!$C$32 -> 1.2827614 | G30: =IFERROR((AH30-AI30)/((AN30+BG30)/2),"n/a") -> -0.032516998 | H30: =IFERROR(AI30/AH30,"n/a") -> 1.647575 | I30: =IFERROR(AK30/AD30*365,"n/a") -> 36.880022 | J30: =IFERROR(N(AL30)/AE30*365,"n/a") -> 114.44487 | K30: =IF(E30>Inputs!$C$7,1,0) -> 0 | L30: =IF(F30>Inputs!$C$8,1,0) -> 0 | M30: =IFERROR((AK30/AD30)/(BD30/AW30),1) -> 1.1197128 | N30: =IFERROR(((AW30-AX30)/AW30)/((AD30-AE30)/AD30),1) -> 0.84278653 | O30: =IFERROR((1-(AM30+AO30)/AN30)/(1-(BF30+BH30)/BG30),1) -> 1.3980629 | P30: =IFERROR(AD30/AW30,1) -> 0.90892549 | Q30: =IFERROR((AZ30/(AZ30+BH30))/(AG30/(AG30+AO30)),1) -> 1.0008196 | R30: =IFERROR((AF30/AD30)/(AY30/AW30),1) -> 1.1865903 | S30: =IFERROR((AH30-AI30)/AN30,0) -> -0.029589294 | T30: =IFERROR(((AS30+N(AU30))/AN30)/((BL30+N(BN30))/BG30),1) -> 1.1408147 | U30: =IFERROR((((AM30-AP30-N(AQ30))-(AS30-N(AV30))+(AN30-AM30-N(AR30))-(AT30-AS30-N(AU30))+(N(AQ30)+N(AR30))-(N(AU30)+N(AV30)))-((BF30-BI30-N(BJ30))-(BL30-N(BO30))+(BG30-BF30-N(BK30))-(BM30-BL30-N(BN30))+(N(BJ30)+N(BK30))-(N(BN30)+N(BO30))))/((AN30+BG30)/2),0) -> -0.0033003615 | V30: =IFERROR((AK30-BD30)/((AN30+BG30)/2),0) -> 0.0032549514 | W30: =IFERROR((N(AL30)-N(BE30))/((AN30+BG30)/2),0) -> 0.058928299 | X30: =IFERROR((AN30-N(AO30)-AP30)/AN30,0) -> 0.72894284 | Y30: =IF(COUNT(BP30,BQ30,BR30,BS30)=4,IFERROR((AD30-(AK30-BD30))/(AW30-(BD30-BP30))-1,0),0) -> 0 | Z30: =IF(COUNT(BP30,BQ30,BR30,BS30)=4,IFERROR(AH30/((AN30+BG30)/2)-BA30/((BG30+BR30)/2),0),0) -> 0 | AA30: =IF(N(AJ30)>0,1,0) -> 1 | AB30: =Inputs!$C$24+Inputs!$C$25*U30+Inputs!$C$26*V30+Inputs!$C$27*W30+Inputs!$C$28*X30+Inputs!$C$29*Y30+Inputs!$C$30*Z30+Inputs!$C$31*AA30 -> -5.3456498 | AD30: 3297.389 | AE30: 2762.662 | AF30: 227.442 | AG30: 26.989 | AH30: 89.568 | AI30: 147.57 | AJ30: 10 | AK30: 333.172 | AL30: 866.226 | AM30: 1648.359 | AN30: 1960.236 | AO30: 230.477 | AP30: 300.859 | AQ30: n/a | AR30: 1.571 | AS30: 784.823 | AT30: 921.841 | AU30: n/a | AV30: 33.158 | AW30: 3627.788 | AX30: 3131.971 | AY30: 210.883 | AZ30: 23.845 | BA30: 74.482 | BB30: 245.662 | BC30: 41.76 | BD30: 327.366 | BE30: 761.113 | BF30: 1356.071 | BG30: 1607.252 | BH30: 203.442 | BI30: 169.735 | BJ30: n/a | BK30: n/a | BL30: 564.069 | BM30: 694.094 | BN30: n/a | BO30: 22.66 | BP30: n/a | BQ30: 3056.998 | BR30: n/a | BS30: 33.146
B31: 44012 | C31: 44074 | D31: yes | E31: =Inputs!$C$13+Inputs!$C$14*M31+Inputs!$C$15*N31+Inputs!$C$16*O31+Inputs!$C$17*P31+Inputs!$C$18*Q31+Inputs!$C$19*R31+Inputs!$C$20*S31+Inputs!$C$21*T31 -> -2.0436173 | F31: =EXP(AB31)/(1+EXP(AB31))/Inputs!$C$32 -> 1.5523717 | G31: =IFERROR((AH31-AI31)/((AN31+BG31)/2),"n/a") -> 0.06366807 | H31: =IFERROR(AI31/AH31,"n/a") -> -0.35979978 | I31: =IFERROR(AK31/AD31*365,"n/a") -> 44.131334 | J31: =IFERROR(N(AL31)/AE31*365,"n/a") -> 110.48309 | K31: =IF(E31>Inputs!$C$7,1,0) -> 0 | L31: =IF(F31>Inputs!$C$8,1,0) -> 0 | M31: =IFERROR((AK31/AD31)/(BD31/AW31),1) -> 1.0751903 | N31: =IFERROR(((AW31-AX31)/AW31)/((AD31-AE31)/AD31),1) -> 0.89834695 | O31: =IFERROR((1-(AM31+AO31)/AN31)/(1-(BF31+BH31)/BG31),1) -> 1.510094 | P31: =IFERROR(AD31/AW31,1) -> 0.95398216 | Q31: =IFERROR((AZ31/(AZ31+BH31))/(AG31/(AG31+AO31)),1) -> 0.9628003 | R31: =IFERROR((AF31/AD31)/(AY31/AW31),1) -> 1.0515784 | S31: =IFERROR((AH31-AI31)/AN31,0) -> 0.059751512 | T31: =IFERROR(((AS31+N(AU31))/AN31)/((BL31+N(BN31))/BG31),1) -> 1.0323472 | U31: =IFERROR((((AM31-AP31-N(AQ31))-(AS31-N(AV31))+(AN31-AM31-N(AR31))-(AT31-AS31-N(AU31))+(N(AQ31)+N(AR31))-(N(AU31)+N(AV31)))-((BF31-BI31-N(BJ31))-(BL31-N(BO31))+(BG31-BF31-N(BK31))-(BM31-BL31-N(BN31))+(N(BJ31)+N(BK31))-(N(BN31)+N(BO31))))/((AN31+BG31)/2),0) -> 0.09005898 | V31: =IFERROR((AK31-BD31)/((AN31+BG31)/2),0) -> 0.0056208417 | W31: =IFERROR((N(AL31)-N(BE31))/((AN31+BG31)/2),0) -> 0.10069309 | X31: =IFERROR((AN31-N(AO31)-AP31)/AN31,0) -> 0.76842106 | Y31: =IF(COUNT(BP31,BQ31,BR31,BS31)=4,IFERROR((AD31-(AK31-BD31))/(AW31-(BD31-BP31))-1,0),0) -> -0.064350955 | Z31: =IF(COUNT(BP31,BQ31,BR31,BS31)=4,IFERROR(AH31/((AN31+BG31)/2)-BA31/((BG31+BR31)/2),0),0) -> 0.0051554061 | AA31: =IF(N(AJ31)>0,1,0) -> 1 | AB31: =Inputs!$C$24+Inputs!$C$25*U31+Inputs!$C$26*V31+Inputs!$C$27*W31+Inputs!$C$28*X31+Inputs!$C$29*Y31+Inputs!$C$30*Z31+Inputs!$C$31*AA31 -> -5.1538782 | AD31: 3339.281 | AE31: 2813.071 | AF31: 219.078 | AG31: 28.472 | AH31: 84.308 | AI31: -30.334 | AJ31: 164.791 | AK31: 403.745 | AL31: 851.498 | AM31: 1592.761 | AN31: 1918.646 | AO31: 233.785 | AP31: 210.533 | AQ31: n/a | AR31: 1.571 | AS31: 707.635 | AT31: 852.939 | AU31: 5.697 | AV31: 23.704 | AW31: 3500.36 | AX31: 3004.838 | AY31: 218.382 | AZ31: 24.202 | BA31: 71.918 | BB31: 262.554 | BC31: 41.76 | BD31: 393.624 | BE31: 670.188 | BF31: 1421.771 | BG31: 1682.594 | BH31: 207.337 | BI31: 248.164 | BJ31: n/a | BK31: 1.571 | BL31: 605.969 | BM31: 741.418 | BN31: 0 | BO31: 23.647 | BP31: 451.393 | BQ31: 3360.492 | BR31: 1769.505 | BS31: 46.165
B32: 44104 | C32: 44141 | D32: yes | E32: =Inputs!$C$13+Inputs!$C$14*M32+Inputs!$C$15*N32+Inputs!$C$16*O32+Inputs!$C$17*P32+Inputs!$C$18*Q32+Inputs!$C$19*R32+Inputs!$C$20*S32+Inputs!$C$21*T32 -> -2.4601449 | F32: =EXP(AB32)/(1+EXP(AB32))/Inputs!$C$32 -> 1.1543196 | G32: =IFERROR((AH32-AI32)/((AN32+BG32)/2),"n/a") -> -5.5145502e-05 | H32: =IFERROR(AI32/AH32,"n/a") -> 1.0011471 | I32: =IFERROR(AK32/AD32*365,"n/a") -> 35.689936 | J32: =IFERROR(N(AL32)/AE32*365,"n/a") -> 101.73034 | K32: =IF(E32>Inputs!$C$7,1,0) -> 0 | L32: =IF(F32>Inputs!$C$8,1,0) -> 0 | M32: =IFERROR((AK32/AD32)/(BD32/AW32),1) -> 0.91378118 | N32: =IFERROR(((AW32-AX32)/AW32)/((AD32-AE32)/AD32),1) -> 0.95027859 | O32: =IFERROR((1-(AM32+AO32)/AN32)/(1-(BF32+BH32)/BG32),1) -> 1.3040193 | P32: =IFERROR(AD32/AW32,1) -> 0.99179375 | Q32: =IFERROR((AZ32/(AZ32+BH32))/(AG32/(AG32+AO32)),1) -> 0.98113749 | R32: =IFERROR((AF32/AD32)/(AY32/AW32),1) -> 1.0089069 | S32: =IFERROR((AH32-AI32)/AN32,0) -> -5.3393721e-05 | T32: =IFERROR(((AS32+N(AU32))/AN32)/((BL32+N(BN32))/BG32),1) -> 0.95756411 | U32: =IFERROR((((AM32-AP32-N(AQ32))-(AS32-N(AV32))+(AN32-AM32-N(AR32))-(AT32-AS32-N(AU32))+(N(AQ32)+N(AR32))-(N(AU32)+N(AV32)))-((BF32-BI32-N(BJ32))-(BL32-N(BO32))+(BG32-BF32-N(BK32))-(BM32-BL32-N(BN32))+(N(BJ32)+N(BK32))-(N(BN32)+N(BO32))))/((AN32+BG32)/2),0) -> 0.022795559 | V32: =IFERROR((AK32-BD32)/((AN32+BG32)/2),0) -> -0.018979717 | W32: =IFERROR((N(AL32)-N(BE32))/((AN32+BG32)/2),0) -> 0.050384228 | X32: =IFERROR((AN32-N(AO32)-AP32)/AN32,0) -> 0.70168818 | Y32: =IF(COUNT(BP32,BQ32,BR32,BS32)=4,IFERROR((AD32-(AK32-BD32))/(AW32-(BD32-BP32))-1,0),0) -> -0.026024283 | Z32: =IF(COUNT(BP32,BQ32,BR32,BS32)=4,IFERROR(AH32/((AN32+BG32)/2)-BA32/((BG32+BR32)/2),0),0) -> 0.002196513 | AA32: =IF(N(AJ32)>0,1,0) -> 1 | AB32: =Inputs!$C$24+Inputs!$C$25*U32+Inputs!$C$26*V32+Inputs!$C$27*W32+Inputs!$C$28*X32+Inputs!$C$29*Y32+Inputs!$C$30*Z32+Inputs!$C$31*AA32 -> -5.4516312 | AD32: 3301.727 | AE32: 2776.531 | AF32: 215.257 | AG32: 29.163 | AH32: 84.564 | AI32: 84.661 | AJ32: 171.199 | AK32: 322.845 | AL32: 773.856 | AM32: 1479.521 | AN32: 1816.693 | AO32: 241.852 | AP32: 300.089 | AQ32: n/a | AR32: 1.571 | AS32: 589.688 | AT32: 743.951 | AU32: 11.98 | AV32: 24.047 | AW32: 3329.046 | AX32: 2825.834 | AY32: 215.122 | AZ32: 25.082 | BA32: 78.921 | BB32: 230.452 | BC32: 15.86 | BD32: 356.23 | BE32: 685.231 | BF32: 1420.331 | BG32: 1701.273 | BH32: 212.489 | BI32: 239.3 | BJ32: n/a | BK32: 1.571 | BL32: 588.412 | BM32: 729.417 | BN32: n/a | BO32: 22.544 | BP32: 451.409 | BQ32: 3614.873 | BR32: 1739.125 | BS32: 59.428
B33: 44196 | C33: 44232 | D33: yes | E33: =Inputs!$C$13+Inputs!$C$14*M33+Inputs!$C$15*N33+Inputs!$C$16*O33+Inputs!$C$17*P33+Inputs!$C$18*Q33+Inputs!$C$19*R33+Inputs!$C$20*S33+Inputs!$C$21*T33 -> -2.3671417 | F33: =EXP(AB33)/(1+EXP(AB33))/Inputs!$C$32 -> 1.1629549 | G33: =IFERROR((AH33-AI33)/((AN33+BG33)/2),"n/a") -> 0.012005584 | H33: =IFERROR(AI33/AH33,"n/a") -> 0.74905119 | I33: =IFERROR(AK33/AD33*365,"n/a") -> 36.154373 | J33: =IFERROR(N(AL33)/AE33*365,"n/a") -> 107.62983 | K33: =IF(E33>Inputs!$C$7,1,0) -> 0 | L33: =IF(F33>Inputs!$C$8,1,0) -> 0 | M33: =IFERROR((AK33/AD33)/(BD33/AW33),1) -> 0.89888443 | N33: =IFERROR(((AW33-AX33)/AW33)/((AD33-AE33)/AD33),1) -> 0.98019752 | O33: =IFERROR((1-(AM33+AO33)/AN33)/(1-(BF33+BH33)/BG33),1) -> 1.3687721 | P33: =IFERROR(AD33/AW33,1) -> 0.99773901 | Q33: =IFERROR((AZ33/(AZ33+BH33))/(AG33/(AG33+AO33)),1) -> 1.0332462 | R33: =IFERROR((AF33/AD33)/(AY33/AW33),1) -> 0.96645985 | S33: =IFERROR((AH33-AI33)/AN33,0) -> 0.011729755 | T33: =IFERROR(((AS33+N(AU33))/AN33)/((BL33+N(BN33))/BG33),1) -> 0.98502296 | U33: =IFERROR((((AM33-AP33-N(AQ33))-(AS33-N(AV33))+(AN33-AM33-N(AR33))-(AT33-AS33-N(AU33))+(N(AQ33)+N(AR33))-(N(AU33)+N(AV33)))-((BF33-BI33-N(BJ33))-(BL33-N(BO33))+(BG33-BF33-N(BK33))-(BM33-BL33-N(BN33))+(N(BJ33)+N(BK33))-(N(BN33)+N(BO33))))/((AN33+BG33)/2),0) -> 0.03031252 | V33: =IFERROR((AK33-BD33)/((AN33+BG33)/2),0) -> -0.020075594 | W33: =IFERROR((N(AL33)-N(BE33))/((AN33+BG33)/2),0) -> 0.055659503 | X33: =IFERROR((AN33-N(AO33)-AP33)/AN33,0) -> 0.69852466 | Y33: =IF(COUNT(BP33,BQ33,BR33,BS33)=4,IFERROR((AD33-(AK33-BD33))/(AW33-(BD33-BP33))-1,0),0) -> -0.011876094 | Z33: =IF(COUNT(BP33,BQ33,BR33,BS33)=4,IFERROR(AH33/((AN33+BG33)/2)-BA33/((BG33+BR33)/2),0),0) -> 0.00019594511 | AA33: =IF(N(AJ33)>0,1,0) -> 1 | AB33: =Inputs!$C$24+Inputs!$C$25*U33+Inputs!$C$26*V33+Inputs!$C$27*W33+Inputs!$C$28*X33+Inputs!$C$29*Y33+Inputs!$C$30*Z33+Inputs!$C$31*AA33 -> -5.4441461 | AD33: 3261.09 | AE33: 2738.203 | AF33: 206.241 | AG33: 29.01 | AH33: 88.532 | AI33: 66.315 | AJ33: 179.46 | AK33: 323.021 | AL33: 807.431 | AM33: 1544.273 | AN33: 1894.072 | AO33: 255.406 | AP33: 315.61 | AQ33: n/a | AR33: 1.571 | AS33: 672.971 | AT33: 829.852 | AU33: 20.577 | AV33: 24.921 | AW33: 3268.48 | AX33: 2754.786 | AY33: 213.882 | AZ33: 25.982 | BA33: 84.407 | BB33: 268.605 | BC33: 0 | BD33: 360.172 | BE33: 704.43 | BF33: 1520.695 | BG33: 1807.039 | BH33: 220.551 | BI33: 309.038 | BJ33: n/a | BK33: 1.571 | BL33: 671.74 | BM33: 805.486 | BN33: n/a | BO33: 23.25 | BP33: 429.574 | BQ33: 3719.399 | BR33: 1736.137 | BS33: 78.431
B34: 44286 | C34: 44323 | D34: yes | E34: =Inputs!$C$13+Inputs!$C$14*M34+Inputs!$C$15*N34+Inputs!$C$16*O34+Inputs!$C$17*P34+Inputs!$C$18*Q34+Inputs!$C$19*R34+Inputs!$C$20*S34+Inputs!$C$21*T34 -> -1.8530223 | F34: =EXP(AB34)/(1+EXP(AB34))/Inputs!$C$32 -> 1.5632161 | G34: =IFERROR((AH34-AI34)/((AN34+BG34)/2),"n/a") -> 0.064566076 | H34: =IFERROR(AI34/AH34,"n/a") -> -0.40215901 | I34: =IFERROR(AK34/AD34*365,"n/a") -> 43.931292 | J34: =IFERROR(N(AL34)/AE34*365,"n/a") -> 114.87549 | K34: =IF(E34>Inputs!$C$7,1,0) -> 0 | L34: =IF(F34>Inputs!$C$8,1,0) -> 0 | M34: =IFERROR((AK34/AD34)/(BD34/AW34),1) -> 1.1911948 | N34: =IFERROR(((AW34-AX34)/AW34)/((AD34-AE34)/AD34),1) -> 1.0708617 | O34: =IFERROR((1-(AM34+AO34)/AN34)/(1-(BF34+BH34)/BG34),1) -> 1.1279585 | P34: =IFERROR(AD34/AW34,1) -> 1.0264373 | Q34: =IFERROR((AZ34/(AZ34+BH34))/(AG34/(AG34+AO34)),1) -> 1.0712915 | R34: =IFERROR((AF34/AD34)/(AY34/AW34),1) -> 0.79699746 | S34: =IFERROR((AH34-AI34)/AN34,0) -> 0.063942587 | T34: =IFERROR(((AS34+N(AU34))/AN34)/((BL34+N(BN34))/BG34),1) -> 1.0119759 | U34: =IFERROR((((AM34-AP34-N(AQ34))-(AS34-N(AV34))+(AN34-AM34-N(AR34))-(AT34-AS34-N(AU34))+(N(AQ34)+N(AR34))-(N(AU34)+N(AV34)))-((BF34-BI34-N(BJ34))-(BL34-N(BO34))+(BG34-BF34-N(BK34))-(BM34-BL34-N(BN34))+(N(BJ34)+N(BK34))-(N(BN34)+N(BO34))))/((AN34+BG34)/2),0) -> 0.069974913 | V34: =IFERROR((AK34-BD34)/((AN34+BG34)/2),0) -> 0.037479957 | W34: =IFERROR((N(AL34)-N(BE34))/((AN34+BG34)/2),0) -> 0.019033229 | X34: =IFERROR((AN34-N(AO34)-AP34)/AN34,0) -> 0.77814132 | Y34: =IF(COUNT(BP34,BQ34,BR34,BS34)=4,IFERROR((AD34-(AK34-BD34))/(AW34-(BD34-BP34))-1,0),0) -> 0.0057075881 | Z34: =IF(COUNT(BP34,BQ34,BR34,BS34)=4,IFERROR(AH34/((AN34+BG34)/2)-BA34/((BG34+BR34)/2),0),0) -> -0.0041658704 | AA34: =IF(N(AJ34)>0,1,0) -> 1 | AB34: =Inputs!$C$24+Inputs!$C$25*U34+Inputs!$C$26*V34+Inputs!$C$27*W34+Inputs!$C$28*X34+Inputs!$C$29*Y34+Inputs!$C$30*Z34+Inputs!$C$31*AA34 -> -5.1468764 | AD34: 3384.563 | AE34: 2872.019 | AF34: 186.063 | AG34: 28.804 | AH34: 91.153 | AI34: -36.658 | AJ34: 217.016 | AK34: 407.365 | AL34: 903.903 | AM34: 1639.65 | AN34: 1998.84 | AO34: 265.566 | AP34: 177.894 | AQ34: n/a | AR34: 1.571 | AS34: 781.996 | AT34: 944.892 | AU34: 27.867 | AV34: 57.503 | AW34: 3297.389 | AX34: 2762.662 | AY34: 227.442 | AZ34: 26.989 | BA34: 89.568 | BB34: 147.57 | BC34: 10 | BD34: 333.172 | BE34: 866.226 | BF34: 1648.359 | BG34: 1960.236 | BH34: 230.477 | BI34: 300.859 | BJ34: n/a | BK34: 1.571 | BL34: 784.823 | BM34: 921.841 | BN34: n/a | BO34: 33.158 | BP34: 327.366 | BQ34: 3627.788 | BR34: 1607.252 | BS34: 74.482
B35: 44377 | C35: 44435 | D35: yes | E35: =Inputs!$C$13+Inputs!$C$14*M35+Inputs!$C$15*N35+Inputs!$C$16*O35+Inputs!$C$17*P35+Inputs!$C$18*Q35+Inputs!$C$19*R35+Inputs!$C$20*S35+Inputs!$C$21*T35 -> -2.388449 | F35: =EXP(AB35)/(1+EXP(AB35))/Inputs!$C$32 -> 1.5649673 | G35: =IFERROR((AH35-AI35)/((AN35+BG35)/2),"n/a") -> -0.0053309491 | H35: =IFERROR(AI35/AH35,"n/a") -> 1.0991374 | I35: =IFERROR(AK35/AD35*365,"n/a") -> 47.590477 | J35: =IFERROR(N(AL35)/AE35*365,"n/a") -> 125.69184 | K35: =IF(E35>Inputs!$C$7,1,0) -> 0 | L35: =IF(F35>Inputs!$C$8,1,0) -> 0 | M35: =IFERROR((AK35/AD35)/(BD35/AW35),1) -> 1.0783829 | N35: =IFERROR(((AW35-AX35)/AW35)/((AD35-AE35)/AD35),1) -> 1.0487282 | O35: =IFERROR((1-(AM35+AO35)/AN35)/(1-(BF35+BH35)/BG35),1) -> 0.92912007 | P35: =IFERROR(AD35/AW35,1) -> 1.0653257 | Q35: =IFERROR((AZ35/(AZ35+BH35))/(AG35/(AG35+AO35)),1) -> 1.166727 | R35: =IFERROR((AF35/AD35)/(AY35/AW35),1) -> 0.79790245 | S35: =IFERROR((AH35-AI35)/AN35,0) -> -0.0049465558 | T35: =IFERROR(((AS35+N(AU35))/AN35)/((BL35+N(BN35))/BG35),1) -> 1.2040193 | U35: =IFERROR((((AM35-AP35-N(AQ35))-(AS35-N(AV35))+(AN35-AM35-N(AR35))-(AT35-AS35-N(AU35))+(N(AQ35)+N(AR35))-(N(AU35)+N(AV35)))-((BF35-BI35-N(BJ35))-(BL35-N(BO35))+(BG35-BF35-N(BK35))-(BM35-BL35-N(BN35))+(N(BJ35)+N(BK35))-(N(BN35)+N(BO35))))/((AN35+BG35)/2),0) -> 0.0043060993 | V35: =IFERROR((AK35-BD35)/((AN35+BG35)/2),0) -> 0.028884707 | W35: =IFERROR((N(AL35)-N(BE35))/((AN35+BG35)/2),0) -> 0.091076068 | X35: =IFERROR((AN35-N(AO35)-AP35)/AN35,0) -> 0.77386836 | Y35: =IF(COUNT(BP35,BQ35,BR35,BS35)=4,IFERROR((AD35-(AK35-BD35))/(AW35-(BD35-BP35))-1,0),0) -> 0.050515145 | Z35: =IF(COUNT(BP35,BQ35,BR35,BS35)=4,IFERROR(AH35/((AN35+BG35)/2)-BA35/((BG35+BR35)/2),0),0) -> 0.0069517146 | AA35: =IF(N(AJ35)>0,1,0) -> 1 | AB35: =Inputs!$C$24+Inputs!$C$25*U35+Inputs!$C$26*V35+Inputs!$C$27*W35+Inputs!$C$28*X35+Inputs!$C$29*Y35+Inputs!$C$30*Z35+Inputs!$C$31*AA35 -> -5.1457503 | AD35: 3557.422 | AE35: 3022.884 | AF35: 186.222 | AG35: 28.185 | AH35: 111.865 | AI35: 122.955 | AJ35: 127.059 | AK35: 463.834 | AL35: 1040.964 | AM35: 1867.259 | AN35: 2241.964 | AO35: 274.713 | AP35: 232.266 | AQ35: n/a | AR35: 1.556 | AS35: 968.896 | AT35: 1145.566 | AU35: 34.7 | AV35: 63.49 | AW35: 3339.281 | AX35: 2813.071 | AY35: 219.078 | AZ35: 28.472 | BA35: 84.308 | BB35: -30.334 | BC35: 164.791 | BD35: 403.745 | BE35: 851.498 | BF35: 1592.761 | BG35: 1918.646 | BH35: 233.785 | BI35: 210.533 | BJ35: n/a | BK35: 1.571 | BL35: 707.635 | BM35: 852.939 | BN35: 5.697 | BO35: 23.704 | BP35: 393.624 | BQ35: 3500.36 | BR35: 1682.594 | BS35: 71.918
B36: 44469 | C36: 44505 | D36: yes | E36: =Inputs!$C$13+Inputs!$C$14*M36+Inputs!$C$15*N36+Inputs!$C$16*O36+Inputs!$C$17*P36+Inputs!$C$18*Q36+Inputs!$C$19*R36+Inputs!$C$20*S36+Inputs!$C$21*T36 -> -1.7415841 | F36: =EXP(AB36)/(1+EXP(AB36))/Inputs!$C$32 -> 2.0019814 | G36: =IFERROR((AH36-AI36)/((AN36+BG36)/2),"n/a") -> 0.11447085 | H36: =IFERROR(AI36/AH36,"n/a") -> -1.1939459 | I36: =IFERROR(AK36/AD36*365,"n/a") -> 43.678689 | J36: =IFERROR(N(AL36)/AE36*365,"n/a") -> 131.61361 | K36: =IF(E36>Inputs!$C$7,1,0) -> 1 | L36: =IF(F36>Inputs!$C$8,1,0) -> 1 | M36: =IFERROR((AK36/AD36)/(BD36/AW36),1) -> 1.2238377 | N36: =IFERROR(((AW36-AX36)/AW36)/((AD36-AE36)/AD36),1) -> 1.1218418 | O36: =IFERROR((1-(AM36+AO36)/AN36)/(1-(BF36+BH36)/BG36),1) -> 0.82928815 | P36: =IFERROR(AD36/AW36,1) -> 1.1593636 | Q36: =IFERROR((AZ36/(AZ36+BH36))/(AG36/(AG36+AO36)),1) -> 1.1912541 | R36: =IFERROR((AF36/AD36)/(AY36/AW36),1) -> 0.74298031 | S36: =IFERROR((AH36-AI36)/AN36,0) -> 0.10008353 | T36: =IFERROR(((AS36+N(AU36))/AN36)/((BL36+N(BN36))/BG36),1) -> 1.4266803 | U36: =IFERROR((((AM36-AP36-N(AQ36))-(AS36-N(AV36))+(AN36-AM36-N(AR36))-(AT36-AS36-N(AU36))+(N(AQ36)+N(AR36))-(N(AU36)+N(AV36)))-((BF36-BI36-N(BJ36))-(BL36-N(BO36))+(BG36-BF36-N(BK36))-(BM36-BL36-N(BN36))+(N(BJ36)+N(BK36))-(N(BN36)+N(BO36))))/((AN36+BG36)/2),0) -> 0.042465145 | V36: =IFERROR((AK36-BD36)/((AN36+BG36)/2),0) -> 0.063737308 | W36: =IFERROR((N(AL36)-N(BE36))/((AN36+BG36)/2),0) -> 0.19357984 | X36: =IFERROR((AN36-N(AO36)-AP36)/AN36,0) -> 0.77162542 | Y36: =IF(COUNT(BP36,BQ36,BR36,BS36)=4,IFERROR((AD36-(AK36-BD36))/(AW36-(BD36-BP36))-1,0),0) -> 0.10721049 | Z36: =IF(COUNT(BP36,BQ36,BR36,BS36)=4,IFERROR(AH36/((AN36+BG36)/2)-BA36/((BG36+BR36)/2),0),0) -> 0.0041002788 | AA36: =IF(N(AJ36)>0,1,0) -> 1 | AB36: =Inputs!$C$24+Inputs!$C$25*U36+Inputs!$C$26*V36+Inputs!$C$27*W36+Inputs!$C$28*X36+Inputs!$C$29*Y36+Inputs!$C$30*Z36+Inputs!$C$31*AA36 -> -4.8978502 | AD36: 3827.902 | AE36: 3285.14 | AF36: 185.419 | AG36: 28.216 | AH36: 110.701 | AI36: -132.171 | AJ36: 390.457 | AK36: 458.076 | AL36: 1184.573 | AM36: 2036.955 | AN36: 2426.693 | AO36: 284.148 | AP36: 270.047 | AQ36: n/a | AR36: 1.556 | AS36: 1101.479 | AT36: 1293.895 | AU36: 45.134 | AV36: 233.674 | AW36: 3301.727 | AX36: 2776.531 | AY36: 215.257 | AZ36: 29.163 | BA36: 84.564 | BB36: 84.661 | BC36: 171.199 | BD36: 322.845 | BE36: 773.856 | BF36: 1479.521 | BG36: 1816.693 | BH36: 241.852 | BI36: 300.089 | BJ36: n/a | BK36: 1.571 | BL36: 589.688 | BM36: 743.951 | BN36: 11.98 | BO36: 24.047 | BP36: 356.23 | BQ36: 3329.046 | BR36: 1701.273 | BS36: 78.921
B37: 44561 | C37: 44596 | D37: yes | E37: =Inputs!$C$13+Inputs!$C$14*M37+Inputs!$C$15*N37+Inputs!$C$16*O37+Inputs!$C$17*P37+Inputs!$C$18*Q37+Inputs!$C$19*R37+Inputs!$C$20*S37+Inputs!$C$21*T37 -> -1.4524532 | F37: =EXP(AB37)/(1+EXP(AB37))/Inputs!$C$32 -> 2.4805434 | G37: =IFERROR((AH37-AI37)/((AN37+BG37)/2),"n/a") -> 0.16344548 | H37: =IFERROR(AI37/AH37,"n/a") -> -1.9892045 | I37: =IFERROR(AK37/AD37*365,"n/a") -> 43.539967 | J37: =IFERROR(N(AL37)/AE37*365,"n/a") -> 141.31836 | K37: =IF(E37>Inputs!$C$7,1,0) -> 1 | L37: =IF(F37>Inputs!$C$8,1,0) -> 1 | M37: =IFERROR((AK37/AD37)/(BD37/AW37),1) -> 1.2042794 | N37: =IFERROR(((AW37-AX37)/AW37)/((AD37-AE37)/AD37),1) -> 1.1721833 | O37: =IFERROR((1-(AM37+AO37)/AN37)/(1-(BF37+BH37)/BG37),1) -> 0.77240491 | P37: =IFERROR(AD37/AW37,1) -> 1.2787182 | Q37: =IFERROR((AZ37/(AZ37+BH37))/(AG37/(AG37+AO37)),1) -> 1.0731027 | R37: =IFERROR((AF37/AD37)/(AY37/AW37),1) -> 0.70771307 | S37: =IFERROR((AH37-AI37)/AN37,0) -> 0.13955306 | T37: =IFERROR(((AS37+N(AU37))/AN37)/((BL37+N(BN37))/BG37),1) -> 1.3658108 | U37: =IFERROR((((AM37-AP37-N(AQ37))-(AS37-N(AV37))+(AN37-AM37-N(AR37))-(AT37-AS37-N(AU37))+(N(AQ37)+N(AR37))-(N(AU37)+N(AV37)))-((BF37-BI37-N(BJ37))-(BL37-N(BO37))+(BG37-BF37-N(BK37))-(BM37-BL37-N(BN37))+(N(BJ37)+N(BK37))-(N(BN37)+N(BO37))))/((AN37+BG37)/2),0) -> 0.083501033 | V37: =IFERROR((AK37-BD37)/((AN37+BG37)/2),0) -> 0.076316972 | W37: =IFERROR((N(AL37)-N(BE37))/((AN37+BG37)/2),0) -> 0.25652278 | X37: =IFERROR((AN37-N(AO37)-AP37)/AN37,0) -> 0.80285115 | Y37: =IF(COUNT(BP37,BQ37,BR37,BS37)=4,IFERROR((AD37-(AK37-BD37))/(AW37-(BD37-BP37))-1,0),0) -> 0.21143513 | Z37: =IF(COUNT(BP37,BQ37,BR37,BS37)=4,IFERROR(AH37/((AN37+BG37)/2)-BA37/((BG37+BR37)/2),0),0) -> 0.0068378179 | AA37: =IF(N(AJ37)>0,1,0) -> 1 | AB37: =Inputs!$C$24+Inputs!$C$25*U37+Inputs!$C$26*V37+Inputs!$C$27*W37+Inputs!$C$28*X37+Inputs!$C$29*Y37+Inputs!$C$30*Z37+Inputs!$C$31*AA37 -> -4.6817244 | AD37: 4170.015 | AE37: 3599.605 | AF37: 186.641 | AG37: 29.439 | AH37: 124.959 | AI37: -248.569 | AJ37: 700.109 | AK37: 497.431 | AL37: 1393.672 | AM37: 2293.288 | AN37: 2676.602 | AO37: 280.282 | AP37: 247.407 | AQ37: n/a | AR37: 1.556 | AS37: 1199.579 | AT37: 1489.757 | AU37: 139.032 | AV37: 176.904 | AW37: 3261.09 | AX37: 2738.203 | AY37: 206.241 | AZ37: 29.01 | BA37: 88.532 | BB37: 66.315 | BC37: 179.46 | BD37: 323.021 | BE37: 807.431 | BF37: 1544.273 | BG37: 1894.072 | BH37: 255.406 | BI37: 315.61 | BJ37: n/a | BK37: 1.571 | BL37: 672.971 | BM37: 829.852 | BN37: 20.577 | BO37: 24.921 | BP37: 360.172 | BQ37: 3268.48 | BR37: 1807.039 | BS37: 84.407
B38: 44651 | C38: 44687 | D38: yes | E38: =Inputs!$C$13+Inputs!$C$14*M38+Inputs!$C$15*N38+Inputs!$C$16*O38+Inputs!$C$17*P38+Inputs!$C$18*Q38+Inputs!$C$19*R38+Inputs!$C$20*S38+Inputs!$C$21*T38 -> -1.2544473 | F38: =EXP(AB38)/(1+EXP(AB38))/Inputs!$C$32 -> 2.8046956 | G38: =IFERROR((AH38-AI38)/((AN38+BG38)/2),"n/a") -> 0.21128055 | H38: =IFERROR(AI38/AH38,"n/a") -> -1.9187425 | I38: =IFERROR(AK38/AD38*365,"n/a") -> 53.594315 | J38: =IFERROR(N(AL38)/AE38*365,"n/a") -> 145.99629 | K38: =IF(E38>Inputs!$C$7,1,0) -> 1 | L38: =IF(F38>Inputs!$C$8,1,0) -> 1 | M38: =IFERROR((AK38/AD38)/(BD38/AW38),1) -> 1.2199576 | N38: =IFERROR(((AW38-AX38)/AW38)/((AD38-AE38)/AD38),1) -> 1.0652156 | O38: =IFERROR((1-(AM38+AO38)/AN38)/(1-(BF38+BH38)/BG38),1) -> 0.76567223 | P38: =IFERROR(AD38/AW38,1) -> 1.3678646 | Q38: =IFERROR((AZ38/(AZ38+BH38))/(AG38/(AG38+AO38)),1) -> 0.99098944 | R38: =IFERROR((AF38/AD38)/(AY38/AW38),1) -> 0.74150621 | S38: =IFERROR((AH38-AI38)/AN38,0) -> 0.17439503 | T38: =IFERROR(((AS38+N(AU38))/AN38)/((BL38+N(BN38))/BG38),1) -> 1.3184344 | U38: =IFERROR((((AM38-AP38-N(AQ38))-(AS38-N(AV38))+(AN38-AM38-N(AR38))-(AT38-AS38-N(AU38))+(N(AQ38)+N(AR38))-(N(AU38)+N(AV38)))-((BF38-BI38-N(BJ38))-(BL38-N(BO38))+(BG38-BF38-N(BK38))-(BM38-BL38-N(BN38))+(N(BJ38)+N(BK38))-(N(BN38)+N(BO38))))/((AN38+BG38)/2),0) -> 0.059345363 | V38: =IFERROR((AK38-BD38)/((AN38+BG38)/2),0) -> 0.10746315 | W38: =IFERROR((N(AL38)-N(BE38))/((AN38+BG38)/2),0) -> 0.27007365 | X38: =IFERROR((AN38-N(AO38)-AP38)/AN38,0) -> 0.82751141 | Y38: =IF(COUNT(BP38,BQ38,BR38,BS38)=4,IFERROR((AD38-(AK38-BD38))/(AW38-(BD38-BP38))-1,0),0) -> 0.3162287 | Z38: =IF(COUNT(BP38,BQ38,BR38,BS38)=4,IFERROR(AH38/((AN38+BG38)/2)-BA38/((BG38+BR38)/2),0),0) -> 0.026339915 | AA38: =IF(N(AJ38)>0,1,0) -> 1 | AB38: =Inputs!$C$24+Inputs!$C$25*U38+Inputs!$C$26*V38+Inputs!$C$27*W38+Inputs!$C$28*X38+Inputs!$C$29*Y38+Inputs!$C$30*Z38+Inputs!$C$31*AA38 -> -4.5576959 | AD38: 4629.624 | AE38: 3971.456 | AF38: 188.72 | AG38: 30.93 | AH38: 183.503 | AI38: -352.095 | AJ38: 1002.909 | AK38: 679.785 | AL38: 1588.542 | AM38: 2678.715 | AN38: 3071.177 | AO38: 282.319 | AP38: 247.424 | AQ38: n/a | AR38: 1.556 | AS38: 1496.155 | AT38: 1797.258 | AU38: 144.423 | AV38: 403.045 | AW38: 3384.563 | AX38: 2872.019 | AY38: 186.063 | AZ38: 28.804 | BA38: 91.153 | BB38: -36.658 | BC38: 217.016 | BD38: 407.365 | BE38: 903.903 | BF38: 1639.65 | BG38: 1998.84 | BH38: 265.566 | BI38: 177.894 | BJ38: n/a | BK38: 1.571 | BL38: 781.996 | BM38: 944.892 | BN38: 27.867 | BO38: 57.503 | BP38: 333.172 | BQ38: 3297.389 | BR38: 1960.236 | BS38: 89.568
B39: 44742 | C39: 44802 | D39: yes | E39: =Inputs!$C$13+Inputs!$C$14*M39+Inputs!$C$15*N39+Inputs!$C$16*O39+Inputs!$C$17*P39+Inputs!$C$18*Q39+Inputs!$C$19*R39+Inputs!$C$20*S39+Inputs!$C$21*T39 -> -0.89551086 | F39: =EXP(AB39)/(1+EXP(AB39))/Inputs!$C$32 -> 2.7969707 | G39: =IFERROR((AH39-AI39)/((AN39+BG39)/2),"n/a") -> 0.26655353 | H39: =IFERROR(AI39/AH39,"n/a") -> -1.5457861 | I39: =IFERROR(AK39/AD39*365,"n/a") -> 58.62037 | J39: =IFERROR(N(AL39)/AE39*365,"n/a") -> 128.32885 | K39: =IF(E39>Inputs!$C$7,1,0) -> 1 | L39: =IF(F39>Inputs!$C$8,1,0) -> 1 | M39: =IFERROR((AK39/AD39)/(BD39/AW39),1) -> 1.2317668 | N39: =IFERROR(((AW39-AX39)/AW39)/((AD39-AE39)/AD39),1) -> 0.97595566 | O39: =IFERROR((1-(AM39+AO39)/AN39)/(1-(BF39+BH39)/BG39),1) -> 0.78903362 | P39: =IFERROR(AD39/AW39,1) -> 1.4606361 | Q39: =IFERROR((AZ39/(AZ39+BH39))/(AG39/(AG39+AO39)),1) -> 0.91255212 | R39: =IFERROR((AF39/AD39)/(AY39/AW39),1) -> 0.70793815 | S39: =IFERROR((AH39-AI39)/AN39,0) -> 0.22650439 | T39: =IFERROR(((AS39+N(AU39))/AN39)/((BL39+N(BN39))/BG39),1) -> 1.1274925 | U39: =IFERROR((((AM39-AP39-N(AQ39))-(AS39-N(AV39))+(AN39-AM39-N(AR39))-(AT39-AS39-N(AU39))+(N(AQ39)+N(AR39))-(N(AU39)+N(AV39)))-((BF39-BI39-N(BJ39))-(BL39-N(BO39))+(BG39-BF39-N(BK39))-(BM39-BL39-N(BN39))+(N(BJ39)+N(BK39))-(N(BN39)+N(BO39))))/((AN39+BG39)/2),0) -> 0.10802856 | V39: =IFERROR((AK39-BD39)/((AN39+BG39)/2),0) -> 0.13610289 | W39: =IFERROR((N(AL39)-N(BE39))/((AN39+BG39)/2),0) -> 0.18529033 | X39: =IFERROR((AN39-N(AO39)-AP39)/AN39,0) -> 0.82734611 | Y39: =IF(COUNT(BP39,BQ39,BR39,BS39)=4,IFERROR((AD39-(AK39-BD39))/(AW39-(BD39-BP39))-1,0),0) -> 0.37974279 | Z39: =IF(COUNT(BP39,BQ39,BR39,BS39)=4,IFERROR(AH39/((AN39+BG39)/2)-BA39/((BG39+BR39)/2),0),0) -> 0.050930455 | AA39: =IF(N(AJ39)>0,1,0) -> 1 | AB39: =Inputs!$C$24+Inputs!$C$25*U39+Inputs!$C$26*V39+Inputs!$C$27*W39+Inputs!$C$28*X39+Inputs!$C$29*Y39+Inputs!$C$30*Z39+Inputs!$C$31*AA39 -> -4.5604828 | AD39: 5196.099 | AE39: 4396.098 | AF39: 192.561 | AG39: 32.471 | AH39: 285.163 | AI39: -440.801 | AJ39: 1153.317 | AK39: 834.513 | AL39: 1545.606 | AM39: 2806.315 | AN39: 3205.077 | AO39: 285.972 | AP39: 267.397 | AQ39: n/a | AR39: 1.59 | AS39: 1470.024 | AT39: 1779.33 | AU39: 147.618 | AV39: 449.146 | AW39: 3557.422 | AX39: 3022.884 | AY39: 186.222 | AZ39: 28.185 | BA39: 111.865 | BB39: 122.955 | BC39: 127.059 | BD39: 463.834 | BE39: 1040.964 | BF39: 1867.259 | BG39: 2241.964 | BH39: 274.713 | BI39: 232.266 | BJ39: n/a | BK39: 1.556 | BL39: 968.896 | BM39: 1145.566 | BN39: 34.7 | BO39: 63.49 | BP39: 403.745 | BQ39: 3339.281 | BR39: 1918.646 | BS39: 84.308
B40: 44834 | C40: 44869 | D40: yes | E40: =Inputs!$C$13+Inputs!$C$14*M40+Inputs!$C$15*N40+Inputs!$C$16*O40+Inputs!$C$17*P40+Inputs!$C$18*Q40+Inputs!$C$19*R40+Inputs!$C$20*S40+Inputs!$C$21*T40 -> -1.3979046 | F40: =EXP(AB40)/(1+EXP(AB40))/Inputs!$C$32 -> 2.7304474 | G40: =IFERROR((AH40-AI40)/((AN40+BG40)/2),"n/a") -> 0.15250937 | H40: =IFERROR(AI40/AH40,"n/a") -> 0.016564522 | I40: =IFERROR(AK40/AD40*365,"n/a") -> 44.676905 | J40: =IFERROR(N(AL40)/AE40*365,"n/a") -> 126.57754 | K40: =IF(E40>Inputs!$C$7,1,0) -> 1 | L40: =IF(F40>Inputs!$C$8,1,0) -> 1 | M40: =IFERROR((AK40/AD40)/(BD40/AW40),1) -> 1.0228536 | N40: =IFERROR(((AW40-AX40)/AW40)/((AD40-AE40)/AD40),1) -> 0.84500304 | O40: =IFERROR((1-(AM40+AO40)/AN40)/(1-(BF40+BH40)/BG40),1) -> 0.90954048 | P40: =IFERROR(AD40/AW40,1) -> 1.5714872 | Q40: =IFERROR((AZ40/(AZ40+BH40))/(AG40/(AG40+AO40)),1) -> 0.87502657 | R40: =IFERROR((AF40/AD40)/(AY40/AW40),1) -> 0.69277066 | S40: =IFERROR((AH40-AI40)/AN40,0) -> 0.13230765 | T40: =IFERROR(((AS40+N(AU40))/AN40)/((BL40+N(BN40))/BG40),1) -> 0.96284853 | U40: =IFERROR((((AM40-AP40-N(AQ40))-(AS40-N(AV40))+(AN40-AM40-N(AR40))-(AT40-AS40-N(AU40))+(N(AQ40)+N(AR40))-(N(AU40)+N(AV40)))-((BF40-BI40-N(BJ40))-(BL40-N(BO40))+(BG40-BF40-N(BK40))-(BM40-BL40-N(BN40))+(N(BJ40)+N(BK40))-(N(BN40)+N(BO40))))/((AN40+BG40)/2),0) -> 0.18302591 | V40: =IFERROR((AK40-BD40)/((AN40+BG40)/2),0) -> 0.097149848 | W40: =IFERROR((N(AL40)-N(BE40))/((AN40+BG40)/2),0) -> 0.19255737 | X40: =IFERROR((AN40-N(AO40)-AP40)/AN40,0) -> 0.83975321 | Y40: =IF(COUNT(BP40,BQ40,BR40,BS40)=4,IFERROR((AD40-(AK40-BD40))/(AW40-(BD40-BP40))-1,0),0) -> 0.55368919 | Z40: =IF(COUNT(BP40,BQ40,BR40,BS40)=4,IFERROR(AH40/((AN40+BG40)/2)-BA40/((BG40+BR40)/2),0),0) -> 0.10290238 | AA40: =IF(N(AJ40)>0,1,0) -> 1 | AB40: =Inputs!$C$24+Inputs!$C$25*U40+Inputs!$C$26*V40+Inputs!$C$27*W40+Inputs!$C$28*X40+Inputs!$C$29*Y40+Inputs!$C$30*Z40+Inputs!$C$31*AA40 -> -4.5848029 | AD40: 6015.499 | AE40: 5006.102 | AF40: 201.862 | AG40: 33.47 | AH40: 444.142 | AI40: 7.357 | AJ40: 962.652 | AK40: 736.312 | AL40: 1736.055 | AM40: 2879.88 | AN40: 3301.283 | AO40: 290.752 | AP40: 238.268 | AQ40: n/a | AR40: 1.59 | AS40: 1353.355 | AT40: 1676.08 | AU40: 148.551 | AV40: 101.173 | AW40: 3827.902 | AX40: 3285.14 | AY40: 185.419 | AZ40: 28.216 | BA40: 110.701 | BB40: -132.171 | BC40: 390.457 | BD40: 458.076 | BE40: 1184.573 | BF40: 2036.955 | BG40: 2426.693 | BH40: 284.148 | BI40: 270.047 | BJ40: n/a | BK40: 1.556 | BL40: 1101.479 | BM40: 1293.895 | BN40: 45.134 | BO40: 233.674 | BP40: 322.845 | BQ40: 3301.727 | BR40: 1816.693 | BS40: 84.564
B41: 44926 | C41: 44960 | D41: yes | E41: =Inputs!$C$13+Inputs!$C$14*M41+Inputs!$C$15*N41+Inputs!$C$16*O41+Inputs!$C$17*P41+Inputs!$C$18*Q41+Inputs!$C$19*R41+Inputs!$C$20*S41+Inputs!$C$21*T41 -> -1.3539356 | F41: =EXP(AB41)/(1+EXP(AB41))/Inputs!$C$32 -> 2.0072345 | G41: =IFERROR((AH41-AI41)/((AN41+BG41)/2),"n/a") -> 0.12406477 | H41: =IFERROR(AI41/AH41,"n/a") -> 0.38313246 | I41: =IFERROR(AK41/AD41*365,"n/a") -> 42.18618 | J41: =IFERROR(N(AL41)/AE41*365,"n/a") -> 94.99255 | K41: =IF(E41>Inputs!$C$7,1,0) -> 1 | L41: =IF(F41>Inputs!$C$8,1,0) -> 1 | M41: =IFERROR((AK41/AD41)/(BD41/AW41),1) -> 0.96890704 | N41: =IFERROR(((AW41-AX41)/AW41)/((AD41-AE41)/AD41),1) -> 0.76844922 | O41: =IFERROR((1-(AM41+AO41)/AN41)/(1-(BF41+BH41)/BG41),1) -> 1.1505376 | P41: =IFERROR(AD41/AW41,1) -> 1.5938252 | Q41: =IFERROR((AZ41/(AZ41+BH41))/(AG41/(AG41+AO41)),1) -> 0.90402156 | R41: =IFERROR((AF41/AD41)/(AY41/AW41),1) -> 0.69310126 | S41: =IFERROR((AH41-AI41)/AN41,0) -> 0.11602886 | T41: =IFERROR(((AS41+N(AU41))/AN41)/((BL41+N(BN41))/BG41),1) -> 0.68877247 | U41: =IFERROR((((AM41-AP41-N(AQ41))-(AS41-N(AV41))+(AN41-AM41-N(AR41))-(AT41-AS41-N(AU41))+(N(AQ41)+N(AR41))-(N(AU41)+N(AV41)))-((BF41-BI41-N(BJ41))-(BL41-N(BO41))+(BG41-BF41-N(BK41))-(BM41-BL41-N(BN41))+(N(BJ41)+N(BK41))-(N(BN41)+N(BO41))))/((AN41+BG41)/2),0) -> 0.19987989 | V41: =IFERROR((AK41-BD41)/((AN41+BG41)/2),0) -> 0.094143764 | W41: =IFERROR((N(AL41)-N(BE41))/((AN41+BG41)/2),0) -> 0.0097869372 | X41: =IFERROR((AN41-N(AO41)-AP41)/AN41,0) -> 0.80687441 | Y41: =IF(COUNT(BP41,BQ41,BR41,BS41)=4,IFERROR((AD41-(AK41-BD41))/(AW41-(BD41-BP41))-1,0),0) -> 0.59563796 | Z41: =IF(COUNT(BP41,BQ41,BR41,BS41)=4,IFERROR(AH41/((AN41+BG41)/2)-BA41/((BG41+BR41)/2),0),0) -> 0.14644202 | AA41: =IF(N(AJ41)>0,1,0) -> 1 | AB41: =Inputs!$C$24+Inputs!$C$25*U41+Inputs!$C$26*V41+Inputs!$C$27*W41+Inputs!$C$28*X41+Inputs!$C$29*Y41+Inputs!$C$30*Z41+Inputs!$C$31*AA41 -> -4.8952101 | AD41: 6646.275 | AE41: 5463.199 | AF41: 206.179 | AG41: 33.986 | AH41: 578.377 | AI41: 221.595 | AJ41: 709.635 | AK41: 768.167 | AL41: 1421.817 | AM41: 2649.503 | AN41: 3074.942 | AO41: 289.255 | AP41: 304.595 | AQ41: n/a | AR41: 1.59 | AS41: 916.94 | AT41: 1256.1 | AU41: 142.273 | AV41: n/a | AW41: 4170.015 | AX41: 3599.605 | AY41: 186.641 | AZ41: 29.439 | BA41: 124.959 | BB41: -248.569 | BC41: 700.109 | BD41: 497.431 | BE41: 1393.672 | BF41: 2293.288 | BG41: 2676.602 | BH41: 280.282 | BI41: 247.407 | BJ41: n/a | BK41: 1.556 | BL41: 1199.579 | BM41: 1489.757 | BN41: 139.032 | BO41: 176.904 | BP41: 323.021 | BQ41: 3261.09 | BR41: 1894.072 | BS41: 88.532
B42: 45016 | C42: 45051 | D42: yes | E42: =Inputs!$C$13+Inputs!$C$14*M42+Inputs!$C$15*N42+Inputs!$C$16*O42+Inputs!$C$17*P42+Inputs!$C$18*Q42+Inputs!$C$19*R42+Inputs!$C$20*S42+Inputs!$C$21*T42 -> -2.2085319 | F42: =EXP(AB42)/(1+EXP(AB42))/Inputs!$C$32 -> 1.4270685 | G42: =IFERROR((AH42-AI42)/((AN42+BG42)/2),"n/a") -> -0.019325388 | H42: =IFERROR(AI42/AH42,"n/a") -> 1.103065 | I42: =IFERROR(AK42/AD42*365,"n/a") -> 37.313212 | J42: =IFERROR(N(AL42)/AE42*365,"n/a") -> 104.597 | K42: =IF(E42>Inputs!$C$7,1,0) -> 0 | L42: =IF(F42>Inputs!$C$8,1,0) -> 0 | M42: =IFERROR((AK42/AD42)/(BD42/AW42),1) -> 0.69621585 | N42: =IFERROR(((AW42-AX42)/AW42)/((AD42-AE42)/AD42),1) -> 0.77970457 | O42: =IFERROR((1-(AM42+AO42)/AN42)/(1-(BF42+BH42)/BG42),1) -> 1.6366342 | P42: =IFERROR(AD42/AW42,1) -> 1.4200032 | Q42: =IFERROR((AZ42/(AZ42+BH42))/(AG42/(AG42+AO42)),1) -> 0.93235875 | R42: =IFERROR((AF42/AD42)/(AY42/AW42),1) -> 0.76800392 | S42: =IFERROR((AH42-AI42)/AN42,0) -> -0.018957879 | T42: =IFERROR(((AS42+N(AU42))/AN42)/((BL42+N(BN42))/BG42),1) -> 0.71864925 | U42: =IFERROR((((AM42-AP42-N(AQ42))-(AS42-N(AV42))+(AN42-AM42-N(AR42))-(AT42-AS42-N(AU42))+(N(AQ42)+N(AR42))-(N(AU42)+N(AV42)))-((BF42-BI42-N(BJ42))-(BL42-N(BO42))+(BG42-BF42-N(BK42))-(BM42-BL42-N(BN42))+(N(BJ42)+N(BK42))-(N(BN42)+N(BO42))))/((AN42+BG42)/2),0) -> 0.12110162 | V42: =IFERROR((AK42-BD42)/((AN42+BG42)/2),0) -> -0.0024681578 | W42: =IFERROR((N(AL42)-N(BE42))/((AN42+BG42)/2),0) -> -0.01536548 | X42: =IFERROR((AN42-N(AO42)-AP42)/AN42,0) -> 0.7955152 | Y42: =IF(COUNT(BP42,BQ42,BR42,BS42)=4,IFERROR((AD42-(AK42-BD42))/(AW42-(BD42-BP42))-1,0),0) -> 0.51055838 | Z42: =IF(COUNT(BP42,BQ42,BR42,BS42)=4,IFERROR(AH42/((AN42+BG42)/2)-BA42/((BG42+BR42)/2),0),0) -> 0.11511935 | AA42: =IF(N(AJ42)>0,1,0) -> 1 | AB42: =Inputs!$C$24+Inputs!$C$25*U42+Inputs!$C$26*V42+Inputs!$C$27*W42+Inputs!$C$28*X42+Inputs!$C$29*Y42+Inputs!$C$30*Z42+Inputs!$C$31*AA42 -> -5.238506 | AD42: 6574.081 | AE42: 5375.421 | AF42: 205.812 | AG42: 34.354 | AH42: 587.251 | AI42: 647.776 | AJ42: 379.568 | AK42: 672.055 | AL42: 1540.419 | AM42: 2715.175 | AN42: 3192.604 | AO42: 290.038 | AP42: 362.801 | AQ42: n/a | AR42: 1.59 | AS42: 1092.38 | AT42: 1424.031 | AU42: 133.235 | AV42: n/a | AW42: 4629.624 | AX42: 3971.456 | AY42: 188.72 | AZ42: 30.93 | BA42: 183.503 | BB42: -352.095 | BC42: 1002.909 | BD42: 679.785 | BE42: 1588.542 | BF42: 2678.715 | BG42: 3071.177 | BH42: 282.319 | BI42: 247.424 | BJ42: n/a | BK42: 1.556 | BL42: 1496.155 | BM42: 1797.258 | BN42: 144.423 | BO42: 403.045 | BP42: 407.365 | BQ42: 3384.563 | BR42: 1998.84 | BS42: 91.153
B43: 45107 | C43: 45166 | D43: yes | E43: =Inputs!$C$13+Inputs!$C$14*M43+Inputs!$C$15*N43+Inputs!$C$16*O43+Inputs!$C$17*P43+Inputs!$C$18*Q43+Inputs!$C$19*R43+Inputs!$C$20*S43+Inputs!$C$21*T43 -> -1.9259469 | F43: =EXP(AB43)/(1+EXP(AB43))/Inputs!$C$32 -> 1.8030647 | G43: =IFERROR((AH43-AI43)/((AN43+BG43)/2),"n/a") -> -0.0068554259 | H43: =IFERROR(AI43/AH43,"n/a") -> 1.036847 | I43: =IFERROR(AK43/AD43*365,"n/a") -> 58.835628 | J43: =IFERROR(N(AL43)/AE43*365,"n/a") -> 90.340479 | K43: =IF(E43>Inputs!$C$7,1,0) -> 0 | L43: =IF(F43>Inputs!$C$8,1,0) -> 0 | M43: =IFERROR((AK43/AD43)/(BD43/AW43),1) -> 1.0036721 | N43: =IFERROR(((AW43-AX43)/AW43)/((AD43-AE43)/AD43),1) -> 0.8548201 | O43: =IFERROR((1-(AM43+AO43)/AN43)/(1-(BF43+BH43)/BG43),1) -> 1.5857323 | P43: =IFERROR(AD43/AW43,1) -> 1.3709288 | Q43: =IFERROR((AZ43/(AZ43+BH43))/(AG43/(AG43+AO43)),1) -> 0.94987072 | R43: =IFERROR((AF43/AD43)/(AY43/AW43),1) -> 0.81295538 | S43: =IFERROR((AH43-AI43)/AN43,0) -> -0.006417344 | T43: =IFERROR(((AS43+N(AU43))/AN43)/((BL43+N(BN43))/BG43),1) -> 0.80597734 | U43: =IFERROR((((AM43-AP43-N(AQ43))-(AS43-N(AV43))+(AN43-AM43-N(AR43))-(AT43-AS43-N(AU43))+(N(AQ43)+N(AR43))-(N(AU43)+N(AV43)))-((BF43-BI43-N(BJ43))-(BL43-N(BO43))+(BG43-BF43-N(BK43))-(BM43-BL43-N(BN43))+(N(BJ43)+N(BK43))-(N(BN43)+N(BO43))))/((AN43+BG43)/2),0) -> 0.10853823 | V43: =IFERROR((AK43-BD43)/((AN43+BG43)/2),0) -> 0.091207804 | W43: =IFERROR((N(AL43)-N(BE43))/((AN43+BG43)/2),0) -> -0.029082797 | X43: =IFERROR((AN43-N(AO43)-AP43)/AN43,0) -> 0.80115568 | Y43: =IF(COUNT(BP43,BQ43,BR43,BS43)=4,IFERROR((AD43-(AK43-BD43))/(AW43-(BD43-BP43))-1,0),0) -> 0.41122141 | Z43: =IF(COUNT(BP43,BQ43,BR43,BS43)=4,IFERROR(AH43/((AN43+BG43)/2)-BA43/((BG43+BR43)/2),0),0) -> 0.081347357 | AA43: =IF(N(AJ43)>0,1,0) -> 1 | AB43: =Inputs!$C$24+Inputs!$C$25*U43+Inputs!$C$26*V43+Inputs!$C$27*W43+Inputs!$C$28*X43+Inputs!$C$29*Y43+Inputs!$C$30*Z43+Inputs!$C$31*AA43 -> -5.0032409 | AD43: 7123.482 | AE43: 5840.47 | AF43: 214.61 | AG43: 34.904 | AH43: 639.998 | AI43: 663.58 | AJ43: 1093.86 | AK43: 1148.259 | AL43: 1445.564 | AM43: 3179.426 | AN43: 3674.729 | AO43: 290.24 | AP43: 440.459 | AQ43: n/a | AR43: n/a | AS43: 1374.652 | AT43: 1702.559 | AU43: 120.179 | AV43: 170.123 | AW43: 5196.099 | AX43: 4396.098 | AY43: 192.561 | AZ43: 32.471 | BA43: 285.163 | BB43: -440.801 | BC43: 1153.317 | BD43: 834.513 | BE43: 1545.606 | BF43: 2806.315 | BG43: 3205.077 | BH43: 285.972 | BI43: 267.397 | BJ43: n/a | BK43: 1.59 | BL43: 1470.024 | BM43: 1779.33 | BN43: 147.618 | BO43: 449.146 | BP43: 463.834 | BQ43: 3557.422 | BR43: 2241.964 | BS43: 111.865
B44: 45199 | C44: 45233 | D44: yes | E44: =Inputs!$C$13+Inputs!$C$14*M44+Inputs!$C$15*N44+Inputs!$C$16*O44+Inputs!$C$17*P44+Inputs!$C$18*Q44+Inputs!$C$19*R44+Inputs!$C$20*S44+Inputs!$C$21*T44 -> -2.1545308 | F44: =EXP(AB44)/(1+EXP(AB44))/Inputs!$C$32 -> 1.7638542 | G44: =IFERROR((AH44-AI44)/((AN44+BG44)/2),"n/a") -> -0.0021307927 | H44: =IFERROR(AI44/AH44,"n/a") -> 1.0128653 | I44: =IFERROR(AK44/AD44*365,"n/a") -> 41.765672 | J44: =IFERROR(N(AL44)/AE44*365,"n/a") -> 122.79441 | K44: =IF(E44>Inputs!$C$7,1,0) -> 0 | L44: =IF(F44>Inputs!$C$8,1,0) -> 0 | M44: =IFERROR((AK44/AD44)/(BD44/AW44),1) -> 0.93483807 | N44: =IFERROR(((AW44-AX44)/AW44)/((AD44-AE44)/AD44),1) -> 0.96202298 | O44: =IFERROR((1-(AM44+AO44)/AN44)/(1-(BF44+BH44)/BG44),1) -> 1.440218 | P44: =IFERROR(AD44/AW44,1) -> 1.2286635 | Q44: =IFERROR((AZ44/(AZ44+BH44))/(AG44/(AG44+AO44)),1) -> 0.95109999 | R44: =IFERROR((AF44/AD44)/(AY44/AW44),1) -> 0.93377373 | S44: =IFERROR((AH44-AI44)/AN44,0) -> -0.0019240892 | T44: =IFERROR(((AS44+N(AU44))/AN44)/((BL44+N(BN44))/BG44),1) -> 0.91776885 | U44: =IFERROR((((AM44-AP44-N(AQ44))-(AS44-N(AV44))+(AN44-AM44-N(AR44))-(AT44-AS44-N(AU44))+(N(AQ44)+N(AR44))-(N(AU44)+N(AV44)))-((BF44-BI44-N(BJ44))-(BL44-N(BO44))+(BG44-BF44-N(BK44))-(BM44-BL44-N(BN44))+(N(BJ44)+N(BK44))-(N(BN44)+N(BO44))))/((AN44+BG44)/2),0) -> 0.063658277 | V44: =IFERROR((AK44-BD44)/((AN44+BG44)/2),0) -> 0.029583168 | W44: =IFERROR((N(AL44)-N(BE44))/((AN44+BG44)/2),0) -> 0.085639968 | X44: =IFERROR((AN44-N(AO44)-AP44)/AN44,0) -> 0.79618351 | Y44: =IF(COUNT(BP44,BQ44,BR44,BS44)=4,IFERROR((AD44-(AK44-BD44))/(AW44-(BD44-BP44))-1,0),0) -> 0.26917783 | Z44: =IF(COUNT(BP44,BQ44,BR44,BS44)=4,IFERROR(AH44/((AN44+BG44)/2)-BA44/((BG44+BR44)/2),0),0) -> 0.010544804 | AA44: =IF(N(AJ44)>0,1,0) -> 1 | AB44: =Inputs!$C$24+Inputs!$C$25*U44+Inputs!$C$26*V44+Inputs!$C$27*W44+Inputs!$C$28*X44+Inputs!$C$29*Y44+Inputs!$C$30*Z44+Inputs!$C$31*AA44 -> -5.0253735 | AD44: 7391.024 | AE44: 6101.856 | AF44: 231.595 | AG44: 35.512 | AH44: 612.577 | AI44: 620.458 | AJ44: 1014.719 | AK44: 845.729 | AL44: 2052.805 | AM44: 3570.834 | AN44: 4095.964 | AO44: 291.669 | AP44: 543.156 | AQ44: n/a | AR44: n/a | AS44: 1604.821 | AT44: 1930.425 | AU44: 105.389 | AV44: n/a | AW44: 6015.499 | AX44: 5006.102 | AY44: 201.862 | AZ44: 33.47 | BA44: 444.142 | BB44: 7.357 | BC44: 962.652 | BD44: 736.312 | BE44: 1736.055 | BF44: 2879.88 | BG44: 3301.283 | BH44: 290.752 | BI44: 238.268 | BJ44: n/a | BK44: 1.59 | BL44: 1353.355 | BM44: 1676.08 | BN44: 148.551 | BO44: 101.173 | BP44: 458.076 | BQ44: 3827.902 | BR44: 2426.693 | BS44: 110.701
B45: 45291 | C45: 45324 | D45: yes | E45: =Inputs!$C$13+Inputs!$C$14*M45+Inputs!$C$15*N45+Inputs!$C$16*O45+Inputs!$C$17*P45+Inputs!$C$18*Q45+Inputs!$C$19*R45+Inputs!$C$20*S45+Inputs!$C$21*T45 -> -0.94695753 | F45: =EXP(AB45)/(1+EXP(AB45))/Inputs!$C$32 -> 3.6553813 | G45: =IFERROR((AH45-AI45)/((AN45+BG45)/2),"n/a") -> 0.20474008 | H45: =IFERROR(AI45/AH45,"n/a") -> -0.18530595 | I45: =IFERROR(AK45/AD45*365,"n/a") -> 59.288778 | J45: =IFERROR(N(AL45)/AE45*365,"n/a") -> 116.38756 | K45: =IF(E45>Inputs!$C$7,1,0) -> 1 | L45: =IF(F45>Inputs!$C$8,1,0) -> 1 | M45: =IFERROR((AK45/AD45)/(BD45/AW45),1) -> 1.4054076 | N45: =IFERROR(((AW45-AX45)/AW45)/((AD45-AE45)/AD45),1) -> 1.0863922 | O45: =IFERROR((1-(AM45+AO45)/AN45)/(1-(BF45+BH45)/BG45),1) -> 1.1093025 | P45: =IFERROR(AD45/AW45,1) -> 1.3921713 | Q45: =IFERROR((AZ45/(AZ45+BH45))/(AG45/(AG45+AO45)),1) -> 0.96136782 | R45: =IFERROR((AF45/AD45)/(AY45/AW45),1) -> 0.9200538 | S45: =IFERROR((AH45-AI45)/AN45,0) -> 0.16060907 | T45: =IFERROR(((AS45+N(AU45))/AN45)/((BL45+N(BN45))/BG45),1) -> 1.123304 | U45: =IFERROR((((AM45-AP45-N(AQ45))-(AS45-N(AV45))+(AN45-AM45-N(AR45))-(AT45-AS45-N(AU45))+(N(AQ45)+N(AR45))-(N(AU45)+N(AV45)))-((BF45-BI45-N(BJ45))-(BL45-N(BO45))+(BG45-BF45-N(BK45))-(BM45-BL45-N(BN45))+(N(BJ45)+N(BK45))-(N(BN45)+N(BO45))))/((AN45+BG45)/2),0) -> 0.1974464 | V45: =IFERROR((AK45-BD45)/((AN45+BG45)/2),0) -> 0.17330402 | W45: =IFERROR((N(AL45)-N(BE45))/((AN45+BG45)/2),0) -> 0.2465064 | X45: =IFERROR((AN45-N(AO45)-AP45)/AN45,0) -> 0.81077484 | Y45: =IF(COUNT(BP45,BQ45,BR45,BS45)=4,IFERROR((AD45-(AK45-BD45))/(AW45-(BD45-BP45))-1,0),0) -> 0.3360359 | Z45: =IF(COUNT(BP45,BQ45,BR45,BS45)=4,IFERROR(AH45/((AN45+BG45)/2)-BA45/((BG45+BR45)/2),0),0) -> -0.028388762 | AA45: =IF(N(AJ45)>0,1,0) -> 1 | AB45: =Inputs!$C$24+Inputs!$C$25*U45+Inputs!$C$26*V45+Inputs!$C$27*W45+Inputs!$C$28*X45+Inputs!$C$29*Y45+Inputs!$C$30*Z45+Inputs!$C$31*AA45 -> -4.2896048 | AD45: 9252.753 | AE45: 7736.685 | AF45: 264.089 | AG45: 36.483 | AH45: 732.378 | AI45: -135.714 | AJ45: 1807.506 | AK45: 1502.971 | AL45: 2466.997 | AM45: 4842.355 | AN45: 5405 | AO45: 297.102 | AP45: 725.66 | AQ45: n/a | AR45: n/a | AS45: 1992.089 | AT45: 2327.926 | AU45: 99.322 | AV45: n/a | AW45: 6646.275 | AX45: 5463.199 | AY45: 206.179 | AZ45: 33.986 | BA45: 578.377 | BB45: 221.595 | BC45: 709.635 | BD45: 768.167 | BE45: 1421.817 | BF45: 2649.503 | BG45: 3074.942 | BH45: 289.255 | BI45: 304.595 | BJ45: n/a | BK45: 1.59 | BL45: 916.94 | BM45: 1256.1 | BN45: 142.273 | BO45: n/a | BP45: 497.431 | BQ45: 4170.015 | BR45: 2676.602 | BS45: 124.959
B46: 45382 | C46: 45418 | D46: yes | E46: =Inputs!$C$13+Inputs!$C$14*M46+Inputs!$C$15*N46+Inputs!$C$16*O46+Inputs!$C$17*P46+Inputs!$C$18*Q46+Inputs!$C$19*R46+Inputs!$C$20*S46+Inputs!$C$21*T46 -> 0.29098257 | F46: =EXP(AB46)/(1+EXP(AB46))/Inputs!$C$32 -> 4.0131007 | G46: =IFERROR((AH46-AI46)/((AN46+BG46)/2),"n/a") -> 0.48152556 | H46: =IFERROR(AI46/AH46,"n/a") -> -1.7669332 | I46: =IFERROR(AK46/AD46*365,"n/a") -> 50.958558 | J46: =IFERROR(N(AL46)/AE46*365,"n/a") -> 151.57135 | K46: =IF(E46>Inputs!$C$7,1,0) -> 1 | L46: =IF(F46>Inputs!$C$8,1,0) -> 1 | M46: =IFERROR((AK46/AD46)/(BD46/AW46),1) -> 1.3656974 | N46: =IFERROR(((AW46-AX46)/AW46)/((AD46-AE46)/AD46),1) -> 1.1420136 | O46: =IFERROR((1-(AM46+AO46)/AN46)/(1-(BF46+BH46)/BG46),1) -> 0.79446331 | P46: =IFERROR(AD46/AW46,1) -> 1.7978974 | Q46: =IFERROR((AZ46/(AZ46+BH46))/(AG46/(AG46+AO46)),1) -> 1.1763294 | R46: =IFERROR((AF46/AD46)/(AY46/AW46),1) -> 0.85710883 | S46: =IFERROR((AH46-AI46)/AN46,0) -> 0.32749179 | T46: =IFERROR(((AS46+N(AU46))/AN46)/((BL46+N(BN46))/BG46),1) -> 0.53002801 | U46: =IFERROR((((AM46-AP46-N(AQ46))-(AS46-N(AV46))+(AN46-AM46-N(AR46))-(AT46-AS46-N(AU46))+(N(AQ46)+N(AR46))-(N(AU46)+N(AV46)))-((BF46-BI46-N(BJ46))-(BL46-N(BO46))+(BG46-BF46-N(BK46))-(BM46-BL46-N(BN46))+(N(BJ46)+N(BK46))-(N(BN46)+N(BO46))))/((AN46+BG46)/2),0) -> 0.26094695 | V46: =IFERROR((AK46-BD46)/((AN46+BG46)/2),0) -> 0.1622674 | W46: =IFERROR((N(AL46)-N(BE46))/((AN46+BG46)/2),0) -> 0.42871596 | X46: =IFERROR((AN46-N(AO46)-AP46)/AN46,0) -> 0.71780393 | Y46: =IF(COUNT(BP46,BQ46,BR46,BS46)=4,IFERROR((AD46-(AK46-BD46))/(AW46-(BD46-BP46))-1,0),0) -> 0.64717963 | Z46: =IF(COUNT(BP46,BQ46,BR46,BS46)=4,IFERROR(AH46/((AN46+BG46)/2)-BA46/((BG46+BR46)/2),0),0) -> -0.013478256 | AA46: =IF(N(AJ46)>0,1,0) -> 1 | AB46: =Inputs!$C$24+Inputs!$C$25*U46+Inputs!$C$26*V46+Inputs!$C$27*W46+Inputs!$C$28*X46+Inputs!$C$29*Y46+Inputs!$C$30*Z46+Inputs!$C$31*AA46 -> -4.1948985 | AD46: 11819.523 | AE46: 9932.446 | AF46: 317.155 | AG46: 38.146 | AH46: 1048.991 | AI46: -1853.497 | AJ46: 2748.384 | AK46: 1650.153 | AL46: 4124.587 | AM46: 8063.932 | AN46: 8862.781 | AO46: 385.566 | AP46: 2115.476 | AQ46: n/a | AR46: n/a | AS46: 1717.695 | AT46: 3768.625 | AU46: 85.646 | AV46: n/a | AW46: 6574.081 | AX46: 5375.421 | AY46: 205.812 | AZ46: 34.354 | BA46: 587.251 | BB46: 647.776 | BC46: 379.568 | BD46: 672.055 | BE46: 1540.419 | BF46: 2715.175 | BG46: 3192.604 | BH46: 290.038 | BI46: 362.801 | BJ46: n/a | BK46: 1.59 | BL46: 1092.38 | BM46: 1424.031 | BN46: 133.235 | BO46: n/a | BP46: 679.785 | BQ46: 4629.624 | BR46: 3071.177 | BS46: 183.503
B47: 45473 | C47: 45713 | D47: yes | E47: =Inputs!$C$13+Inputs!$C$14*M47+Inputs!$C$15*N47+Inputs!$C$16*O47+Inputs!$C$17*P47+Inputs!$C$18*Q47+Inputs!$C$19*R47+Inputs!$C$20*S47+Inputs!$C$21*T47 -> 0.66171151 | F47: =EXP(AB47)/(1+EXP(AB47))/Inputs!$C$32 -> 6.1292581 | G47: =IFERROR((AH47-AI47)/((AN47+BG47)/2),"n/a") -> 0.5390247 | H47: =IFERROR(AI47/AH47,"n/a") -> -2.156715 | I47: =IFERROR(AK47/AD47*365,"n/a") -> 66.656153 | J47: =IFERROR(N(AL47)/AE47*365,"n/a") -> 122.33718 | K47: =IF(E47>Inputs!$C$7,1,0) -> 1 | L47: =IF(F47>Inputs!$C$8,1,0) -> 1 | M47: =IFERROR((AK47/AD47)/(BD47/AW47),1) -> 1.1329216 | N47: =IFERROR(((AW47-AX47)/AW47)/((AD47-AE47)/AD47),1) -> 1.3096461 | O47: =IFERROR((1-(AM47+AO47)/AN47)/(1-(BF47+BH47)/BG47),1) -> 0.87560977 | P47: =IFERROR(AD47/AW47,1) -> 2.1042028 | Q47: =IFERROR((AZ47/(AZ47+BH47))/(AG47/(AG47+AO47)),1) -> 1.2514784 | R47: =IFERROR((AF47/AD47)/(AY47/AW47),1) -> 0.85718024 | S47: =IFERROR((AH47-AI47)/AN47,0) -> 0.37030368 | T47: =IFERROR(((AS47+N(AU47))/AN47)/((BL47+N(BN47))/BG47),1) -> 0.58685222 | U47: =IFERROR((((AM47-AP47-N(AQ47))-(AS47-N(AV47))+(AN47-AM47-N(AR47))-(AT47-AS47-N(AU47))+(N(AQ47)+N(AR47))-(N(AU47)+N(AV47)))-((BF47-BI47-N(BJ47))-(BL47-N(BO47))+(BG47-BF47-N(BK47))-(BM47-BL47-N(BN47))+(N(BJ47)+N(BK47))-(N(BN47)+N(BO47))))/((AN47+BG47)/2),0) -> 0.32826048 | V47: =IFERROR((AK47-BD47)/((AN47+BG47)/2),0) -> 0.23540376 | W47: =IFERROR((N(AL47)-N(BE47))/((AN47+BG47)/2),0) -> 0.42774658 | X47: =IFERROR((AN47-N(AO47)-AP47)/AN47,0) -> 0.78793461 | Y47: =IF(COUNT(BP47,BQ47,BR47,BS47)=4,IFERROR((AD47-(AK47-BD47))/(AW47-(BD47-BP47))-1,0),0) -> 0.96779714 | Z47: =IF(COUNT(BP47,BQ47,BR47,BS47)=4,IFERROR(AH47/((AN47+BG47)/2)-BA47/((BG47+BR47)/2),0),0) -> -0.015296228 | AA47: =IF(N(AJ47)>0,1,0) -> 1 | AB47: =Inputs!$C$24+Inputs!$C$25*U47+Inputs!$C$26*V47+Inputs!$C$27*W47+Inputs!$C$28*X47+Inputs!$C$29*Y47+Inputs!$C$30*Z47+Inputs!$C$31*AA47 -> -3.7634094 | AD47: 14989.251 | AE47: 12927.841 | AF47: 387.088 | AG47: 30.1 | AH47: 1152.666 | AI47: -2485.972 | AJ47: 2156.529 | AK47: 2737.331 | AL47: 4333.029 | AM47: 8931.96 | AN47: 9826.092 | AO47: 414.008 | AP47: 1669.766 | AQ47: n/a | AR47: n/a | AS47: 2345.721 | AT47: 4408.722 | AU47: n/a | AV47: n/a | AW47: 7123.482 | AX47: 5840.47 | AY47: 214.61 | AZ47: 26.9 | BA47: 639.998 | BB47: 663.58 | BC47: 1093.86 | BD47: 1148.259 | BE47: 1445.564 | BF47: 3179.426 | BG47: 3674.729 | BH47: 290.24 | BI47: 440.459 | BJ47: n/a | BK47: n/a | BL47: 1374.652 | BM47: 1702.559 | BN47: 120.179 | BO47: 170.123 | BP47: 834.513 | BQ47: 5196.099 | BR47: 3205.077 | BS47: 285.163
B48: 45565 | C48: 45713 | D48: yes | E48: =Inputs!$C$13+Inputs!$C$14*M48+Inputs!$C$15*N48+Inputs!$C$16*O48+Inputs!$C$17*P48+Inputs!$C$18*Q48+Inputs!$C$19*R48+Inputs!$C$20*S48+Inputs!$C$21*T48 -> 1.0775624 | F48: =EXP(AB48)/(1+EXP(AB48))/Inputs!$C$32 -> 5.7903645 | G48: =IFERROR((AH48-AI48)/((AN48+BG48)/2),"n/a") -> 0.50410698 | H48: =IFERROR(AI48/AH48,"n/a") -> -1.6531946 | I48: =IFERROR(AK48/AD48*365,"n/a") -> 53.017166 | J48: =IFERROR(N(AL48)/AE48*365,"n/a") -> 110.25046 | K48: =IF(E48>Inputs!$C$7,1,0) -> 1 | L48: =IF(F48>Inputs!$C$8,1,0) -> 1 | M48: =IFERROR((AK48/AD48)/(BD48/AW48),1) -> 1.2693957 | N48: =IFERROR(((AW48-AX48)/AW48)/((AD48-AE48)/AD48),1) -> 1.3209659 | O48: =IFERROR((1-(AM48+AO48)/AN48)/(1-(BF48+BH48)/BG48),1) -> 0.88720203 | P48: =IFERROR(AD48/AW48,1) -> 2.5445507 | Q48: =IFERROR((AZ48/(AZ48+BH48))/(AG48/(AG48+AO48)),1) -> 1.2037212 | R48: =IFERROR((AF48/AD48)/(AY48/AW48),1) -> 0.76543019 | S48: =IFERROR((AH48-AI48)/AN48,0) -> 0.34719362 | T48: =IFERROR(((AS48+N(AU48))/AN48)/((BL48+N(BN48))/BG48),1) -> 0.6336801 | U48: =IFERROR((((AM48-AP48-N(AQ48))-(AS48-N(AV48))+(AN48-AM48-N(AR48))-(AT48-AS48-N(AU48))+(N(AQ48)+N(AR48))-(N(AU48)+N(AV48)))-((BF48-BI48-N(BJ48))-(BL48-N(BO48))+(BG48-BF48-N(BK48))-(BM48-BL48-N(BN48))+(N(BJ48)+N(BK48))-(N(BN48)+N(BO48))))/((AN48+BG48)/2),0) -> 0.2897927 | V48: =IFERROR((AK48-BD48)/((AN48+BG48)/2),0) -> 0.25235395 | W48: =IFERROR((N(AL48)-N(BE48))/((AN48+BG48)/2),0) -> 0.38506071 | X48: =IFERROR((AN48-N(AO48)-AP48)/AN48,0) -> 0.76594891 | Y48: =IF(COUNT(BP48,BQ48,BR48,BS48)=4,IFERROR((AD48-(AK48-BD48))/(AW48-(BD48-BP48))-1,0),0) -> 1.3237761 | Z48: =IF(COUNT(BP48,BQ48,BR48,BS48)=4,IFERROR(AH48/((AN48+BG48)/2)-BA48/((BG48+BR48)/2),0),0) -> 0.024377037 | AA48: =IF(N(AJ48)>0,1,0) -> 1 | AB48: =Inputs!$C$24+Inputs!$C$25*U48+Inputs!$C$26*V48+Inputs!$C$27*W48+Inputs!$C$28*X48+Inputs!$C$29*Y48+Inputs!$C$30*Z48+Inputs!$C$31*AA48 -> -3.82157 | AD48: 18806.835 | AE48: 16323.536 | AF48: 451.072 | AG48: 32.1 | AH48: 1419.998 | AI48: -2347.533 | AJ48: 3341.563 | AK48: 2731.74 | AL48: 4930.623 | AM48: 9851.584 | AN48: 10851.383 | AO48: 451.06 | AP48: 2088.718 | AQ48: n/a | AR48: n/a | AS48: 2871.101 | AT48: 4974.466 | AU48: n/a | AV48: n/a | AW48: 7391.024 | AX48: 6101.856 | AY48: 231.595 | AZ48: 25.353 | BA48: 612.577 | BB48: 620.458 | BC48: 1014.719 | BD48: 845.729 | BE48: 2052.805 | BF48: 3570.834 | BG48: 4095.964 | BH48: 291.669 | BI48: 543.156 | BJ48: n/a | BK48: n/a | BL48: 1604.821 | BM48: 1930.425 | BN48: 105.389 | BO48: n/a | BP48: 736.312 | BQ48: 6015.499 | BR48: 3301.283 | BS48: 444.142
B49: 45657 | C49: 45713 | D49: yes | E49: =Inputs!$C$13+Inputs!$C$14*M49+Inputs!$C$15*N49+Inputs!$C$16*O49+Inputs!$C$17*P49+Inputs!$C$18*Q49+Inputs!$C$19*R49+Inputs!$C$20*S49+Inputs!$C$21*T49 -> 0.70339054 | F49: =EXP(AB49)/(1+EXP(AB49))/Inputs!$C$32 -> 4.3115912 | G49: =IFERROR((AH49-AI49)/((AN49+BG49)/2),"n/a") -> 0.4542063 | H49: =IFERROR(AI49/AH49,"n/a") -> -1.3790455 | I49: =IFERROR(AK49/AD49*365,"n/a") -> 53.63727 | J49: =IFERROR(N(AL49)/AE49*365,"n/a") -> 71.998354 | K49: =IF(E49>Inputs!$C$7,1,0) -> 1 | L49: =IF(F49>Inputs!$C$8,1,0) -> 1 | M49: =IFERROR((AK49/AD49)/(BD49/AW49),1) -> 0.90467829 | N49: =IFERROR(((AW49-AX49)/AW49)/((AD49-AE49)/AD49),1) -> 1.3176313 | O49: =IFERROR((1-(AM49+AO49)/AN49)/(1-(BF49+BH49)/BG49),1) -> 1.2214492 | P49: =IFERROR(AD49/AW49,1) -> 2.2501274 | Q49: =IFERROR((AZ49/(AZ49+BH49))/(AG49/(AG49+AO49)),1) -> 1.1080959 | R49: =IFERROR((AF49/AD49)/(AY49/AW49),1) -> 0.85859626 | S49: =IFERROR((AH49-AI49)/AN49,0) -> 0.35328002 | T49: =IFERROR(((AS49+N(AU49))/AN49)/((BL49+N(BN49))/BG49),1) -> 0.36070837 | U49: =IFERROR((((AM49-AP49-N(AQ49))-(AS49-N(AV49))+(AN49-AM49-N(AR49))-(AT49-AS49-N(AU49))+(N(AQ49)+N(AR49))-(N(AU49)+N(AV49)))-((BF49-BI49-N(BJ49))-(BL49-N(BO49))+(BG49-BF49-N(BK49))-(BM49-BL49-N(BN49))+(N(BJ49)+N(BK49))-(N(BN49)+N(BO49))))/((AN49+BG49)/2),0) -> 0.32471995 | V49: =IFERROR((AK49-BD49)/((AN49+BG49)/2),0) -> 0.2057098 | W49: =IFERROR((N(AL49)-N(BE49))/((AN49+BG49)/2),0) -> 0.14922646 | X49: =IFERROR((AN49-N(AO49)-AP49)/AN49,0) -> 0.80392416 | Y49: =IF(COUNT(BP49,BQ49,BR49,BS49)=4,IFERROR((AD49-(AK49-BD49))/(AW49-(BD49-BP49))-1,0),0) -> 1.2614991 | Z49: =IF(COUNT(BP49,BQ49,BR49,BS49)=4,IFERROR(AH49/((AN49+BG49)/2)-BA49/((BG49+BR49)/2),0),0) -> 0.018187709 | AA49: =IF(N(AJ49)>0,1,0) -> 1 | AB49: =Inputs!$C$24+Inputs!$C$25*U49+Inputs!$C$26*V49+Inputs!$C$27*W49+Inputs!$C$28*X49+Inputs!$C$29*Y49+Inputs!$C$30*Z49+Inputs!$C$31*AA49 -> -4.1220339 | AD49: 20819.873 | AE49: 18230.874 | AF49: 510.207 | AG49: 34.4 | AH49: 1444.626 | AI49: -1992.205 | AJ49: 2605.623 | AK49: 3059.51 | AL49: 3596.145 | AM49: 8667.07 | AN49: 9728.348 | AO49: 477.492 | AP49: 1430.002 | AQ49: n/a | AR49: n/a | AS49: 1357.81 | AT49: 3489.882 | AU49: n/a | AV49: n/a | AW49: 9252.753 | AX49: 7736.685 | AY49: 264.089 | AZ49: 23.904 | BA49: 732.378 | BB49: -135.714 | BC49: 1807.506 | BD49: 1502.971 | BE49: 2466.997 | BF49: 4842.355 | BG49: 5405 | BH49: 297.102 | BI49: 725.66 | BJ49: n/a | BK49: n/a | BL49: 1992.089 | BM49: 2327.926 | BN49: 99.322 | BO49: n/a | BP49: 768.167 | BQ49: 6646.275 | BR49: 3074.942 | BS49: 578.377
B50: 45747 | C50: 45789 | D50: yes | E50: =Inputs!$C$13+Inputs!$C$14*M50+Inputs!$C$15*N50+Inputs!$C$16*O50+Inputs!$C$17*P50+Inputs!$C$18*Q50+Inputs!$C$19*R50+Inputs!$C$20*S50+Inputs!$C$21*T50 -> -0.91212706 | F50: =EXP(AB50)/(1+EXP(AB50))/Inputs!$C$32 -> 1.9140712 | G50: =IFERROR((AH50-AI50)/((AN50+BG50)/2),"n/a") -> 0.10232451 | H50: =IFERROR(AI50/AH50,"n/a") -> 0.12867438 | I50: =IFERROR(AK50/AD50*365,"n/a") -> 44.716989 | J50: =IFERROR(N(AL50)/AE50*365,"n/a") -> 73.813785 | K50: =IF(E50>Inputs!$C$7,1,0) -> 1 | L50: =IF(F50>Inputs!$C$8,1,0) -> 1 | M50: =IFERROR((AK50/AD50)/(BD50/AW50),1) -> 0.87751678 | N50: =IFERROR(((AW50-AX50)/AW50)/((AD50-AE50)/AD50),1) -> 1.4161119 | O50: =IFERROR((1-(AM50+AO50)/AN50)/(1-(BF50+BH50)/BG50),1) -> 1.4625441 | P50: =IFERROR(AD50/AW50,1) -> 1.8249231 | Q50: =IFERROR((AZ50/(AZ50+BH50))/(AG50/(AG50+AO50)),1) -> 0.78945886 | R50: =IFERROR((AF50/AD50)/(AY50/AW50),1) -> 0.92946676 | S50: =IFERROR((AH50-AI50)/AN50,0) -> 0.093387779 | T50: =IFERROR(((AS50+N(AU50))/AN50)/((BL50+N(BN50))/BG50),1) -> 0.6536076 | U50: =IFERROR((((AM50-AP50-N(AQ50))-(AS50-N(AV50))+(AN50-AM50-N(AR50))-(AT50-AS50-N(AU50))+(N(AQ50)+N(AR50))-(N(AU50)+N(AV50)))-((BF50-BI50-N(BJ50))-(BL50-N(BO50))+(BG50-BF50-N(BK50))-(BM50-BL50-N(BN50))+(N(BJ50)+N(BK50))-(N(BN50)+N(BO50))))/((AN50+BG50)/2),0) -> 0.088228611 | V50: =IFERROR((AK50-BD50)/((AN50+BG50)/2),0) -> 0.10125887 | W50: =IFERROR((N(AL50)-N(BE50))/((AN50+BG50)/2),0) -> -0.02595174 | X50: =IFERROR((AN50-N(AO50)-AP50)/AN50,0) -> 0.71796257 | Y50: =IF(COUNT(BP50,BQ50,BR50,BS50)=4,IFERROR((AD50-(AK50-BD50))/(AW50-(BD50-BP50))-1,0),0) -> 0.89802697 | Z50: =IF(COUNT(BP50,BQ50,BR50,BS50)=4,IFERROR(AH50/((AN50+BG50)/2)-BA50/((BG50+BR50)/2),0),0) -> -0.056593178 | AA50: =IF(N(AJ50)>0,1,0) -> 1 | AB50: =Inputs!$C$24+Inputs!$C$25*U50+Inputs!$C$26*V50+Inputs!$C$27*W50+Inputs!$C$28*X50+Inputs!$C$29*Y50+Inputs!$C$30*Z50+Inputs!$C$31*AA50 -> -4.9430827 | AD50: 21569.72 | AE50: 19137.871 | AF50: 537.96 | AG50: 37.6 | AH50: 1150.944 | AI50: 148.097 | AJ50: 1695.67 | AK50: 2642.556 | AL50: 3870.243 | AM50: 9513.589 | AN50: 10738.525 | AO50: 492.565 | AP50: 2536.101 | AQ50: n/a | AR50: n/a | AS50: 1428.136 | AT50: 4359.046 | AU50: n/a | AV50: n/a | AW50: 11819.523 | AX50: 9932.446 | AY50: 317.155 | AZ50: 22.868 | BA50: 1048.991 | BB50: -1847.497 | BC50: 2748.384 | BD50: 1650.153 | BE50: 4124.587 | BF50: 8063.932 | BG50: 8862.781 | BH50: 385.566 | BI50: 2115.476 | BJ50: n/a | BK50: n/a | BL50: 1717.695 | BM50: 3768.625 | BN50: 85.646 | BO50: n/a | BP50: 672.055 | BQ50: 6574.081 | BR50: 3192.604 | BS50: 587.251
B52: Complete = every Beneish index available. Quarters to March 2019 were filed late in December 2019, when the prior-year balance sheets were not re-reported; their indices fall back to neutral.
B53: Financials are as first filed: the value each fact had in the first 10-K or 10-Q covering that quarter, from the SEC XBRL company-facts API with filing dates.

Sheet Validation
B2: Validation: companies the SEC later charged
B3: Each misstated fiscal year as first filed · $ millions · thresholds on Inputs
B5: Company | C5: Ticker | D5: Fiscal year | E5: Filed | F5: Usable | G5: M-score | H5: F-score | I5: M flag | J5: F flag | K5: Either | L5: Both | M5: DSRI | N5: GMI | O5: AQI | P5: SGI | Q5: DEPI | R5: SGAI | S5: TATA | T5: LVGI | U5: RSST accruals | V5: Change in receivables | W5: Change in inventory | X5: Soft assets | Y5: Change in cash sales | Z5: Change in ROA | AA5: Securities issued (0/1) | AB5: F-score logit | AD5: t: Sales | AE5: t: Cost of sales | AF5: t: SG&A | AG5: t: Depreciation | AH5: t: Net income | AI5: t: Operating cash flow | AJ5: t: Debt/equity issued | AK5: t: Receivables | AL5: t: Inventory | AM5: t: Current assets | AN5: t: Total assets | AO5: t: Net PP&E | AP5: t: Cash | AQ5: t: Short-term investments | AR5: t: Long-term investments | AS5: t: Current liabilities | AT5: t: Total liabilities | AU5: t: Long-term debt | AV5: t: Current debt | AW5: t−1: Sales | AX5: t−1: Cost of sales | AY5: t−1: SG&A | AZ5: t−1: Depreciation | BA5: t−1: Net income | BB5: t−1: Operating cash flow | BC5: t−1: Debt/equity issued | BD5: t−1: Receivables | BE5: t−1: Inventory | BF5: t−1: Current assets | BG5: t−1: Total assets | BH5: t−1: Net PP&E | BI5: t−1: Cash | BJ5: t−1: Short-term investments | BK5: t−1: Long-term investments | BL5: t−1: Current liabilities | BM5: t−1: Total liabilities | BN5: t−1: Long-term debt | BO5: t−1: Current debt | BP5: t−2: Receivables | BQ5: t−2: Sales | BR5: t−2: Total assets | BS5: t−2: Net income
B6: Super Micro Computer | C6: SMCI | D6: 2015 | E6: 42257 | F6: 1 | G6: =Inputs!$C$13+Inputs!$C$14*M6+Inputs!$C$15*N6+Inputs!$C$16*O6+Inputs!$C$17*P6+Inputs!$C$18*Q6+Inputs!$C$19*R6+Inputs!$C$20*S6+Inputs!$C$21*T6 -> -1.5400437 | H6: =EXP(AB6)/(1+EXP(AB6))/Inputs!$C$32 -> 2.3889361 | I6: =IF(AND(F6=1,G6>Inputs!$C$7),1,0) -> 1 | J6: =IF(AND(F6=1,H6>Inputs!$C$8),1,0) -> 1 | K6: =MAX(I6,J6) -> 1 | L6: =I6*J6 -> 1 | M6: =IFERROR((AK6/AD6)/(BD6/AW6),1) -> 1.1173676 | N6: =IFERROR(((AW6-AX6)/AW6)/((AD6-AE6)/AD6),1) -> 0.95583954 | O6: =IFERROR((1-(AM6+AO6)/AN6)/(1-(BF6+BH6)/BG6),1) -> 0.7746501 | P6: =IFERROR(AD6/AW6,1) -> 1.3571103 | Q6: =IFERROR((AZ6/(AZ6+BH6))/(AG6/(AG6+AO6)),1) -> 0.97799816 | R6: =IFERROR((AF6/AD6)/(AY6/AW6),1) -> 0.88414961 | S6: =IFERROR((AH6-AI6)/AN6,0) -> 0.13442631 | T6: =IFERROR(((AS6+N(AU6))/AN6)/((BL6+N(BN6))/BG6),1) -> 1.0568287 | U6: =IFERROR((((AM6-AP6-N(AQ6))-(AS6-N(AV6))+(AN6-AM6-N(AR6))-(AT6-AS6-N(AU6))+(N(AQ6)+N(AR6))-(N(AU6)+N(AV6)))-((BF6-BI6-N(BJ6))-(BL6-N(BO6))+(BG6-BF6-N(BK6))-(BM6-BL6-N(BN6))+(N(BJ6)+N(BK6))-(N(BN6)+N(BO6))))/((AN6+BG6)/2),0) -> 0.16041702 | V6: =IFERROR((AK6-BD6)/((AN6+BG6)/2),0) -> 0.11648801 | W6: =IFERROR((N(AL6)-N(BE6))/((AN6+BG6)/2),0) -> 0.15657 | X6: =IFERROR((AN6-N(AO6)-AP6)/AN6,0) -> 0.76282082 | Y6: =IF(COUNT(BP6,BQ6,BR6,BS6)=4,IFERROR((AD6-(AK6-BD6))/(AW6-(BD6-BP6))-1,0),0) -> 0.34014364 | Z6: =IF(COUNT(BP6,BQ6,BR6,BS6)=4,IFERROR(AH6/((AN6+BG6)/2)-BA6/((BG6+BR6)/2),0),0) -> 0.032193235 | AA6: =IF(N(AJ6)>0,1,0) -> 1 | AB6: =Inputs!$C$24+Inputs!$C$25*U6+Inputs!$C$26*V6+Inputs!$C$27*W6+Inputs!$C$28*X6+Inputs!$C$29*Y6+Inputs!$C$30*Z6+Inputs!$C$31*AA6 -> -4.719696 | AD6: 1991.155 | AE6: 1670.924 | AF6: 73.228 | AG6: 8.133 | AH6: 101.863 | AI6: -44.636 | AJ6: 84.9 | AK6: 322.594 | AL6: 463.493 | AM6: 914.415 | AN6: 1089.809 | AO6: 163.038 | AP6: 95.442 | AQ6: n/a | AR6: 2.633 | AS6: 454.107 | AT6: 470.724 | AU6: 0.933 | AV6: 93.479 | AW6: 1467.202 | AX6: 1241.657 | AY6: 61.029 | AZ6: 6.364 | BA6: 54.157 | BB6: 6.538 | BC6: 17.354 | BD6: 212.738 | BE6: 315.837 | BF6: 654.081 | BG6: 796.325 | BH6: 130.589 | BI6: 96.872 | BJ6: n/a | BK6: 2.647 | BL6: 310.886 | BM6: 327.094 | BN6: 3.733 | BO6: 42.554 | BP6: 149.34 | BQ6: 1162.561 | BR6: 632.257 | BS6: 21.279
B7: Super Micro Computer | C7: SMCI | D7: 2016 | E7: 42608 | F7: 1 | G7: =Inputs!$C$13+Inputs!$C$14*M7+Inputs!$C$15*N7+Inputs!$C$16*O7+Inputs!$C$17*P7+Inputs!$C$18*Q7+Inputs!$C$19*R7+Inputs!$C$20*S7+Inputs!$C$21*T7 -> -1.8707052 | H7: =EXP(AB7)/(1+EXP(AB7))/Inputs!$C$32 -> 1.0831999 | I7: =IF(AND(F7=1,G7>Inputs!$C$7),1,0) -> 0 | J7: =IF(AND(F7=1,H7>Inputs!$C$8),1,0) -> 0 | K7: =MAX(I7,J7) -> 0 | L7: =I7*J7 -> 0 | M7: =IFERROR((AK7/AD7)/(BD7/AW7),1) -> 0.80495553 | N7: =IFERROR(((AW7-AX7)/AW7)/((AD7-AE7)/AD7),1) -> 1.0748011 | O7: =IFERROR((1-(AM7+AO7)/AN7)/(1-(BF7+BH7)/BG7),1) -> 3.0002344 | P7: =IFERROR(AD7/AW7,1) -> 1.1127074 | Q7: =IFERROR((AZ7/(AZ7+BH7))/(AG7/(AG7+AO7)),1) -> 0.71986655 | R7: =IFERROR((AF7/AD7)/(AY7/AW7),1) -> 1.2356326 | S7: =IFERROR((AH7-AI7)/AN7,0) -> -0.030446122 | T7: =IFERROR(((AS7+N(AU7))/AN7)/((BL7+N(BN7))/BG7),1) -> 0.82931936 | U7: =IFERROR((((AM7-AP7-N(AQ7))-(AS7-N(AV7))+(AN7-AM7-N(AR7))-(AT7-AS7-N(AU7))+(N(AQ7)+N(AR7))-(N(AU7)+N(AV7)))-((BF7-BI7-N(BJ7))-(BL7-N(BO7))+(BG7-BF7-N(BK7))-(BM7-BL7-N(BN7))+(N(BJ7)+N(BK7))-(N(BN7)+N(BO7))))/((AN7+BG7)/2),0) -> 0.01487269 | V7: =IFERROR((AK7-BD7)/((AN7+BG7)/2),0) -> -0.029842038 | W7: =IFERROR((N(AL7)-N(BE7))/((AN7+BG7)/2),0) -> -0.012869506 | X7: =IFERROR((AN7-N(AO7)-AP7)/AN7,0) -> 0.68349949 | Y7: =IF(COUNT(BP7,BQ7,BR7,BS7)=4,IFERROR((AD7-(AK7-BD7))/(AW7-(BD7-BP7))-1,0),0) -> 0.19557072 | Z7: =IF(COUNT(BP7,BQ7,BR7,BS7)=4,IFERROR(AH7/((AN7+BG7)/2)-BA7/((BG7+BR7)/2),0),0) -> -0.044147339 | AA7: =IF(N(AJ7)>0,1,0) -> 1 | AB7: =Inputs!$C$24+Inputs!$C$25*U7+Inputs!$C$26*V7+Inputs!$C$27*W7+Inputs!$C$28*X7+Inputs!$C$29*Y7+Inputs!$C$30*Z7+Inputs!$C$31*AA7 -> -5.515487 | AD7: 2215.573 | AE7: 1884.048 | AF7: 100.681 | AG7: 13.282 | AH7: 72.021 | AI7: 107.509 | AJ7: 34.2 | AK7: 288.941 | AL7: 448.98 | AM7: 938.002 | AN7: 1165.6 | AO7: 187.949 | AP7: 180.964 | AQ7: n/a | AR7: 2.643 | AS7: 363.618 | AT7: 444.221 | AU7: 40 | AV7: 53.589 | AW7: 1991.155 | AX7: 1670.924 | AY7: 73.228 | AZ7: 8.133 | BA7: 101.863 | BB7: -44.636 | BC7: 84.9 | BD7: 322.594 | BE7: 463.493 | BF7: 914.415 | BG7: 1089.809 | BH7: 163.038 | BI7: 95.442 | BJ7: n/a | BK7: 2.633 | BL7: 454.107 | BM7: 470.724 | BN7: 0.933 | BO7: 93.479 | BP7: 212.738 | BQ7: 1467.202 | BR7: 796.325 | BS7: 54.157
B8: Super Micro Computer | C8: SMCI | D8: 2017 | E8: 43602 | F8: 1 | G8: =Inputs!$C$13+Inputs!$C$14*M8+Inputs!$C$15*N8+Inputs!$C$16*O8+Inputs!$C$17*P8+Inputs!$C$18*Q8+Inputs!$C$19*R8+Inputs!$C$20*S8+Inputs!$C$21*T8 -> -1.340136 | H8: =EXP(AB8)/(1+EXP(AB8))/Inputs!$C$32 -> 2.3906289 | I8: =IF(AND(F8=1,G8>Inputs!$C$7),1,0) -> 1 | J8: =IF(AND(F8=1,H8>Inputs!$C$8),1,0) -> 1 | K8: =MAX(I8,J8) -> 1 | L8: =I8*J8 -> 1 | M8: =IFERROR((AK8/AD8)/(BD8/AW8),1) -> 1.6584369 | N8: =IFERROR(((AW8-AX8)/AW8)/((AD8-AE8)/AD8),1) -> 1.0547184 | O8: =IFERROR((1-(AM8+AO8)/AN8)/(1-(BF8+BH8)/BG8),1) -> 0.93313287 | P8: =IFERROR(AD8/AW8,1) -> 1.116811 | Q8: =IFERROR((AZ8/(AZ8+BH8))/(AG8/(AG8+AO8)),1) -> 0.85519179 | R8: =IFERROR((AF8/AD8)/(AY8/AW8),1) -> 1.0069303 | S8: =IFERROR((AH8-AI8)/AN8,0) -> 0.10760925 | T8: =IFERROR(((AS8+N(AU8))/AN8)/((BL8+N(BN8))/BG8),1) -> 1.1762356 | U8: =IFERROR((((AM8-AP8-N(AQ8))-(AS8-N(AV8))+(AN8-AM8-N(AR8))-(AT8-AS8-N(AU8))+(N(AQ8)+N(AR8))-(N(AU8)+N(AV8)))-((BF8-BI8-N(BJ8))-(BL8-N(BO8))+(BG8-BF8-N(BK8))-(BM8-BL8-N(BN8))+(N(BJ8)+N(BK8))-(N(BN8)+N(BO8))))/((AN8+BG8)/2),0) -> 0.10744573 | V8: =IFERROR((AK8-BD8)/((AN8+BG8)/2),0) -> 0.11015317 | W8: =IFERROR((N(AL8)-N(BE8))/((AN8+BG8)/2),0) -> 0.16246209 | X8: =IFERROR((AN8-N(AO8)-AP8)/AN8,0) -> 0.79791701 | Y8: =IF(COUNT(BP8,BQ8,BR8,BS8)=4,IFERROR((AD8-(AK8-BD8))/(AW8-(BD8-BP8))-1,0),0) -> -0.015520405 | Z8: =IF(COUNT(BP8,BQ8,BR8,BS8)=4,IFERROR(AH8/((AN8+BG8)/2)-BA8/((BG8+BR8)/2),0),0) -> -0.013792651 | AA8: =IF(N(AJ8)>0,1,0) -> 1 | AB8: =Inputs!$C$24+Inputs!$C$25*U8+Inputs!$C$26*V8+Inputs!$C$27*W8+Inputs!$C$28*X8+Inputs!$C$29*Y8+Inputs!$C$30*Z8+Inputs!$C$31*AA8 -> -4.7189813 | AD8: 2484.929 | AE8: 2134.971 | AF8: 111.091 | AG8: 16.357 | AH8: 66.854 | AI8: -96.188 | AJ8: 207.029 | AK8: 324.004 | AL8: 736.668 | AM8: 1261.166 | AN8: 1515.13 | AO8: 195.576 | AP8: 110.606 | AQ8: n/a | AR8: 2.625 | AS8: 672.53 | AT8: 741.284 | AU8: 0 | AV8: 161.447 | AW8: 2225.022 | AX8: 1894.521 | AY8: 98.787 | AZ8: 13.282 | BA8: 72.081 | BB8: 107.987 | BC8: 34.2 | BD8: 174.933 | BE8: 516.807 | BF8: 954.328 | BG8: 1191.483 | BH8: 187.949 | BI8: 178.82 | BJ8: n/a | BK8: 2.643 | BL8: 409.63 | BM8: 494.83 | BN8: 40 | BO8: 53.589 | BP8: 322.594 | BQ8: 1954.353 | BR8: 1089.809 | BS8: 92.555
B9: MiMedx | C9: MDXG | D9: 2013 | E9: 41702 | F9: 1 | G9: =Inputs!$C$13+Inputs!$C$14*M9+Inputs!$C$15*N9+Inputs!$C$16*O9+Inputs!$C$17*P9+Inputs!$C$18*Q9+Inputs!$C$19*R9+Inputs!$C$20*S9+Inputs!$C$21*T9 -> -1.6217923 | H9: =EXP(AB9)/(1+EXP(AB9))/Inputs!$C$32 -> 1.2725106 | I9: =IF(AND(F9=1,G9>Inputs!$C$7),1,0) -> 1 | J9: =IF(AND(F9=1,H9>Inputs!$C$8),1,0) -> 0 | K9: =MAX(I9,J9) -> 1 | L9: =I9*J9 -> 0 | M9: =IFERROR((AK9/AD9)/(BD9/AW9),1) -> 0.96120613 | N9: =IFERROR(((AW9-AX9)/AW9)/((AD9-AE9)/AD9),1) -> 0.95944889 | O9: =IFERROR((1-(AM9+AO9)/AN9)/(1-(BF9+BH9)/BG9),1) -> 0.394585 | P9: =IFERROR(AD9/AW9,1) -> 2.1875224 | Q9: =IFERROR((AZ9/(AZ9+BH9))/(AG9/(AG9+AO9)),1) -> 2.244229 | R9: =IFERROR((AF9/AD9)/(AY9/AW9),1) -> 1.0786642 | S9: =IFERROR((AH9-AI9)/AN9,0) -> -0.045178889 | T9: =IFERROR(((AS9+N(AU9))/AN9)/((BL9+N(BN9))/BG9),1) -> 0.44201025 | U9: =IFERROR((((AM9-AP9-N(AQ9))-(AS9-N(AV9))+(AN9-AM9-N(AR9))-(AT9-AS9-N(AU9))+(N(AQ9)+N(AR9))-(N(AU9)+N(AV9)))-((BF9-BI9-N(BJ9))-(BL9-N(BO9))+(BG9-BF9-N(BK9))-(BM9-BL9-N(BN9))+(N(BJ9)+N(BK9))-(N(BN9)+N(BO9))))/((AN9+BG9)/2),0) -> 0.27090384 | V9: =IFERROR((AK9-BD9)/((AN9+BG9)/2),0) -> 0.14079949 | W9: =IFERROR((N(AL9)-N(BE9))/((AN9+BG9)/2),0) -> 0.014314599 | X9: =IFERROR((AN9-N(AO9)-AP9)/AN9,0) -> 0.43131842 | Y9: =IF(COUNT(BP9,BQ9,BR9,BS9)=4,IFERROR((AD9-(AK9-BD9))/(AW9-(BD9-BP9))-1,0),0) -> 1.3831085 | Z9: =IF(COUNT(BP9,BQ9,BR9,BS9)=4,IFERROR(AH9/((AN9+BG9)/2)-BA9/((BG9+BR9)/2),0),0) -> 0.17746543 | AA9: =IF(N(AJ9)>0,1,0) -> 1 | AB9: =Inputs!$C$24+Inputs!$C$25*U9+Inputs!$C$26*V9+Inputs!$C$27*W9+Inputs!$C$28*X9+Inputs!$C$29*Y9+Inputs!$C$30*Z9+Inputs!$C$31*AA9 -> -5.3537112 | AD9: 59.180734 | AE9: 9.328114 | AF9: 46.225657 | AG9: 0.637246 | AH9: -4.111853 | AI9: -0.285477 | AJ9: 36.602306 | AK9: 16.092836 | AL9: 3.880776 | AM9: 65.388771 | AN9: 84.693893 | AO9: 4.086106 | AP9: 44.077751 | AQ9: n/a | AR9: n/a | AS9: 9.607867 | AT9: 11.125823 | AU9: 0 | AV9: n/a | AW9: 27.053773 | AX9: 5.188378 | AY9: 19.590446 | AZ9: 0.465367 | BA9: -7.662376 | BB9: -3.33126 | BC9: 0 | BD9: 7.653561 | BE9: 3.022784 | BF9: 18.088791 | BG9: 35.182608 | BH9: 1.071625 | BI9: 6.754485 | BJ9: n/a | BK9: n/a | BL9: 5.017201 | BM9: 15.175306 | BN9: 4.012442 | BO9: 0 | BP9: 1.891919 | BQ9: 7.760446 | BR9: 27.096192 | BS9: -10.193986
B10: MiMedx | C10: MDXG | D10: 2014 | E10: 42076 | F10: 1 | G10: =Inputs!$C$13+Inputs!$C$14*M10+Inputs!$C$15*N10+Inputs!$C$16*O10+Inputs!$C$17*P10+Inputs!$C$18*Q10+Inputs!$C$19*R10+Inputs!$C$20*S10+Inputs!$C$21*T10 -> -2.4446408 | H10: =EXP(AB10)/(1+EXP(AB10))/Inputs!$C$32 -> 0.4526892 | I10: =IF(AND(F10=1,G10>Inputs!$C$7),1,0) -> 0 | J10: =IF(AND(F10=1,H10>Inputs!$C$8),1,0) -> 0 | K10: =MAX(I10,J10) -> 0 | L10: =I10*J10 -> 0 | M10: =IFERROR((AK10/AD10)/(BD10/AW10),1) -> 0.8296576 | N10: =IFERROR(((AW10-AX10)/AW10)/((AD10-AE10)/AD10),1) -> 0.94345203 | O10: =IFERROR((1-(AM10+AO10)/AN10)/(1-(BF10+BH10)/BG10),1) -> 0.92369133 | P10: =IFERROR(AD10/AW10,1) -> 1.9976513 | Q10: =IFERROR((AZ10/(AZ10+BH10))/(AG10/(AG10+AO10)),1) -> 0.7486123 | R10: =IFERROR((AF10/AD10)/(AY10/AW10),1) -> 0.97979948 | S10: =IFERROR((AH10-AI10)/AN10,0) -> -0.096852433 | T10: =IFERROR(((AS10+N(AU10))/AN10)/((BL10+N(BN10))/BG10),1) -> 1.4848229 | U10: =IFERROR((((AM10-AP10-N(AQ10))-(AS10-N(AV10))+(AN10-AM10-N(AR10))-(AT10-AS10-N(AU10))+(N(AQ10)+N(AR10))-(N(AU10)+N(AV10)))-((BF10-BI10-N(BJ10))-(BL10-N(BO10))+(BG10-BF10-N(BK10))-(BM10-BL10-N(BN10))+(N(BJ10)+N(BK10))-(N(BN10)+N(BO10))))/((AN10+BG10)/2),0) -> 0.13670322 | V10: =IFERROR((AK10-BD10)/((AN10+BG10)/2),0) -> 0.10908828 | W10: =IFERROR((N(AL10)-N(BE10))/((AN10+BG10)/2),0) -> 0.012910344 | X10: =IFERROR((AN10-N(AO10)-AP10)/AN10,0) -> 0.52380124 | Y10: =IF(COUNT(BP10,BQ10,BR10,BS10)=4,IFERROR((AD10-(AK10-BD10))/(AW10-(BD10-BP10))-1,0),0) -> 1.1214168 | Z10: =IF(COUNT(BP10,BQ10,BR10,BS10)=4,IFERROR(AH10/((AN10+BG10)/2)-BA10/((BG10+BR10)/2),0),0) -> 0.13274313 | AA10: =IF(N(AJ10)>0,1,0) -> 0 | AB10: =Inputs!$C$24+Inputs!$C$25*U10+Inputs!$C$26*V10+Inputs!$C$27*W10+Inputs!$C$28*X10+Inputs!$C$29*Y10+Inputs!$C$30*Z10+Inputs!$C$31*AA10 -> -6.3902956 | AD10: 118.223 | AE10: 12.665 | AF10: 90.48 | AG10: 1.197 | AH10: 6.22 | AI10: 16.802 | AJ10: 0 | AK10: 26.672 | AL10: 5.133 | AM10: 85.677 | AN10: 109.259 | AO10: 5.447 | AP10: 46.582 | AQ10: 5.75 | AR10: n/a | AS10: 18.404 | AT10: 19.93 | AU10: n/a | AV10: n/a | AW10: 59.181 | AX10: 9.328 | AY10: 46.227 | AZ10: 0.637 | BA10: -4.112 | BB10: -0.284 | BC10: 36.602 | BD10: 16.093 | BE10: 3.881 | BF10: 65.389 | BG10: 84.694 | BH10: 4.086 | BI10: 44.078 | BJ10: 0 | BK10: n/a | BL10: 9.608 | BM10: 11.126 | BN10: 0 | BO10: n/a | BP10: 7.653561 | BQ10: 27.053 | BR10: 35.182608 | BS10: -7.663
B11: MiMedx | C11: MDXG | D11: 2015 | E11: 42429 | F11: 1 | G11: =Inputs!$C$13+Inputs!$C$14*M11+Inputs!$C$15*N11+Inputs!$C$16*O11+Inputs!$C$17*P11+Inputs!$C$18*Q11+Inputs!$C$19*R11+Inputs!$C$20*S11+Inputs!$C$21*T11 -> -1.2348965 | H11: =EXP(AB11)/(1+EXP(AB11))/Inputs!$C$32 -> 0.87339766 | I11: =IF(AND(F11=1,G11>Inputs!$C$7),1,0) -> 1 | J11: =IF(AND(F11=1,H11>Inputs!$C$8),1,0) -> 0 | K11: =MAX(I11,J11) -> 1 | L11: =I11*J11 -> 0 | M11: =IFERROR((AK11/AD11)/(BD11/AW11),1) -> 1.2721454 | N11: =IFERROR(((AW11-AX11)/AW11)/((AD11-AE11)/AD11),1) -> 1.000822 | O11: =IFERROR((1-(AM11+AO11)/AN11)/(1-(BF11+BH11)/BG11),1) -> 1.3355156 | P11: =IFERROR(AD11/AW11,1) -> 1.5842603 | Q11: =IFERROR((AZ11/(AZ11+BH11))/(AG11/(AG11+AO11)),1) -> 1.1290454 | R11: =IFERROR((AF11/AD11)/(AY11/AW11),1) -> 0.93051766 | S11: =IFERROR((AH11-AI11)/AN11,0) -> 0.078278016 | T11: =IFERROR(((AS11+N(AU11))/AN11)/((BL11+N(BN11))/BG11),1) -> 1.169623 | U11: =IFERROR((((AM11-AP11-N(AQ11))-(AS11-N(AV11))+(AN11-AM11-N(AR11))-(AT11-AS11-N(AU11))+(N(AQ11)+N(AR11))-(N(AU11)+N(AV11)))-((BF11-BI11-N(BJ11))-(BL11-N(BO11))+(BG11-BF11-N(BK11))-(BM11-BL11-N(BN11))+(N(BJ11)+N(BK11))-(N(BN11)+N(BO11))))/((AN11+BG11)/2),0) -> 0.29983032 | V11: =IFERROR((AK11-BD11)/((AN11+BG11)/2),0) -> 0.22093061 | W11: =IFERROR((N(AL11)-N(BE11))/((AN11+BG11)/2),0) -> 0.018982592 | X11: =IFERROR((AN11-N(AO11)-AP11)/AN11,0) -> 0.72069633 | Y11: =IF(COUNT(BP11,BQ11,BR11,BS11)=4,IFERROR((AD11-(AK11-BD11))/(AW11-(BD11-BP11))-1,0),0) -> 0.48835978 | Z11: =IF(COUNT(BP11,BQ11,BR11,BS11)=4,IFERROR(AH11/((AN11+BG11)/2)-BA11/((BG11+BR11)/2),0),0) -> 0.17606762 | AA11: =IF(N(AJ11)>0,1,0) -> 0 | AB11: =Inputs!$C$24+Inputs!$C$25*U11+Inputs!$C$26*V11+Inputs!$C$27*W11+Inputs!$C$28*X11+Inputs!$C$29*Y11+Inputs!$C$30*Z11+Inputs!$C$31*AA11 -> -5.73155 | AD11: 187.296 | AE11: 20.202 | AF11: 133.384 | AG11: 1.799 | AH11: 29.446 | AI11: 18.807 | AJ11: 0 | AK11: 53.755 | AL11: 7.46 | AM11: 96.31 | AN11: 135.913 | AO11: 9.475 | AP11: 28.486 | AQ11: 3 | AR11: n/a | AS11: 26.777 | AT11: 27.925 | AU11: n/a | AV11: n/a | AW11: 118.223 | AX11: 12.665 | AY11: 90.48 | AZ11: 1.197 | BA11: 6.22 | BB11: 16.802 | BC11: 0 | BD11: 26.672 | BE11: 5.133 | BF11: 85.677 | BG11: 109.259 | BH11: 5.447 | BI11: 46.582 | BJ11: 5.75 | BK11: n/a | BL11: 18.404 | BM11: 19.93 | BN11: n/a | BO11: n/a | BP11: 16.093 | BQ11: 59.181 | BR11: 84.694 | BS11: -4.112
B12: MiMedx | C12: MDXG | D12: 2016 | E12: 42795 | F12: 1 | G12: =Inputs!$C$13+Inputs!$C$14*M12+Inputs!$C$15*N12+Inputs!$C$16*O12+Inputs!$C$17*P12+Inputs!$C$18*Q12+Inputs!$C$19*R12+Inputs!$C$20*S12+Inputs!$C$21*T12 -> -2.6067854 | H12: =EXP(AB12)/(1+EXP(AB12))/Inputs!$C$32 -> 0.81297162 | I12: =IF(AND(F12=1,G12>Inputs!$C$7),1,0) -> 0 | J12: =IF(AND(F12=1,H12>Inputs!$C$8),1,0) -> 0 | K12: =MAX(I12,J12) -> 0 | L12: =I12*J12 -> 0 | M12: =IFERROR((AK12/AD12)/(BD12/AW12),1) -> 0.95492541 | N12: =IFERROR(((AW12-AX12)/AW12)/((AD12-AE12)/AD12),1) -> 1.0281238 | O12: =IFERROR((1-(AM12+AO12)/AN12)/(1-(BF12+BH12)/BG12),1) -> 1.2357133 | P12: =IFERROR(AD12/AW12,1) -> 1.30817 | Q12: =IFERROR((AZ12/(AZ12+BH12))/(AG12/(AG12+AO12)),1) -> 0.81958917 | R12: =IFERROR((AF12/AD12)/(AY12/AW12),1) -> 1.0315668 | S12: =IFERROR((AH12-AI12)/AN12,0) -> -0.071684699 | T12: =IFERROR(((AS12+N(AU12))/AN12)/((BL12+N(BN12))/BG12),1) -> 1.332393 | U12: =IFERROR((((AM12-AP12-N(AQ12))-(AS12-N(AV12))+(AN12-AM12-N(AR12))-(AT12-AS12-N(AU12))+(N(AQ12)+N(AR12))-(N(AU12)+N(AV12)))-((BF12-BI12-N(BJ12))-(BL12-N(BO12))+(BG12-BF12-N(BK12))-(BM12-BL12-N(BN12))+(N(BJ12)+N(BK12))-(N(BN12)+N(BO12))))/((AN12+BG12)/2),0) -> 0.11608987 | V12: =IFERROR((AK12-BD12)/((AN12+BG12)/2),0) -> 0.08139111 | W12: =IFERROR((N(AL12)-N(BE12))/((AN12+BG12)/2),0) -> 0.062908596 | X12: =IFERROR((AN12-N(AO12)-AP12)/AN12,0) -> 0.75071793 | Y12: =IF(COUNT(BP12,BQ12,BR12,BS12)=4,IFERROR((AD12-(AK12-BD12))/(AW12-(BD12-BP12))-1,0),0) -> 0.44569417 | Z12: =IF(COUNT(BP12,BQ12,BR12,BS12)=4,IFERROR(AH12/((AN12+BG12)/2)-BA12/((BG12+BR12)/2),0),0) -> -0.16745552 | AA12: =IF(N(AJ12)>0,1,0) -> 0 | AB12: =Inputs!$C$24+Inputs!$C$25*U12+Inputs!$C$26*V12+Inputs!$C$27*W12+Inputs!$C$28*X12+Inputs!$C$29*Y12+Inputs!$C$30*Z12+Inputs!$C$31*AA12 -> -5.803469 | AD12: 245.015 | AE12: 32.407 | AF12: 179.997 | AG12: 3.333 | AH12: 11.974 | AI12: 25.828 | AJ12: n/a | AK12: 67.151 | AL12: 17.814 | AM12: 126.538 | AN12: 193.263 | AO12: 13.786 | AP12: 34.391 | AQ12: 0 | AR12: n/a | AS12: 50.732 | AT12: 60.263 | AU12: n/a | AV12: n/a | AW12: 187.296 | AX12: 20.202 | AY12: 133.384 | AZ12: 1.799 | BA12: 29.446 | BB12: 18.807 | BC12: 0 | BD12: 53.755 | BE12: 7.46 | BF12: 96.31 | BG12: 135.913 | BH12: 9.475 | BI12: 28.486 | BJ12: 3 | BK12: n/a | BL12: 26.777 | BM12: 27.925 | BN12: n/a | BO12: n/a | BP12: 26.672 | BQ12: 118.223 | BR12: 109.259 | BS12: 6.22
B13: Synchronoss | C13: SNCR | D13: 2015 | E13: 42426 | F13: 1 | G13: =Inputs!$C$13+Inputs!$C$14*M13+Inputs!$C$15*N13+Inputs!$C$16*O13+Inputs!$C$17*P13+Inputs!$C$18*Q13+Inputs!$C$19*R13+Inputs!$C$20*S13+Inputs!$C$21*T13 -> -2.3925824 | H13: =EXP(AB13)/(1+EXP(AB13))/Inputs!$C$32 -> 0.4543386 | I13: =IF(AND(F13=1,G13>Inputs!$C$7),1,0) -> 0 | J13: =IF(AND(F13=1,H13>Inputs!$C$8),1,0) -> 0 | K13: =MAX(I13,J13) -> 0 | L13: =I13*J13 -> 0 | M13: =IFERROR((AK13/AD13)/(BD13/AW13),1) -> 0.9590693 | N13: =IFERROR(((AW13-AX13)/AW13)/((AD13-AE13)/AD13),1) -> 1.0166522 | O13: =IFERROR((1-(AM13+AO13)/AN13)/(1-(BF13+BH13)/BG13),1) -> 1.386665 | P13: =IFERROR(AD13/AW13,1) -> 1.265719 | Q13: =IFERROR((AZ13/(AZ13+BH13))/(AG13/(AG13+AO13)),1) -> 0.90023075 | R13: =IFERROR((AF13/AD13)/(AY13/AW13),1) -> 0.90482449 | S13: =IFERROR((AH13-AI13)/AN13,0) -> -0.075787659 | T13: =IFERROR(((AS13+N(AU13))/AN13)/((BL13+N(BN13))/BG13),1) -> 0.77748836 | U13: =IFERROR((((AM13-AP13-N(AQ13))-(AS13-N(AV13))+(AN13-AM13-N(AR13))-(AT13-AS13-N(AU13))+(N(AQ13)+N(AR13))-(N(AU13)+N(AV13)))-((BF13-BI13-N(BJ13))-(BL13-N(BO13))+(BG13-BF13-N(BK13))-(BM13-BL13-N(BN13))+(N(BJ13)+N(BK13))-(N(BN13)+N(BO13))))/((AN13+BG13)/2),0) -> 0 | V13: =IFERROR((AK13-BD13)/((AN13+BG13)/2),0) -> 0.026963452 | W13: =IFERROR((N(AL13)-N(BE13))/((AN13+BG13)/2),0) -> 0 | X13: =IFERROR((AN13-N(AO13)-AP13)/AN13,0) -> 0.68886197 | Y13: =IF(COUNT(BP13,BQ13,BR13,BS13)=4,IFERROR((AD13-(AK13-BD13))/(AW13-(BD13-BP13))-1,0),0) -> 0.3704949 | Z13: =IF(COUNT(BP13,BQ13,BR13,BS13)=4,IFERROR(AH13/((AN13+BG13)/2)-BA13/((BG13+BR13)/2),0),0) -> -0.012704958 | AA13: =IF(N(AJ13)>0,1,0) -> 0 | AB13: =Inputs!$C$24+Inputs!$C$25*U13+Inputs!$C$26*V13+Inputs!$C$27*W13+Inputs!$C$28*X13+Inputs!$C$29*Y13+Inputs!$C$30*Z13+Inputs!$C$31*AA13 -> -6.3866525 | AD13: 578.831 | AE13: 239.074 | AF13: 90.735 | AG13: 72.152 | AH13: 40.63 | AI13: 117.581 | AJ13: n/a | AK13: 143.692 | AL13: n/a | AM13: 406.945 | AN13: 1015.35 | AO13: 168.28 | AP13: 147.634 | AQ13: 66.357 | AR13: 19.635 | AS13: 80.18 | AT13: n/a | AU13: n/a | AV13: n/a | AW13: 457.314 | AX13: 184.414 | AY13: 79.227 | AZ13: 55.956 | BA13: 38.895 | BB13: 70.979 | BC13: 230 | BD13: 118.371 | BE13: n/a | BF13: 441.933 | BG13: 862.822 | BH13: 151.171 | BI13: 235.967 | BJ13: 51.097 | BK13: 3.313 | BL13: 87.635 | BM13: n/a | BN13: n/a | BO13: n/a | BP13: 64.933 | BQ13: 349.047 | BR13: 527.019 | BS13: 23.351
B14: Synchronoss | C14: SNCR | D14: 2016 | E14: 42793 | F14: 1 | G14: =Inputs!$C$13+Inputs!$C$14*M14+Inputs!$C$15*N14+Inputs!$C$16*O14+Inputs!$C$17*P14+Inputs!$C$18*Q14+Inputs!$C$19*R14+Inputs!$C$20*S14+Inputs!$C$21*T14 -> -3.4438001 | H14: =EXP(AB14)/(1+EXP(AB14))/Inputs!$C$32 -> 0.44443907 | I14: =IF(AND(F14=1,G14>Inputs!$C$7),1,0) -> 0 | J14: =IF(AND(F14=1,H14>Inputs!$C$8),1,0) -> 0 | K14: =MAX(I14,J14) -> 0 | L14: =I14*J14 -> 0 | M14: =IFERROR((AK14/AD14)/(BD14/AW14),1) -> 0.90535303 | N14: =IFERROR(((AW14-AX14)/AW14)/((AD14-AE14)/AD14),1) -> 1 | O14: =IFERROR((1-(AM14+AO14)/AN14)/(1-(BF14+BH14)/BG14),1) -> 1.2854182 | P14: =IFERROR(AD14/AW14,1) -> 1.1135975 | Q14: =IFERROR((AZ14/(AZ14+BH14))/(AG14/(AG14+AO14)),1) -> 0.77027468 | R14: =IFERROR((AF14/AD14)/(AY14/AW14),1) -> 1.3316437 | S14: =IFERROR((AH14-AI14)/AN14,0) -> -0.16959653 | T14: =IFERROR(((AS14+N(AU14))/AN14)/((BL14+N(BN14))/BG14),1) -> 1.6616497 | U14: =IFERROR((((AM14-AP14-N(AQ14))-(AS14-N(AV14))+(AN14-AM14-N(AR14))-(AT14-AS14-N(AU14))+(N(AQ14)+N(AR14))-(N(AU14)+N(AV14)))-((BF14-BI14-N(BJ14))-(BL14-N(BO14))+(BG14-BF14-N(BK14))-(BM14-BL14-N(BN14))+(N(BJ14)+N(BK14))-(N(BN14)+N(BO14))))/((AN14+BG14)/2),0) -> 0 | V14: =IFERROR((AK14-BD14)/((AN14+BG14)/2),0) -> 0.0010262272 | W14: =IFERROR((N(AL14)-N(BE14))/((AN14+BG14)/2),0) -> 0 | X14: =IFERROR((AN14-N(AO14)-AP14)/AN14,0) -> 0.71099114 | Y14: =IF(COUNT(BP14,BQ14,BR14,BS14)=4,IFERROR((AD14-(AK14-BD14))/(AW14-(BD14-BP14))-1,0),0) -> 0.15903414 | Z14: =IF(COUNT(BP14,BQ14,BR14,BS14)=4,IFERROR(AH14/((AN14+BG14)/2)-BA14/((BG14+BR14)/2),0),0) -> -0.05091274 | AA14: =IF(N(AJ14)>0,1,0) -> 0 | AB14: =Inputs!$C$24+Inputs!$C$25*U14+Inputs!$C$26*V14+Inputs!$C$27*W14+Inputs!$C$28*X14+Inputs!$C$29*Y14+Inputs!$C$30*Z14+Inputs!$C$31*AA14 -> -6.408719 | AD14: 476.75 | AE14: n/a | AF14: 131.106 | AG14: 99.311 | AH14: -54.945 | AI14: 142.589 | AJ14: 0 | AK14: 137.233 | AL14: n/a | AM14: 364.453 | AN14: 1164.729 | AO14: 155.599 | AP14: 181.018 | AQ14: 12.506 | AR14: 2.974 | AS14: 153.607 | AT14: n/a | AU14: n/a | AV14: 29 | AW14: 428.117 | AX14: 239.074 | AY14: 88.411 | AZ14: 72.152 | BA14: 0.363 | BB14: 139.822 | BC14: 0 | BD14: 136.117 | BE14: n/a | BF14: 406.945 | BG14: 1010.228 | BH14: 168.28 | BI14: 147.634 | BJ14: 66.357 | BK14: 19.635 | BL14: 80.18 | BM14: n/a | BN14: n/a | BO14: 0 | BP14: 118.371 | BQ14: 307.301 | BR14: 862.822 | BS14: -2.023
B15: comScore | C15: SCOR | D15: 2014 | E15: 42055 | F15: 1 | G15: =Inputs!$C$13+Inputs!$C$14*M15+Inputs!$C$15*N15+Inputs!$C$16*O15+Inputs!$C$17*P15+Inputs!$C$18*Q15+Inputs!$C$19*R15+Inputs!$C$20*S15+Inputs!$C$21*T15 -> -3.2664376 | H15: =EXP(AB15)/(1+EXP(AB15))/Inputs!$C$32 -> 0.50743548 | I15: =IF(AND(F15=1,G15>Inputs!$C$7),1,0) -> 0 | J15: =IF(AND(F15=1,H15>Inputs!$C$8),1,0) -> 0 | K15: =MAX(I15,J15) -> 0 | L15: =I15*J15 -> 0 | M15: =IFERROR((AK15/AD15)/(BD15/AW15),1) -> 0.95035196 | N15: =IFERROR(((AW15-AX15)/AW15)/((AD15-AE15)/AD15),1) -> 0.97514285 | O15: =IFERROR((1-(AM15+AO15)/AN15)/(1-(BF15+BH15)/BG15),1) -> 0.92928697 | P15: =IFERROR(AD15/AW15,1) -> 1.1474273 | Q15: =IFERROR((AZ15/(AZ15+BH15))/(AG15/(AG15+AO15)),1) -> 1.0279132 | R15: =IFERROR((AF15/AD15)/(AY15/AW15),1) -> 0.99088713 | S15: =IFERROR((AH15-AI15)/AN15,0) -> -0.16781937 | T15: =IFERROR(((AS15+N(AU15))/AN15)/((BL15+N(BN15))/BG15),1) -> 1.153286 | U15: =IFERROR((((AM15-AP15-N(AQ15))-(AS15-N(AV15))+(AN15-AM15-N(AR15))-(AT15-AS15-N(AU15))+(N(AQ15)+N(AR15))-(N(AU15)+N(AV15)))-((BF15-BI15-N(BJ15))-(BL15-N(BO15))+(BG15-BF15-N(BK15))-(BM15-BL15-N(BN15))+(N(BJ15)+N(BK15))-(N(BN15)+N(BO15))))/((AN15+BG15)/2),0) -> 0.0034654604 | V15: =IFERROR((AK15-BD15)/((AN15+BG15)/2),0) -> 0.022708105 | W15: =IFERROR((N(AL15)-N(BE15))/((AN15+BG15)/2),0) -> 0 | X15: =IFERROR((AN15-N(AO15)-AP15)/AN15,0) -> 0.75878085 | Y15: =IF(COUNT(BP15,BQ15,BR15,BS15)=4,IFERROR((AD15-(AK15-BD15))/(AW15-(BD15-BP15))-1,0),0) -> 0.21057594 | Z15: =IF(COUNT(BP15,BQ15,BR15,BS15)=4,IFERROR(AH15/((AN15+BG15)/2)-BA15/((BG15+BR15)/2),0),0) -> -0.02094269 | AA15: =IF(N(AJ15)>0,1,0) -> 0 | AB15: =Inputs!$C$24+Inputs!$C$25*U15+Inputs!$C$26*V15+Inputs!$C$27*W15+Inputs!$C$28*X15+Inputs!$C$29*Y15+Inputs!$C$30*Z15+Inputs!$C$31*AA15 -> -6.2759289 | AD15: 329.151 | AE15: 97.467 | AF15: 166.448 | AG15: 17.983 | AH15: -9.903 | AI15: 49.497 | AJ15: n/a | AK15: 98.185 | AL15: n/a | AM15: 178.883 | AN15: 353.952 | AO15: 42.365 | AP15: 43.015 | AQ15: n/a | AR15: n/a | AS15: 151.61 | AT15: 178.687 | AU15: n/a | AV15: n/a | AW15: 286.86 | AX15: 89.963 | AY15: 146.396 | AZ15: 16.777 | BA15: -2.333 | BB15: 44.574 | BC15: n/a | BD15: 90.04 | BE15: n/a | BF15: 178.799 | BG15: 363.413 | BH15: 37.995 | BI15: 67.795 | BJ15: n/a | BK15: n/a | BL15: 134.973 | BM15: 164.611 | BN15: n/a | BO15: n/a | BP15: 68.348 | BQ15: 255.193 | BR15: 336.485 | BS15: -11.789
B16: Osiris Therapeutics | C16: OSIR | D16: 2014 | E16: 42083 | F16: 1 | G16: =Inputs!$C$13+Inputs!$C$14*M16+Inputs!$C$15*N16+Inputs!$C$16*O16+Inputs!$C$17*P16+Inputs!$C$18*Q16+Inputs!$C$19*R16+Inputs!$C$20*S16+Inputs!$C$21*T16 -> -1.1737991 | H16: =EXP(AB16)/(1+EXP(AB16))/Inputs!$C$32 -> 1.4454281 | I16: =IF(AND(F16=1,G16>Inputs!$C$7),1,0) -> 1 | J16: =IF(AND(F16=1,H16>Inputs!$C$8),1,0) -> 0 | K16: =MAX(I16,J16) -> 1 | L16: =I16*J16 -> 0 | M16: =IFERROR((AK16/AD16)/(BD16/AW16),1) -> 1.3231604 | N16: =IFERROR(((AW16-AX16)/AW16)/((AD16-AE16)/AD16),1) -> 0.93100606 | O16: =IFERROR((1-(AM16+AO16)/AN16)/(1-(BF16+BH16)/BG16),1) -> 0.014637284 | P16: =IFERROR(AD16/AW16,1) -> 2.4628517 | Q16: =IFERROR((AZ16/(AZ16+BH16))/(AG16/(AG16+AO16)),1) -> 0.76128268 | R16: =IFERROR((AF16/AD16)/(AY16/AW16),1) -> 0.99395993 | S16: =IFERROR((AH16-AI16)/AN16,0) -> 0.029586824 | T16: =IFERROR(((AS16+N(AU16))/AN16)/((BL16+N(BN16))/BG16),1) -> 0.9188936 | U16: =IFERROR((((AM16-AP16-N(AQ16))-(AS16-N(AV16))+(AN16-AM16-N(AR16))-(AT16-AS16-N(AU16))+(N(AQ16)+N(AR16))-(N(AU16)+N(AV16)))-((BF16-BI16-N(BJ16))-(BL16-N(BO16))+(BG16-BF16-N(BK16))-(BM16-BL16-N(BN16))+(N(BJ16)+N(BK16))-(N(BN16)+N(BO16))))/((AN16+BG16)/2),0) -> 0.033877454 | V16: =IFERROR((AK16-BD16)/((AN16+BG16)/2),0) -> 0.17714691 | W16: =IFERROR((N(AL16)-N(BE16))/((AN16+BG16)/2),0) -> 0.094577189 | X16: =IFERROR((AN16-N(AO16)-AP16)/AN16,0) -> 0.95622618 | Y16: =IF(COUNT(BP16,BQ16,BR16,BS16)=4,IFERROR((AD16-(AK16-BD16))/(AW16-(BD16-BP16))-1,0),0) -> 1.1833731 | Z16: =IF(COUNT(BP16,BQ16,BR16,BS16)=4,IFERROR(AH16/((AN16+BG16)/2)-BA16/((BG16+BR16)/2),0),0) -> 0.013780506 | AA16: =IF(N(AJ16)>0,1,0) -> 0 | AB16: =Inputs!$C$24+Inputs!$C$25*U16+Inputs!$C$26*V16+Inputs!$C$27*W16+Inputs!$C$28*X16+Inputs!$C$29*Y16+Inputs!$C$30*Z16+Inputs!$C$31*AA16 -> -5.2256545 | AD16: 59.867 | AE16: 13.171 | AF16: 37.432 | AG16: 0.94 | AH16: -0.246 | AI16: -3.149 | AJ16: n/a | AK16: 24.307 | AL16: 10.924 | AM16: 95.936 | AN16: 98.118 | AO16: 2.087 | AP16: 2.208 | AQ16: 37.305 | AR16: n/a | AS16: 10.566 | AT16: 14.155 | AU16: n/a | AV16: n/a | AW16: 24.308 | AX16: 6.656 | AY16: 15.291 | AZ16: 0.587 | BA16: -1.093 | BB16: -13.269 | BC16: n/a | BD16: 7.459 | BE16: 1.929 | BF16: 84.109 | BG16: 92.097 | BH16: 1.896 | BI16: 2.416 | BJ16: 39.508 | BK16: n/a | BL16: 10.793 | BM16: 11.148 | BN16: n/a | BO16: n/a | BP16: 2.854 | BQ16: 7.849 | BR16: 41.464 | BS16: -5.747
B17: MagnaChip | C17: MX | D17: 2011 | E17: 41327 | F17: 1 | G17: =Inputs!$C$13+Inputs!$C$14*M17+Inputs!$C$15*N17+Inputs!$C$16*O17+Inputs!$C$17*P17+Inputs!$C$18*Q17+Inputs!$C$19*R17+Inputs!$C$20*S17+Inputs!$C$21*T17 -> -3.135705 | H17: =EXP(AB17)/(1+EXP(AB17))/Inputs!$C$32 -> 0.68039703 | I17: =IF(AND(F17=1,G17>Inputs!$C$7),1,0) -> 0 | J17: =IF(AND(F17=1,H17>Inputs!$C$8),1,0) -> 0 | K17: =MAX(I17,J17) -> 0 | L17: =I17*J17 -> 0 | M17: =IFERROR((AK17/AD17)/(BD17/AW17),1) -> 1.0543679 | N17: =IFERROR(((AW17-AX17)/AW17)/((AD17-AE17)/AD17),1) -> 1.0427157 | O17: =IFERROR((1-(AM17+AO17)/AN17)/(1-(BF17+BH17)/BG17),1) -> 0.73040855 | P17: =IFERROR(AD17/AW17,1) -> 1.003149 | Q17: =IFERROR((AZ17/(AZ17+BH17))/(AG17/(AG17+AO17)),1) -> 1.1230905 | R17: =IFERROR((AF17/AD17)/(AY17/AW17),1) -> 1.0226949 | S17: =IFERROR((AH17-AI17)/AN17,0) -> -0.13728461 | T17: =IFERROR(((AS17+N(AU17))/AN17)/((BL17+N(BN17))/BG17),1) -> 0.9696285 | U17: =IFERROR((((AM17-AP17-N(AQ17))-(AS17-N(AV17))+(AN17-AM17-N(AR17))-(AT17-AS17-N(AU17))+(N(AQ17)+N(AR17))-(N(AU17)+N(AV17)))-((BF17-BI17-N(BJ17))-(BL17-N(BO17))+(BG17-BF17-N(BK17))-(BM17-BL17-N(BN17))+(N(BJ17)+N(BK17))-(N(BN17)+N(BO17))))/((AN17+BG17)/2),0) -> 0.022598153 | V17: =IFERROR((AK17-BD17)/((AN17+BG17)/2),0) -> 0.011181852 | W17: =IFERROR((N(AL17)-N(BE17))/((AN17+BG17)/2),0) -> -0.0091157822 | X17: =IFERROR((AN17-N(AO17)-AP17)/AN17,0) -> 0.42792716 | Y17: =IF(COUNT(BP17,BQ17,BR17,BS17)=4,IFERROR((AD17-(AK17-BD17))/(AW17-(BD17-BP17))-1,0),0) -> 0 | Z17: =IF(COUNT(BP17,BQ17,BR17,BS17)=4,IFERROR(AH17/((AN17+BG17)/2)-BA17/((BG17+BR17)/2),0),0) -> 0 | AA17: =IF(N(AJ17)>0,1,0) -> 1 | AB17: =Inputs!$C$24+Inputs!$C$25*U17+Inputs!$C$26*V17+Inputs!$C$27*W17+Inputs!$C$28*X17+Inputs!$C$29*Y17+Inputs!$C$30*Z17+Inputs!$C$31*AA17 -> -5.9819806 | AD17: 772.831 | AE17: 538.515 | AF17: 68.367 | AG17: 51.224 | AH17: 21.793 | AI17: 104.531 | AJ17: 9.336 | AK17: 125.922 | AL17: 62.836 | AM17: 379.896 | AN17: 602.675 | AO17: 182.663 | AP17: 162.111 | AQ17: n/a | AR17: n/a | AS17: 137.639 | AT17: 436.005 | AU17: 201.389 | AV17: n/a | AW17: 770.405 | AX17: 526.847 | AY17: 66.64 | AZ17: 58.395 | BA17: 74.12 | BB17: 106.392 | BC17: 246.685 | BD17: 119.054 | BE17: 68.435 | BF17: 389.707 | BG17: 625.744 | BH17: 179.012 | BI17: 172.172 | BJ17: n/a | BK17: n/a | BL17: 116.149 | BM17: 462.893 | BN17: 246.882 | BO17: n/a | BP17: n/a | BQ17: n/a | BR17: n/a | BS17: n/a
B18: MagnaChip | C18: MX | D18: 2012 | E18: 41327 | F18: 1 | G18: =Inputs!$C$13+Inputs!$C$14*M18+Inputs!$C$15*N18+Inputs!$C$16*O18+Inputs!$C$17*P18+Inputs!$C$18*Q18+Inputs!$C$19*R18+Inputs!$C$20*S18+Inputs!$C$21*T18 -> -1.4864134 | H18: =EXP(AB18)/(1+EXP(AB18))/Inputs!$C$32 -> 0.73284624 | I18: =IF(AND(F18=1,G18>Inputs!$C$7),1,0) -> 1 | J18: =IF(AND(F18=1,H18>Inputs!$C$8),1,0) -> 0 | K18: =MAX(I18,J18) -> 1 | L18: =I18*J18 -> 0 | M18: =IFERROR((AK18/AD18)/(BD18/AW18),1) -> 1.0733104 | N18: =IFERROR(((AW18-AX18)/AW18)/((AD18-AE18)/AD18),1) -> 0.94304595 | O18: =IFERROR((1-(AM18+AO18)/AN18)/(1-(BF18+BH18)/BG18),1) -> 1.804472 | P18: =IFERROR(AD18/AW18,1) -> 1.0605061 | Q18: =IFERROR((AZ18/(AZ18+BH18))/(AG18/(AG18+AO18)),1) -> 1.8300294 | R18: =IFERROR((AF18/AD18)/(AY18/AW18),1) -> 1.0892008 | S18: =IFERROR((AH18-AI18)/AN18,0) -> 0.091393807 | T18: =IFERROR(((AS18+N(AU18))/AN18)/((BL18+N(BN18))/BG18),1) -> 0.78748579 | U18: =IFERROR((((AM18-AP18-N(AQ18))-(AS18-N(AV18))+(AN18-AM18-N(AR18))-(AT18-AS18-N(AU18))+(N(AQ18)+N(AR18))-(N(AU18)+N(AV18)))-((BF18-BI18-N(BJ18))-(BL18-N(BO18))+(BG18-BF18-N(BK18))-(BM18-BL18-N(BN18))+(N(BJ18)+N(BK18))-(N(BN18)+N(BO18))))/((AN18+BG18)/2),0) -> 0.17737809 | V18: =IFERROR((AK18-BD18)/((AN18+BG18)/2),0) -> 0.025001418 | W18: =IFERROR((N(AL18)-N(BE18))/((AN18+BG18)/2),0) -> 0.038095963 | X18: =IFERROR((AN18-N(AO18)-AP18)/AN18,0) -> 0.46770621 | Y18: =IF(COUNT(BP18,BQ18,BR18,BS18)=4,IFERROR((AD18-(AK18-BD18))/(AW18-(BD18-BP18))-1,0),0) -> 0.047286879 | Z18: =IF(COUNT(BP18,BQ18,BR18,BS18)=4,IFERROR(AH18/((AN18+BG18)/2)-BA18/((BG18+BR18)/2),0),0) -> 0.24212211 | AA18: =IF(N(AJ18)>0,1,0) -> 1 | AB18: =Inputs!$C$24+Inputs!$C$25*U18+Inputs!$C$26*V18+Inputs!$C$27*W18+Inputs!$C$28*X18+Inputs!$C$29*Y18+Inputs!$C$30*Z18+Inputs!$C$31*AA18 -> -5.9075266 | AD18: 819.592 | AE18: 556.091 | AF18: 78.971 | AG18: 32.39 | AH18: 193.301 | AI18: 121.103 | AJ18: 0.962 | AK18: 143.331 | AL18: 89.363 | AM18: 456.826 | AN18: 789.966 | AO18: 238.256 | AP18: 182.238 | AQ18: n/a | AR18: n/a | AS18: 148.295 | AT18: 479.657 | AU18: 201.653 | AV18: n/a | AW18: 772.831 | AX18: 538.515 | AY18: 68.367 | AZ18: 51.224 | BA18: 21.793 | BB18: 104.531 | BC18: 9.336 | BD18: 125.922 | BE18: 62.836 | BF18: 379.896 | BG18: 602.675 | BH18: 182.663 | BI18: 162.111 | BJ18: n/a | BK18: n/a | BL18: 137.639 | BM18: 436.005 | BN18: 201.389 | BO18: n/a | BP18: 119.054 | BQ18: 770.405 | BR18: 625.744 | BS18: 74.12
B19: MagnaChip | C19: MX | D19: 2013 | E19: 42047 | F19: 1 | G19: =Inputs!$C$13+Inputs!$C$14*M19+Inputs!$C$15*N19+Inputs!$C$16*O19+Inputs!$C$17*P19+Inputs!$C$18*Q19+Inputs!$C$19*R19+Inputs!$C$20*S19+Inputs!$C$21*T19 -> -3.6619142 | H19: =EXP(AB19)/(1+EXP(AB19))/Inputs!$C$32 -> 0.57667799 | I19: =IF(AND(F19=1,G19>Inputs!$C$7),1,0) -> 0 | J19: =IF(AND(F19=1,H19>Inputs!$C$8),1,0) -> 0 | K19: =MAX(I19,J19) -> 0 | L19: =I19*J19 -> 0 | M19: =IFERROR((AK19/AD19)/(BD19/AW19),1) -> 0.81862184 | N19: =IFERROR(((AW19-AX19)/AW19)/((AD19-AE19)/AD19),1) -> 1.4265 | O19: =IFERROR((1-(AM19+AO19)/AN19)/(1-(BF19+BH19)/BG19),1) -> 0.78792379 | P19: =IFERROR(AD19/AW19,1) -> 0.90938222 | Q19: =IFERROR((AZ19/(AZ19+BH19))/(AG19/(AG19+AO19)),1) -> 1.0437043 | R19: =IFERROR((AF19/AD19)/(AY19/AW19),1) -> 1.1407463 | S19: =IFERROR((AH19-AI19)/AN19,0) -> -0.21266815 | T19: =IFERROR(((AS19+N(AU19))/AN19)/((BL19+N(BN19))/BG19),1) -> 1.1818709 | U19: =IFERROR((((AM19-AP19-N(AQ19))-(AS19-N(AV19))+(AN19-AM19-N(AR19))-(AT19-AS19-N(AU19))+(N(AQ19)+N(AR19))-(N(AU19)+N(AV19)))-((BF19-BI19-N(BJ19))-(BL19-N(BO19))+(BG19-BF19-N(BK19))-(BM19-BL19-N(BN19))+(N(BJ19)+N(BK19))-(N(BN19)+N(BO19))))/((AN19+BG19)/2),0) -> -0.12459416 | V19: =IFERROR((AK19-BD19)/((AN19+BG19)/2),0) -> -0.041479827 | W19: =IFERROR((N(AL19)-N(BE19))/((AN19+BG19)/2),0) -> -0.011770868 | X19: =IFERROR((AN19-N(AO19)-AP19)/AN19,0) -> 0.34755354 | Y19: =IF(COUNT(BP19,BQ19,BR19,BS19)=4,IFERROR((AD19-(AK19-BD19))/(AW19-(BD19-BP19))-1,0),0) -> -0.053127274 | Z19: =IF(COUNT(BP19,BQ19,BR19,BS19)=4,IFERROR(AH19/((AN19+BG19)/2)-BA19/((BG19+BR19)/2),0),0) -> -0.27297562 | AA19: =IF(N(AJ19)>0,1,0) -> 1 | AB19: =Inputs!$C$24+Inputs!$C$25*U19+Inputs!$C$26*V19+Inputs!$C$27*W19+Inputs!$C$28*X19+Inputs!$C$29*Y19+Inputs!$C$30*Z19+Inputs!$C$31*AA19 -> -6.1477577 | AD19: 734.177 | AE19: 579.109 | AF19: 85.767 | AG19: 32.726 | AH19: -64.203 | AI19: 68.755 | AJ19: 230.211 | AK19: 78.898 | AL19: 74.698 | AM19: 334.162 | AN19: 625.19 | AO19: 254.297 | AP19: 153.606 | AQ19: n/a | AR19: n/a | AS19: 162.095 | AT19: 543.649 | AU19: 223.923 | AV19: n/a | AW19: 807.336 | AX19: 564.089 | AY19: 82.677 | AZ19: 32.066 | BA19: 110.038 | BB19: 121.103 | BC19: 0.962 | BD19: 105.983 | BE19: 82.384 | BF19: 392.594 | BG19: 680.746 | BH19: 237.392 | BI19: 182.238 | BJ19: n/a | BK19: n/a | BL19: 153.987 | BM19: 489.217 | BN19: 201.653 | BO19: n/a | BP19: 102.622 | BQ19: 743.13 | BR19: 579.346 | BS19: -11.301
B20: Orthofix | C20: OFIX | D20: 2011 | E20: 40968 | F20: 1 | G20: =Inputs!$C$13+Inputs!$C$14*M20+Inputs!$C$15*N20+Inputs!$C$16*O20+Inputs!$C$17*P20+Inputs!$C$18*Q20+Inputs!$C$19*R20+Inputs!$C$20*S20+Inputs!$C$21*T20 -> -3.1551497 | H20: =EXP(AB20)/(1+EXP(AB20))/Inputs!$C$32 -> 1.6802696 | I20: =IF(AND(F20=1,G20>Inputs!$C$7),1,0) -> 0 | J20: =IF(AND(F20=1,H20>Inputs!$C$8),1,0) -> 0 | K20: =MAX(I20,J20) -> 0 | L20: =I20*J20 -> 0 | M20: =IFERROR((AK20/AD20)/(BD20/AW20),1) -> 1.0644956 | N20: =IFERROR(((AW20-AX20)/AW20)/((AD20-AE20)/AD20),1) -> 1.0092277 | O20: =IFERROR((1-(AM20+AO20)/AN20)/(1-(BF20+BH20)/BG20),1) -> 0.84070392 | P20: =IFERROR(AD20/AW20,1) -> 1.0259014 | Q20: =IFERROR((AZ20/(AZ20+BH20))/(AG20/(AG20+AO20)),1) -> 1.0882423 | R20: =IFERROR((AF20/AD20)/(AY20/AW20),1) -> 0.97629895 | S20: =IFERROR((AH20-AI20)/AN20,0) -> -0.094678895 | T20: =IFERROR(((AS20+N(AU20))/AN20)/((BL20+N(BN20))/BG20),1) -> 1.8236339 | U20: =IFERROR((((AM20-AP20-N(AQ20))-(AS20-N(AV20))+(AN20-AM20-N(AR20))-(AT20-AS20-N(AU20))+(N(AQ20)+N(AR20))-(N(AU20)+N(AV20)))-((BF20-BI20-N(BJ20))-(BL20-N(BO20))+(BG20-BF20-N(BK20))-(BM20-BL20-N(BN20))+(N(BJ20)+N(BK20))-(N(BN20)+N(BO20))))/((AN20+BG20)/2),0) -> -0.0082583068 | V20: =IFERROR((AK20-BD20)/((AN20+BG20)/2),0) -> 0.019012881 | W20: =IFERROR((N(AL20)-N(BE20))/((AN20+BG20)/2),0) -> 0.010246703 | X20: =IFERROR((AN20-N(AO20)-AP20)/AN20,0) -> 0.87731885 | Y20: =IF(COUNT(BP20,BQ20,BR20,BS20)=4,IFERROR((AD20-(AK20-BD20))/(AW20-(BD20-BP20))-1,0),0) -> 0 | Z20: =IF(COUNT(BP20,BQ20,BR20,BS20)=4,IFERROR(AH20/((AN20+BG20)/2)-BA20/((BG20+BR20)/2),0),0) -> 0 | AA20: =IF(N(AJ20)>0,1,0) -> 1 | AB20: =Inputs!$C$24+Inputs!$C$25*U20+Inputs!$C$26*V20+Inputs!$C$27*W20+Inputs!$C$28*X20+Inputs!$C$29*Y20+Inputs!$C$30*Z20+Inputs!$C$31*AA20 -> -5.0742318 | AD20: 578.988 | AE20: 139.186 | AF20: 320.077 | AG20: 22.776 | AH20: -1.073 | AI20: 64.781 | AJ20: 20.113 | AK20: 146.538 | AL20: 91.247 | AM20: 404.59 | AN20: 695.551 | AO20: 52.124 | AP20: 33.207 | AQ20: n/a | AR20: n/a | AS20: 175.412 | AT20: 380.38 | AU20: n/a | AV20: 17.5 | AW20: 564.37 | AX20: 131.716 | AY20: 319.57 | AZ20: 22.521 | BA20: n/a | BB20: 42.508 | BC20: 7.854 | BD20: 134.184 | BE20: 84.589 | BF20: 311.76 | BG20: 603.989 | BH20: 45.535 | BI20: 13.561 | BJ20: n/a | BK20: n/a | BL20: 83.526 | BM20: 303.098 | BN20: n/a | BO20: 7.5 | BP20: n/a | BQ20: 545.635 | BR20: n/a | BS20: n/a
B21: Orthofix | C21: OFIX | D21: 2012 | E21: 41334 | F21: 1 | G21: =Inputs!$C$13+Inputs!$C$14*M21+Inputs!$C$15*N21+Inputs!$C$16*O21+Inputs!$C$17*P21+Inputs!$C$18*Q21+Inputs!$C$19*R21+Inputs!$C$20*S21+Inputs!$C$21*T21 -> -1.6138998 | H21: =EXP(AB21)/(1+EXP(AB21))/Inputs!$C$32 -> 1.6264335 | I21: =IF(AND(F21=1,G21>Inputs!$C$7),1,0) -> 1 | J21: =IF(AND(F21=1,H21>Inputs!$C$8),1,0) -> 0 | K21: =MAX(I21,J21) -> 1 | L21: =I21*J21 -> 0 | M21: =IFERROR((AK21/AD21)/(BD21/AW21),1) -> 1.1507541 | N21: =IFERROR(((AW21-AX21)/AW21)/((AD21-AE21)/AD21),1) -> 0.98778665 | O21: =IFERROR((1-(AM21+AO21)/AN21)/(1-(BF21+BH21)/BG21),1) -> 1.409401 | P21: =IFERROR(AD21/AW21,1) -> 0.9834064 | Q21: =IFERROR((AZ21/(AZ21+BH21))/(AG21/(AG21+AO21)),1) -> 1.2172468 | R21: =IFERROR((AF21/AD21)/(AY21/AW21),1) -> 0.97708959 | S21: =IFERROR((AH21-AI21)/AN21,0) -> 0.084734503 | T21: =IFERROR(((AS21+N(AU21))/AN21)/((BL21+N(BN21))/BG21),1) -> 0.51724212 | U21: =IFERROR((((AM21-AP21-N(AQ21))-(AS21-N(AV21))+(AN21-AM21-N(AR21))-(AT21-AS21-N(AU21))+(N(AQ21)+N(AR21))-(N(AU21)+N(AV21)))-((BF21-BI21-N(BJ21))-(BL21-N(BO21))+(BG21-BF21-N(BK21))-(BM21-BL21-N(BN21))+(N(BJ21)+N(BK21))-(N(BN21)+N(BO21))))/((AN21+BG21)/2),0) -> 0.14242612 | V21: =IFERROR((AK21-BD21)/((AN21+BG21)/2),0) -> 0.028935606 | W21: =IFERROR((N(AL21)-N(BE21))/((AN21+BG21)/2),0) -> 0.009555302 | X21: =IFERROR((AN21-N(AO21)-AP21)/AN21,0) -> 0.83656533 | Y21: =IF(COUNT(BP21,BQ21,BR21,BS21)=4,IFERROR((AD21-(AK21-BD21))/(AW21-(BD21-BP21))-1,0),0) -> -0.056513891 | Z21: =IF(COUNT(BP21,BQ21,BR21,BS21)=4,IFERROR(AH21/((AN21+BG21)/2)-BA21/((BG21+BR21)/2),0),0) -> 0.091901998 | AA21: =IF(N(AJ21)>0,1,0) -> 1 | AB21: =Inputs!$C$24+Inputs!$C$25*U21+Inputs!$C$26*V21+Inputs!$C$27*W21+Inputs!$C$28*X21+Inputs!$C$29*Y21+Inputs!$C$30*Z21+Inputs!$C$31*AA21 -> -5.1069969 | AD21: 462.32 | AE21: 86.492 | AF21: 254.17 | AG21: 20.261 | AH21: 53.936 | AI21: 11.206 | AJ21: 25.586 | AK21: 150.316 | AL21: 88.744 | AM21: 340.444 | AN21: 504.281 | AO21: 51.362 | AP21: 31.055 | AQ21: n/a | AR21: n/a | AS21: 68.797 | AT21: 105.183 | AU21: n/a | AV21: n/a | AW21: 470.121 | AX21: 92.619 | AY21: 264.519 | AZ21: 22.776 | BA21: -1.74 | BB21: 64.781 | BC21: 20.113 | BD21: 132.828 | BE21: 82.969 | BF21: 549.62 | BG21: 704.472 | BH21: 43.368 | BI21: 33.207 | BJ21: n/a | BK21: n/a | BL21: 185.809 | BM21: 389.301 | BN21: n/a | BO21: 17.5 | BP21: 134.184 | BQ21: 460.629 | BR21: 603.989 | BS21: 27.758
B22: Pareteum | C22: TEUM | D22: 2018 | E22: 43542 | F22: 1 | G22: =Inputs!$C$13+Inputs!$C$14*M22+Inputs!$C$15*N22+Inputs!$C$16*O22+Inputs!$C$17*P22+Inputs!$C$18*Q22+Inputs!$C$19*R22+Inputs!$C$20*S22+Inputs!$C$21*T22 -> 2.5620237 | H22: =EXP(AB22)/(1+EXP(AB22))/Inputs!$C$32 -> 4.9582857 | I22: =IF(AND(F22=1,G22>Inputs!$C$7),1,0) -> 1 | J22: =IF(AND(F22=1,H22>Inputs!$C$8),1,0) -> 1 | K22: =MAX(I22,J22) -> 1 | L22: =I22*J22 -> 1 | M22: =IFERROR((AK22/AD22)/(BD22/AW22),1) -> 3.117214 | N22: =IFERROR(((AW22-AX22)/AW22)/((AD22-AE22)/AD22),1) -> 1.0683191 | O22: =IFERROR((1-(AM22+AO22)/AN22)/(1-(BF22+BH22)/BG22),1) -> 5.3235416 | P22: =IFERROR(AD22/AW22,1) -> 2.3942218 | Q22: =IFERROR((AZ22/(AZ22+BH22))/(AG22/(AG22+AO22)),1) -> 0.90153864 | R22: =IFERROR((AF22/AD22)/(AY22/AW22),1) -> 0.75039206 | S22: =IFERROR((AH22-AI22)/AN22,0) -> -0.032991012 | T22: =IFERROR(((AS22+N(AU22))/AN22)/((BL22+N(BN22))/BG22),1) -> 0.4173909 | U22: =IFERROR((((AM22-AP22-N(AQ22))-(AS22-N(AV22))+(AN22-AM22-N(AR22))-(AT22-AS22-N(AU22))+(N(AQ22)+N(AR22))-(N(AU22)+N(AV22)))-((BF22-BI22-N(BJ22))-(BL22-N(BO22))+(BG22-BF22-N(BK22))-(BM22-BL22-N(BN22))+(N(BJ22)+N(BK22))-(N(BN22)+N(BO22))))/((AN22+BG22)/2),0) -> 1.3320941 | V22: =IFERROR((AK22-BD22)/((AN22+BG22)/2),0) -> 0.1427645 | W22: =IFERROR((N(AL22)-N(BE22))/((AN22+BG22)/2),0) -> 0 | X22: =IFERROR((AN22-N(AO22)-AP22)/AN22,0) -> 0.93414753 | Y22: =IF(COUNT(BP22,BQ22,BR22,BS22)=4,IFERROR((AD22-(AK22-BD22))/(AW22-(BD22-BP22))-1,0),0) -> 0.58068367 | Z22: =IF(COUNT(BP22,BQ22,BR22,BS22)=4,IFERROR(AH22/((AN22+BG22)/2)-BA22/((BG22+BR22)/2),0),0) -> 0.51036114 | AA22: =IF(N(AJ22)>0,1,0) -> 1 | AB22: =Inputs!$C$24+Inputs!$C$25*U22+Inputs!$C$26*V22+Inputs!$C$27*W22+Inputs!$C$28*X22+Inputs!$C$29*Y22+Inputs!$C$30*Z22+Inputs!$C$31*AA22 -> -3.9798464 | AD22: 32.435736 | AE22: 10.329646 | AF22: 20.970146 | AG22: 5.427029 | AH22: -12.97465 | AI22: -7.661739 | AJ22: 12.200002 | AK22: 15.361594 | AL22: n/a | AM22: 23.927908 | AN22: 161.04117 | AO22: 4.55325 | AP22: 6.051709 | AQ22: n/a | AR22: 0 | AS22: 20.005976 | AT22: 28.976502 | AU22: n/a | AV22: n/a | AW22: 13.547507 | AX22: 3.683609 | AY22: 11.672096 | AZ22: 4.533109 | BA22: -12.462979 | BB22: -2.61616 | BC22: 24.242171 | BD22: 2.058284 | BE22: n/a | BF22: 16.696328 | BG22: 25.326033 | BH22: 4.71371 | BI22: 13.537899 | BJ22: n/a | BK22: 3.230208 | BL22: 7.537842 | BM22: 9.9045 | BN22: n/a | BO22: n/a | BP22: 0.61467 | BQ22: 12.855811 | BR22: 13.045289 | BS22: -31.444704
B23: Iconix Brand | C23: ICON | D23: 2013 | E23: 41697 | F23: 1 | G23: =Inputs!$C$13+Inputs!$C$14*M23+Inputs!$C$15*N23+Inputs!$C$16*O23+Inputs!$C$17*P23+Inputs!$C$18*Q23+Inputs!$C$19*R23+Inputs!$C$20*S23+Inputs!$C$21*T23 -> -2.6174636 | H23: =EXP(AB23)/(1+EXP(AB23))/Inputs!$C$32 -> 1.6271897 | I23: =IF(AND(F23=1,G23>Inputs!$C$7),1,0) -> 0 | J23: =IF(AND(F23=1,H23>Inputs!$C$8),1,0) -> 0 | K23: =MAX(I23,J23) -> 0 | L23: =I23*J23 -> 0 | M23: =IFERROR((AK23/AD23)/(BD23/AW23),1) -> 0.97076835 | N23: =IFERROR(((AW23-AX23)/AW23)/((AD23-AE23)/AD23),1) -> 1 | O23: =IFERROR((1-(AM23+AO23)/AN23)/(1-(BF23+BH23)/BG23),1) -> 0.978726 | P23: =IFERROR(AD23/AW23,1) -> 1.222736 | Q23: =IFERROR((AZ23/(AZ23+BH23))/(AG23/(AG23+AO23)),1) -> 0.92350352 | R23: =IFERROR((AF23/AD23)/(AY23/AW23),1) -> 1.035626 | S23: =IFERROR((AH23-AI23)/AN23,0) -> -0.036620243 | T23: =IFERROR(((AS23+N(AU23))/AN23)/((BL23+N(BN23))/BG23),1) -> 1.3498025 | U23: =IFERROR((((AM23-AP23-N(AQ23))-(AS23-N(AV23))+(AN23-AM23-N(AR23))-(AT23-AS23-N(AU23))+(N(AQ23)+N(AR23))-(N(AU23)+N(AV23)))-((BF23-BI23-N(BJ23))-(BL23-N(BO23))+(BG23-BF23-N(BK23))-(BM23-BL23-N(BN23))+(N(BJ23)+N(BK23))-(N(BN23)+N(BO23))))/((AN23+BG23)/2),0) -> -0.089111954 | V23: =IFERROR((AK23-BD23)/((AN23+BG23)/2),0) -> 0.0059682527 | W23: =IFERROR((N(AL23)-N(BE23))/((AN23+BG23)/2),0) -> 0 | X23: =IFERROR((AN23-N(AO23)-AP23)/AN23,0) -> 0.89943829 | Y23: =IF(COUNT(BP23,BQ23,BR23,BS23)=4,IFERROR((AD23-(AK23-BD23))/(AW23-(BD23-BP23))-1,0),0) -> 0.19655236 | Z23: =IF(COUNT(BP23,BQ23,BR23,BS23)=4,IFERROR(AH23/((AN23+BG23)/2)-BA23/((BG23+BR23)/2),0),0) -> 0.00081297385 | AA23: =IF(N(AJ23)>0,1,0) -> 1 | AB23: =Inputs!$C$24+Inputs!$C$25*U23+Inputs!$C$26*V23+Inputs!$C$27*W23+Inputs!$C$28*X23+Inputs!$C$29*Y23+Inputs!$C$30*Z23+Inputs!$C$31*AA23 -> -5.1065292 | AD23: 432.626 | AE23: n/a | AF23: 175.215 | AG23: 2.702 | AH23: 128.048 | AI23: 232.789 | AJ23: 662.188 | AK23: 101.19 | AL23: n/a | AM23: 476.628 | AN23: 2860.194 | AO23: 8.837 | AP23: 278.789 | AQ23: n/a | AR23: n/a | AS23: 127.858 | AT23: 1758.252 | AU23: 1366.069 | AV23: 61.25 | AW23: 353.818 | AX23: n/a | AY23: 138.368 | AZ23: 2.784 | BA23: 109.408 | BB23: 204.434 | BC23: 750 | BD23: 85.249 | BE23: n/a | BF23: 366.351 | BG23: 2481.738 | BH23: 10.09 | BI23: 238.672 | BJ23: n/a | BK23: n/a | BL23: 100.61 | BM23: 1181.898 | BN23: 859.718 | BO23: 52 | BP23: 79.669 | BQ23: 369.845 | BR23: 2161.303 | BS23: 126.105
B24: Iconix Brand | C24: ICON | D24: 2014 | E24: 42065 | F24: 1 | G24: =Inputs!$C$13+Inputs!$C$14*M24+Inputs!$C$15*N24+Inputs!$C$16*O24+Inputs!$C$17*P24+Inputs!$C$18*Q24+Inputs!$C$19*R24+Inputs!$C$20*S24+Inputs!$C$21*T24 -> -2.2308508 | H24: =EXP(AB24)/(1+EXP(AB24))/Inputs!$C$32 -> 0.70030294 | I24: =IF(AND(F24=1,G24>Inputs!$C$7),1,0) -> 0 | J24: =IF(AND(F24=1,H24>Inputs!$C$8),1,0) -> 0 | K24: =MAX(I24,J24) -> 0 | L24: =I24*J24 -> 0 | M24: =IFERROR((AK24/AD24)/(BD24/AW24),1) -> 1.2272368 | N24: =IFERROR(((AW24-AX24)/AW24)/((AD24-AE24)/AD24),1) -> 1 | O24: =IFERROR((1-(AM24+AO24)/AN24)/(1-(BF24+BH24)/BG24),1) -> 1.0369423 | P24: =IFERROR(AD24/AW24,1) -> 1.0661472 | Q24: =IFERROR((AZ24/(AZ24+BH24))/(AG24/(AG24+AO24)),1) -> 0.93152592 | R24: =IFERROR((AF24/AD24)/(AY24/AW24),1) -> 1.0995959 | S24: =IFERROR((AH24-AI24)/AN24,0) -> -0.0034053841 | T24: =IFERROR(((AS24+N(AU24))/AN24)/((BL24+N(BN24))/BG24),1) -> 0.97828094 | U24: =IFERROR((((AM24-AP24-N(AQ24))-(AS24-N(AV24))+(AN24-AM24-N(AR24))-(AT24-AS24-N(AU24))+(N(AQ24)+N(AR24))-(N(AU24)+N(AV24)))-((BF24-BI24-N(BJ24))-(BL24-N(BO24))+(BG24-BF24-N(BK24))-(BM24-BL24-N(BN24))+(N(BJ24)+N(BK24))-(N(BN24)+N(BO24))))/((AN24+BG24)/2),0) -> 0.04098928 | V24: =IFERROR((AK24-BD24)/((AN24+BG24)/2),0) -> 0.0097592195 | W24: =IFERROR((N(AL24)-N(BE24))/((AN24+BG24)/2),0) -> 0 | X24: =IFERROR((AN24-N(AO24)-AP24)/AN24,0) -> 0.95274677 | Y24: =IF(COUNT(BP24,BQ24,BR24,BS24)=4,IFERROR((AD24-(AK24-BD24))/(AW24-(BD24-BP24))-1,0),0) -> 0.014394823 | Z24: =IF(COUNT(BP24,BQ24,BR24,BS24)=4,IFERROR(AH24/((AN24+BG24)/2)-BA24/((BG24+BR24)/2),0),0) -> 0.0053356931 | AA24: =IF(N(AJ24)>0,1,0) -> 0 | AB24: =Inputs!$C$24+Inputs!$C$25*U24+Inputs!$C$26*V24+Inputs!$C$27*W24+Inputs!$C$28*X24+Inputs!$C$29*Y24+Inputs!$C$30*Z24+Inputs!$C$31*AA24 -> -5.9530702 | AD24: 461.243 | AE24: n/a | AF24: 205.41 | AG24: 2.605 | AH24: 152.736 | AI24: 162.521 | AJ24: n/a | AK24: 118.774 | AL24: n/a | AM24: 385.268 | AN24: 2873.391 | AO24: 7.758 | AP24: 128.019 | AQ24: n/a | AR24: n/a | AS24: 137.128 | AT24: 1804.63 | AU24: 1332.954 | AV24: 61.123 | AW24: 432.626 | AX24: n/a | AY24: 175.215 | AZ24: 2.702 | BA24: 128.048 | BB24: 232.789 | BC24: 392 | BD24: 90.777 | BE24: n/a | BF24: 471.008 | BG24: 2864.158 | BH24: 8.837 | BI24: 278.789 | BJ24: n/a | BK24: n/a | BL24: 131.822 | BM24: 1762.216 | BN24: 1366.069 | BO24: 61.25 | BP24: 85.249 | BQ24: 353.818 | BR24: 2481.738 | BS24: 109.408
B25: Granite Construction | C25: GVA | D25: 2017 | E25: 43147 | F25: 1 | G25: =Inputs!$C$13+Inputs!$C$14*M25+Inputs!$C$15*N25+Inputs!$C$16*O25+Inputs!$C$17*P25+Inputs!$C$18*Q25+Inputs!$C$19*R25+Inputs!$C$20*S25+Inputs!$C$21*T25 -> -2.4529073 | H25: =EXP(AB25)/(1+EXP(AB25))/Inputs!$C$32 -> 0.37196843 | I25: =IF(AND(F25=1,G25>Inputs!$C$7),1,0) -> 0 | J25: =IF(AND(F25=1,H25>Inputs!$C$8),1,0) -> 0 | K25: =MAX(I25,J25) -> 0 | L25: =I25*J25 -> 0 | M25: =IFERROR((AK25/AD25)/(BD25/AW25),1) -> 1 | N25: =IFERROR(((AW25-AX25)/AW25)/((AD25-AE25)/AD25),1) -> 1.1377308 | O25: =IFERROR((1-(AM25+AO25)/AN25)/(1-(BF25+BH25)/BG25),1) -> 0.9052504 | P25: =IFERROR(AD25/AW25,1) -> 1.1889337 | Q25: =IFERROR((AZ25/(AZ25+BH25))/(AG25/(AG25+AO25)),1) -> 0.97594698 | R25: =IFERROR((AF25/AD25)/(AY25/AW25),1) -> 0.85455953 | S25: =IFERROR((AH25-AI25)/AN25,0) -> -0.041184779 | T25: =IFERROR(((AS25+N(AU25))/AN25)/((BL25+N(BN25))/BG25),1) -> 1.0165911 | U25: =IFERROR((((AM25-AP25-N(AQ25))-(AS25-N(AV25))+(AN25-AM25-N(AR25))-(AT25-AS25-N(AU25))+(N(AQ25)+N(AR25))-(N(AU25)+N(AV25)))-((BF25-BI25-N(BJ25))-(BL25-N(BO25))+(BG25-BF25-N(BK25))-(BM25-BL25-N(BN25))+(N(BJ25)+N(BK25))-(N(BN25)+N(BO25))))/((AN25+BG25)/2),0) -> 0 | V25: =IFERROR((AK25-BD25)/((AN25+BG25)/2),0) -> 0 | W25: =IFERROR((N(AL25)-N(BE25))/((AN25+BG25)/2),0) -> 0.00402282 | X25: =IFERROR((AN25-N(AO25)-AP25)/AN25,0) -> 0.65751253 | Y25: =IF(COUNT(BP25,BQ25,BR25,BS25)=4,IFERROR((AD25-(AK25-BD25))/(AW25-(BD25-BP25))-1,0),0) -> 0 | Z25: =IF(COUNT(BP25,BQ25,BR25,BS25)=4,IFERROR(AH25/((AN25+BG25)/2)-BA25/((BG25+BR25)/2),0),0) -> 0 | AA25: =IF(N(AJ25)>0,1,0) -> 0 | AB25: =Inputs!$C$24+Inputs!$C$25*U25+Inputs!$C$26*V25+Inputs!$C$27*W25+Inputs!$C$28*X25+Inputs!$C$29*Y25+Inputs!$C$30*Z25+Inputs!$C$31*AA25 -> -6.5869915 | AD25: 2989.713 | AE25: 2674.78 | AF25: 222.811 | AG25: 66.345 | AH25: 69.098 | AI25: 146.195 | AJ25: n/a | AK25: n/a | AL25: 62.497 | AM25: 1232.078 | AN25: 1871.978 | AO25: 407.418 | AP25: 233.711 | AQ25: 67.775 | AR25: 65.015 | AS25: 655.274 | AT25: n/a | AU25: 178.453 | AV25: 46.048 | AW25: 2514.617 | AX25: 2213.247 | AY25: 219.299 | AZ25: 64.375 | BA25: 57.122 | BB25: 73.146 | BC25: n/a | BD25: n/a | BE25: 55.245 | BF25: 1088.992 | BG25: 1733.453 | BH25: 406.65 | BI25: 189.326 | BJ25: 64.884 | BK25: 62.895 | BL25: 529.934 | BM25: n/a | BN25: 229.498 | BO25: 14.796 | BP25: n/a | BQ25: 2371.029 | BR25: 1626.878 | BS25: 60.485
B26: Granite Construction | C26: GVA | D26: 2018 | E26: 43518 | F26: 1 | G26: =Inputs!$C$13+Inputs!$C$14*M26+Inputs!$C$15*N26+Inputs!$C$16*O26+Inputs!$C$17*P26+Inputs!$C$18*Q26+Inputs!$C$19*R26+Inputs!$C$20*S26+Inputs!$C$21*T26 -> -2.3659551 | H26: =EXP(AB26)/(1+EXP(AB26))/Inputs!$C$32 -> 0.38041561 | I26: =IF(AND(F26=1,G26>Inputs!$C$7),1,0) -> 0 | J26: =IF(AND(F26=1,H26>Inputs!$C$8),1,0) -> 0 | K26: =MAX(I26,J26) -> 0 | L26: =I26*J26 -> 0 | M26: =IFERROR((AK26/AD26)/(BD26/AW26),1) -> 0.88865623 | N26: =IFERROR(((AW26-AX26)/AW26)/((AD26-AE26)/AD26),1) -> 0.89816336 | O26: =IFERROR((1-(AM26+AO26)/AN26)/(1-(BF26+BH26)/BG26),1) -> 1.6631115 | P26: =IFERROR(AD26/AW26,1) -> 1.109944 | Q26: =IFERROR((AZ26/(AZ26+BH26))/(AG26/(AG26+AO26)),1) -> 0.83014643 | R26: =IFERROR((AF26/AD26)/(AY26/AW26),1) -> 1.1150478 | S26: =IFERROR((AH26-AI26)/AN26,0) -> -0.01775821 | T26: =IFERROR(((AS26+N(AU26))/AN26)/((BL26+N(BN26))/BG26),1) -> 0.91836126 | U26: =IFERROR((((AM26-AP26-N(AQ26))-(AS26-N(AV26))+(AN26-AM26-N(AR26))-(AT26-AS26-N(AU26))+(N(AQ26)+N(AR26))-(N(AU26)+N(AV26)))-((BF26-BI26-N(BJ26))-(BL26-N(BO26))+(BG26-BF26-N(BK26))-(BM26-BL26-N(BN26))+(N(BJ26)+N(BK26))-(N(BN26)+N(BO26))))/((AN26+BG26)/2),0) -> 0 | V26: =IFERROR((AK26-BD26)/((AN26+BG26)/2),0) -> -0.0030101787 | W26: =IFERROR((N(AL26)-N(BE26))/((AN26+BG26)/2),0) -> 0.012015879 | X26: =IFERROR((AN26-N(AO26)-AP26)/AN26,0) -> 0.66789483 | Y26: =IF(COUNT(BP26,BQ26,BR26,BS26)=4,IFERROR((AD26-(AK26-BD26))/(AW26-(BD26-BP26))-1,0),0) -> 0 | Z26: =IF(COUNT(BP26,BQ26,BR26,BS26)=4,IFERROR(AH26/((AN26+BG26)/2)-BA26/((BG26+BR26)/2),0),0) -> 0 | AA26: =IF(N(AJ26)>0,1,0) -> 0 | AB26: =Inputs!$C$24+Inputs!$C$25*U26+Inputs!$C$26*V26+Inputs!$C$27*W26+Inputs!$C$28*X26+Inputs!$C$29*Y26+Inputs!$C$30*Z26+Inputs!$C$31*AA26 -> -6.5645049 | AD26: 3318.414 | AE26: 2929.222 | AF26: 272.776 | AG26: 111.544 | AH26: 42.41 | AI26: 86.39 | AJ26: n/a | AK26: 473.246 | AL26: 88.623 | AM26: 1415.389 | AN26: 2476.601 | AO26: 549.688 | AP26: 272.804 | AQ26: n/a | AR26: n/a | AS26: 677.842 | AT26: n/a | AU26: 335.119 | AV26: 47.286 | AW26: 2989.713 | AX26: 2674.78 | AY26: 220.4 | AZ26: 66.345 | BA26: 69.098 | BB26: 146.195 | BC26: n/a | BD26: 479.791 | BE26: 62.497 | BF26: 1232.078 | BG26: 1871.978 | BH26: 407.418 | BI26: 233.711 | BJ26: 67.775 | BK26: 65.015 | BL26: 655.274 | BM26: n/a | BN26: 178.453 | BO26: 46.048 | BP26: n/a | BQ26: 2514.617 | BR26: 1733.453 | BS26: 57.122
B27: Granite Construction | C27: GVA | D27: 2019 | E27: 44249 | F27: 1 | G27: =Inputs!$C$13+Inputs!$C$14*M27+Inputs!$C$15*N27+Inputs!$C$16*O27+Inputs!$C$17*P27+Inputs!$C$18*Q27+Inputs!$C$19*R27+Inputs!$C$20*S27+Inputs!$C$21*T27 -> -2.4083786 | H27: =EXP(AB27)/(1+EXP(AB27))/Inputs!$C$32 -> 1.1806857 | I27: =IF(AND(F27=1,G27>Inputs!$C$7),1,0) -> 0 | J27: =IF(AND(F27=1,H27>Inputs!$C$8),1,0) -> 0 | K27: =MAX(I27,J27) -> 0 | L27: =I27*J27 -> 0 | M27: =IFERROR((AK27/AD27)/(BD27/AW27),1) -> 1.0772983 | N27: =IFERROR(((AW27-AX27)/AW27)/((AD27-AE27)/AD27),1) -> 1.5833486 | O27: =IFERROR((1-(AM27+AO27)/AN27)/(1-(BF27+BH27)/BG27),1) -> 1.0529567 | P27: =IFERROR(AD27/AW27,1) -> 1.0482426 | Q27: =IFERROR((AZ27/(AZ27+BH27))/(AG27/(AG27+AO27)),1) -> 0.90991786 | R27: =IFERROR((AF27/AD27)/(AY27/AW27),1) -> 1.0770998 | S27: =IFERROR((AH27-AI27)/AN27,0) -> -0.06859431 | T27: =IFERROR(((AS27+N(AU27))/AN27)/((BL27+N(BN27))/BG27),1) -> 1.0836532 | U27: =IFERROR((((AM27-AP27-N(AQ27))-(AS27-N(AV27))+(AN27-AM27-N(AR27))-(AT27-AS27-N(AU27))+(N(AQ27)+N(AR27))-(N(AU27)+N(AV27)))-((BF27-BI27-N(BJ27))-(BL27-N(BO27))+(BG27-BF27-N(BK27))-(BM27-BL27-N(BN27))+(N(BJ27)+N(BK27))-(N(BN27)+N(BO27))))/((AN27+BG27)/2),0) -> 0 | V27: =IFERROR((AK27-BD27)/((AN27+BG27)/2),0) -> 0.025425431 | W27: =IFERROR((N(AL27)-N(BE27))/((AN27+BG27)/2),0) -> 0.00010630446 | X27: =IFERROR((AN27-N(AO27)-AP27)/AN27,0) -> 0.67844057 | Y27: =IF(COUNT(BP27,BQ27,BR27,BS27)=4,IFERROR((AD27-(AK27-BD27))/(AW27-(BD27-BP27))-1,0),0) -> 0.030734576 | Z27: =IF(COUNT(BP27,BQ27,BR27,BS27)=4,IFERROR(AH27/((AN27+BG27)/2)-BA27/((BG27+BR27)/2),0),0) -> -0.024692783 | AA27: =IF(N(AJ27)>0,1,0) -> 1 | AB27: =Inputs!$C$24+Inputs!$C$25*U27+Inputs!$C$26*V27+Inputs!$C$27*W27+Inputs!$C$28*X27+Inputs!$C$29*Y27+Inputs!$C$30*Z27+Inputs!$C$31*AA27 -> -5.428949 | AD27: 3445.606 | AE27: 3223.928 | AF27: 307.981 | AG27: 123.418 | AH27: -60.191 | AI27: 111.438 | AJ27: 230 | AK27: 547.417 | AL27: 88.885 | AM27: 1376.941 | AN27: 2502.088 | AO27: 542.297 | AP27: 262.273 | AQ27: n/a | AR27: n/a | AS27: 842.056 | AT27: n/a | AU27: 356.108 | AV27: 8.244 | AW27: 3287.031 | AX27: 2952.191 | AY27: 272.776 | AZ27: 111.544 | BA27: 0.582 | BB27: 86.39 | BC27: 0 | BD27: 484.753 | BE27: 88.623 | BF27: 1340.504 | BG27: 2427.15 | BH27: 549.688 | BI27: 272.804 | BJ27: n/a | BK27: n/a | BL27: 737.437 | BM27: n/a | BN27: 335.119 | BO27: 47.286 | BP27: 479.791 | BQ27: 2958.374 | BR27: 1871.978 | BS27: 34.116
B28: Diamond Foods | C28: DMND | D28: 2011 | E28: 41250 | F28: 0 | G28: =Inputs!$C$13+Inputs!$C$14*M28+Inputs!$C$15*N28+Inputs!$C$16*O28+Inputs!$C$17*P28+Inputs!$C$18*Q28+Inputs!$C$19*R28+Inputs!$C$20*S28+Inputs!$C$21*T28 -> -2.2890514 | H28: =EXP(AB28)/(1+EXP(AB28))/Inputs!$C$32 -> 0.59315565 | I28: =IF(AND(F28=1,G28>Inputs!$C$7),1,0) -> 0 | J28: =IF(AND(F28=1,H28>Inputs!$C$8),1,0) -> 0 | K28: =MAX(I28,J28) -> 0 | L28: =I28*J28 -> 0 | M28: =IFERROR((AK28/AD28)/(BD28/AW28),1) -> 1 | N28: =IFERROR(((AW28-AX28)/AW28)/((AD28-AE28)/AD28),1) -> 0.94792319 | O28: =IFERROR((1-(AM28+AO28)/AN28)/(1-(BF28+BH28)/BG28),1) -> 1 | P28: =IFERROR(AD28/AW28,1) -> 1.4167539 | Q28: =IFERROR((AZ28/(AZ28+BH28))/(AG28/(AG28+AO28)),1) -> 1 | R28: =IFERROR((AF28/AD28)/(AY28/AW28),1) -> 1.0661884 | S28: =IFERROR((AH28-AI28)/AN28,0) -> -0.030330174 | T28: =IFERROR(((AS28+N(AU28))/AN28)/((BL28+N(BN28))/BG28),1) -> 1 | U28: =IFERROR((((AM28-AP28-N(AQ28))-(AS28-N(AV28))+(AN28-AM28-N(AR28))-(AT28-AS28-N(AU28))+(N(AQ28)+N(AR28))-(N(AU28)+N(AV28)))-((BF28-BI28-N(BJ28))-(BL28-N(BO28))+(BG28-BF28-N(BK28))-(BM28-BL28-N(BN28))+(N(BJ28)+N(BK28))-(N(BN28)+N(BO28))))/((AN28+BG28)/2),0) -> 0 | V28: =IFERROR((AK28-BD28)/((AN28+BG28)/2),0) -> 0 | W28: =IFERROR((N(AL28)-N(BE28))/((AN28+BG28)/2),0) -> 0 | X28: =IFERROR((AN28-N(AO28)-AP28)/AN28,0) -> 0.89614765 | Y28: =IF(COUNT(BP28,BQ28,BR28,BS28)=4,IFERROR((AD28-(AK28-BD28))/(AW28-(BD28-BP28))-1,0),0) -> 0 | Z28: =IF(COUNT(BP28,BQ28,BR28,BS28)=4,IFERROR(AH28/((AN28+BG28)/2)-BA28/((BG28+BR28)/2),0),0) -> 0 | AA28: =IF(N(AJ28)>0,1,0) -> 0 | AB28: =Inputs!$C$24+Inputs!$C$25*U28+Inputs!$C$26*V28+Inputs!$C$27*W28+Inputs!$C$28*X28+Inputs!$C$29*Y28+Inputs!$C$30*Z28+Inputs!$C$31*AA28 -> -6.1195238 | AD28: 966.688 | AE28: 750.209 | AF28: 97.506 | AG28: 20 | AH28: 26.567 | AI28: 66.691 | AJ28: n/a | AK28: 98.275 | AL28: 153.534 | AM28: 299.999 | AN28: 1322.907 | AO28: 134.275 | AP28: 3.112 | AQ28: n/a | AR28: n/a | AS28: 247.553 | AT28: n/a | AU28: 490.001 | AV28: 41.7 | AW28: 682.326 | AX28: 537.484 | AY28: 64.551 | AZ28: 12.4 | BA28: 15.676 | BB28: -1.846 | BC28: 191.475 | BD28: n/a | BE28: n/a | BF28: n/a | BG28: n/a | BH28: n/a | BI28: 5.642 | BJ28: n/a | BK28: n/a | BL28: n/a | BM28: n/a | BN28: n/a | BO28: n/a | BP28: n/a | BQ28: n/a | BR28: n/a | BS28: n/a
B29: Hertz Global | C29: HTZ | D29: 2011 | E29: 40966 | F29: 0 | G29: =Inputs!$C$13+Inputs!$C$14*M29+Inputs!$C$15*N29+Inputs!$C$16*O29+Inputs!$C$17*P29+Inputs!$C$18*Q29+Inputs!$C$19*R29+Inputs!$C$20*S29+Inputs!$C$21*T29 -> -2.936456 | H29: =EXP(AB29)/(1+EXP(AB29))/Inputs!$C$32 -> 1.5900635 | I29: =IF(AND(F29=1,G29>Inputs!$C$7),1,0) -> 0 | J29: =IF(AND(F29=1,H29>Inputs!$C$8),1,0) -> 0 | K29: =MAX(I29,J29) -> 0 | L29: =I29*J29 -> 0 | M29: =IFERROR((AK29/AD29)/(BD29/AW29),1) -> 1 | N29: =IFERROR(((AW29-AX29)/AW29)/((AD29-AE29)/AD29),1) -> 1 | O29: =IFERROR((1-(AM29+AO29)/AN29)/(1-(BF29+BH29)/BG29),1) -> 1 | P29: =IFERROR(AD29/AW29,1) -> 1.0973015 | Q29: =IFERROR((AZ29/(AZ29+BH29))/(AG29/(AG29+AO29)),1) -> 1 | R29: =IFERROR((AF29/AD29)/(AY29/AW29),1) -> 1.0220908 | S29: =IFERROR((AH29-AI29)/AN29,0) -> -0.11529159 | T29: =IFERROR(((AS29+N(AU29))/AN29)/((BL29+N(BN29))/BG29),1) -> 1 | U29: =IFERROR((((AM29-AP29-N(AQ29))-(AS29-N(AV29))+(AN29-AM29-N(AR29))-(AT29-AS29-N(AU29))+(N(AQ29)+N(AR29))-(N(AU29)+N(AV29)))-((BF29-BI29-N(BJ29))-(BL29-N(BO29))+(BG29-BF29-N(BK29))-(BM29-BL29-N(BN29))+(N(BJ29)+N(BK29))-(N(BN29)+N(BO29))))/((AN29+BG29)/2),0) -> 0 | V29: =IFERROR((AK29-BD29)/((AN29+BG29)/2),0) -> 0 | W29: =IFERROR((N(AL29)-N(BE29))/((AN29+BG29)/2),0) -> -0.00019709595 | X29: =IFERROR((AN29-N(AO29)-AP29)/AN29,0) -> 0.87644611 | Y29: =IF(COUNT(BP29,BQ29,BR29,BS29)=4,IFERROR((AD29-(AK29-BD29))/(AW29-(BD29-BP29))-1,0),0) -> 0 | Z29: =IF(COUNT(BP29,BQ29,BR29,BS29)=4,IFERROR(AH29/((AN29+BG29)/2)-BA29/((BG29+BR29)/2),0),0) -> 0 | AA29: =IF(N(AJ29)>0,1,0) -> 1 | AB29: =Inputs!$C$24+Inputs!$C$25*U29+Inputs!$C$26*V29+Inputs!$C$27*W29+Inputs!$C$28*X29+Inputs!$C$29*Y29+Inputs!$C$30*Z29+Inputs!$C$31*AA29 -> -5.1297479 | AD29: 8298.38 | AE29: n/a | AF29: 745.278 | AG29: n/a | AH29: 195.73 | AI29: 2233.339 | AJ29: 3062.479 | AK29: n/a | AL29: 83.978 | AM29: n/a | AN29: 17673.527 | AO29: 1251.854 | AP29: 931.779 | AQ29: n/a | AR29: n/a | AS29: n/a | AT29: 15438.852 | AU29: n/a | AV29: n/a | AW29: 7562.534 | AX29: n/a | AY29: 664.512 | AZ29: n/a | BA29: -48.044 | BB29: 2208.679 | BC29: 2635.713 | BD29: n/a | BE29: 87.429 | BF29: n/a | BG29: 17344.95 | BH29: 1163.569 | BI29: 2374.17 | BJ29: n/a | BK29: n/a | BL29: n/a | BM29: 15226.499 | BN29: n/a | BO29: n/a | BP29: n/a | BQ29: 7101.507 | BR29: 16002.419 | BS29: -126.022
B30: Hertz Global | C30: HTZ | D30: 2012 | E30: 41337 | F30: 0 | G30: =Inputs!$C$13+Inputs!$C$14*M30+Inputs!$C$15*N30+Inputs!$C$16*O30+Inputs!$C$17*P30+Inputs!$C$18*Q30+Inputs!$C$19*R30+Inputs!$C$20*S30+Inputs!$C$21*T30 -> -2.9284363 | H30: =EXP(AB30)/(1+EXP(AB30))/Inputs!$C$32 -> 1.7192921 | I30: =IF(AND(F30=1,G30>Inputs!$C$7),1,0) -> 0 | J30: =IF(AND(F30=1,H30>Inputs!$C$8),1,0) -> 0 | K30: =MAX(I30,J30) -> 0 | L30: =I30*J30 -> 0 | M30: =IFERROR((AK30/AD30)/(BD30/AW30),1) -> 1 | N30: =IFERROR(((AW30-AX30)/AW30)/((AD30-AE30)/AD30),1) -> 1 | O30: =IFERROR((1-(AM30+AO30)/AN30)/(1-(BF30+BH30)/BG30),1) -> 1 | P30: =IFERROR(AD30/AW30,1) -> 1.0870564 | Q30: =IFERROR((AZ30/(AZ30+BH30))/(AG30/(AG30+AO30)),1) -> 1 | R30: =IFERROR((AF30/AD30)/(AY30/AW30),1) -> 1.1674051 | S30: =IFERROR((AH30-AI30)/AN30,0) -> -0.10628274 | T30: =IFERROR(((AS30+N(AU30))/AN30)/((BL30+N(BN30))/BG30),1) -> 1 | U30: =IFERROR((((AM30-AP30-N(AQ30))-(AS30-N(AV30))+(AN30-AM30-N(AR30))-(AT30-AS30-N(AU30))+(N(AQ30)+N(AR30))-(N(AU30)+N(AV30)))-((BF30-BI30-N(BJ30))-(BL30-N(BO30))+(BG30-BF30-N(BK30))-(BM30-BL30-N(BN30))+(N(BJ30)+N(BK30))-(N(BN30)+N(BO30))))/((AN30+BG30)/2),0) -> 0 | V30: =IFERROR((AK30-BD30)/((AN30+BG30)/2),0) -> 0 | W30: =IFERROR((N(AL30)-N(BE30))/((AN30+BG30)/2),0) -> 0.001062023 | X30: =IFERROR((AN30-N(AO30)-AP30)/AN30,0) -> 0.91541537 | Y30: =IF(COUNT(BP30,BQ30,BR30,BS30)=4,IFERROR((AD30-(AK30-BD30))/(AW30-(BD30-BP30))-1,0),0) -> 0 | Z30: =IF(COUNT(BP30,BQ30,BR30,BS30)=4,IFERROR(AH30/((AN30+BG30)/2)-BA30/((BG30+BR30)/2),0),0) -> 0 | AA30: =IF(N(AJ30)>0,1,0) -> 1 | AB30: =Inputs!$C$24+Inputs!$C$25*U30+Inputs!$C$26*V30+Inputs!$C$27*W30+Inputs!$C$28*X30+Inputs!$C$29*Y30+Inputs!$C$30*Z30+Inputs!$C$31*AA30 -> -5.0511281 | AD30: 9020.807 | AE30: n/a | AF30: 945.784 | AG30: n/a | AH30: 243.079 | AI30: 2717.983 | AJ30: 2237.28 | AK30: n/a | AL30: 105.728 | AM30: n/a | AN30: 23286.038 | AO30: 1436.386 | AP30: 533.255 | AQ30: n/a | AR30: n/a | AS30: n/a | AT30: 20778.733 | AU30: n/a | AV30: n/a | AW30: 8298.38 | AX30: n/a | AY30: 745.278 | AZ30: n/a | BA30: 195.73 | BB30: 2233.339 | BC30: 3062.479 | BD30: n/a | BE30: 83.978 | BF30: n/a | BG30: 17673.527 | BH30: 1251.854 | BI30: 931.779 | BJ30: n/a | BK30: n/a | BL30: n/a | BM30: 15438.852 | BN30: n/a | BO30: n/a | BP30: n/a | BQ30: 7562.534 | BR30: 17344.95 | BS30: -48.044
B31: Hertz Global | C31: HTZ | D31: 2013 | E31: 41717 | F31: 0 | G31: =Inputs!$C$13+Inputs!$C$14*M31+Inputs!$C$15*N31+Inputs!$C$16*O31+Inputs!$C$17*P31+Inputs!$C$18*Q31+Inputs!$C$19*R31+Inputs!$C$20*S31+Inputs!$C$21*T31 -> -2.9046847 | H31: =EXP(AB31)/(1+EXP(AB31))/Inputs!$C$32 -> 1.7356344 | I31: =IF(AND(F31=1,G31>Inputs!$C$7),1,0) -> 0 | J31: =IF(AND(F31=1,H31>Inputs!$C$8),1,0) -> 0 | K31: =MAX(I31,J31) -> 0 | L31: =I31*J31 -> 0 | M31: =IFERROR((AK31/AD31)/(BD31/AW31),1) -> 1 | N31: =IFERROR(((AW31-AX31)/AW31)/((AD31-AE31)/AD31),1) -> 1 | O31: =IFERROR((1-(AM31+AO31)/AN31)/(1-(BF31+BH31)/BG31),1) -> 1 | P31: =IFERROR(AD31/AW31,1) -> 1.1935756 | Q31: =IFERROR((AZ31/(AZ31+BH31))/(AG31/(AG31+AO31)),1) -> 1 | R31: =IFERROR((AF31/AD31)/(AY31/AW31),1) -> 0.88463831 | S31: =IFERROR((AH31-AI31)/AN31,0) -> -0.13190773 | T31: =IFERROR(((AS31+N(AU31))/AN31)/((BL31+N(BN31))/BG31),1) -> 1 | U31: =IFERROR((((AM31-AP31-N(AQ31))-(AS31-N(AV31))+(AN31-AM31-N(AR31))-(AT31-AS31-N(AU31))+(N(AQ31)+N(AR31))-(N(AU31)+N(AV31)))-((BF31-BI31-N(BJ31))-(BL31-N(BO31))+(BG31-BF31-N(BK31))-(BM31-BL31-N(BN31))+(N(BJ31)+N(BK31))-(N(BN31)+N(BO31))))/((AN31+BG31)/2),0) -> 0 | V31: =IFERROR((AK31-BD31)/((AN31+BG31)/2),0) -> 0 | W31: =IFERROR((N(AL31)-N(BE31))/((AN31+BG31)/2),0) -> -0.00056005199 | X31: =IFERROR((AN31-N(AO31)-AP31)/AN31,0) -> 0.92120268 | Y31: =IF(COUNT(BP31,BQ31,BR31,BS31)=4,IFERROR((AD31-(AK31-BD31))/(AW31-(BD31-BP31))-1,0),0) -> 0 | Z31: =IF(COUNT(BP31,BQ31,BR31,BS31)=4,IFERROR(AH31/((AN31+BG31)/2)-BA31/((BG31+BR31)/2),0),0) -> 0 | AA31: =IF(N(AJ31)>0,1,0) -> 1 | AB31: =Inputs!$C$24+Inputs!$C$25*U31+Inputs!$C$26*V31+Inputs!$C$27*W31+Inputs!$C$28*X31+Inputs!$C$29*Y31+Inputs!$C$30*Z31+Inputs!$C$31*AA31 -> -5.0416069 | AD31: 10771.9 | AE31: n/a | AF31: 1022.2 | AG31: n/a | AH31: 346.2 | AI31: 3589.6 | AJ31: 1774.7 | AK31: n/a | AL31: 92.3 | AM31: n/a | AN31: 24588.4 | AO31: 1514.3 | AP31: 423.2 | AQ31: n/a | AR31: n/a | AS31: n/a | AT31: 21817.2 | AU31: n/a | AV31: n/a | AW31: 9024.9 | AX31: n/a | AY31: 968.1 | AZ31: n/a | BA31: 238.6 | BB31: 2709.7 | BC31: 2237.3 | BD31: n/a | BE31: 105.7 | BF31: n/a | BG31: 23264.3 | BH31: 1436.4 | BI31: 545.5 | BJ31: n/a | BK31: n/a | BL31: n/a | BM31: 20778.1 | BN31: n/a | BO31: n/a | BP31: n/a | BQ31: 8299.3 | BR31: 17673.527 | BS31: 183.8
B32: Roadrunner Transportation | C32: RRTS | D32: 2013 | E32: 41711 | F32: 1 | G32: =Inputs!$C$13+Inputs!$C$14*M32+Inputs!$C$15*N32+Inputs!$C$16*O32+Inputs!$C$17*P32+Inputs!$C$18*Q32+Inputs!$C$19*R32+Inputs!$C$20*S32+Inputs!$C$21*T32 -> -2.0971025 | H32: =EXP(AB32)/(1+EXP(AB32))/Inputs!$C$32 -> 2.1921846 | I32: =IF(AND(F32=1,G32>Inputs!$C$7),1,0) -> 0 | J32: =IF(AND(F32=1,H32>Inputs!$C$8),1,0) -> 1 | K32: =MAX(I32,J32) -> 1 | L32: =I32*J32 -> 0 | M32: =IFERROR((AK32/AD32)/(BD32/AW32),1) -> 1.0976176 | N32: =IFERROR(((AW32-AX32)/AW32)/((AD32-AE32)/AD32),1) -> 1 | O32: =IFERROR((1-(AM32+AO32)/AN32)/(1-(BF32+BH32)/BG32),1) -> 0.96682362 | P32: =IFERROR(AD32/AW32,1) -> 1.26837 | Q32: =IFERROR((AZ32/(AZ32+BH32))/(AG32/(AG32+AO32)),1) -> 0.86737501 | R32: =IFERROR((AF32/AD32)/(AY32/AW32),1) -> 1 | S32: =IFERROR((AH32-AI32)/AN32,0) -> 0.014764647 | T32: =IFERROR(((AS32+N(AU32))/AN32)/((BL32+N(BN32))/BG32),1) -> 0.95940487 | U32: =IFERROR((((AM32-AP32-N(AQ32))-(AS32-N(AV32))+(AN32-AM32-N(AR32))-(AT32-AS32-N(AU32))+(N(AQ32)+N(AR32))-(N(AU32)+N(AV32)))-((BF32-BI32-N(BJ32))-(BL32-N(BO32))+(BG32-BF32-N(BK32))-(BM32-BL32-N(BN32))+(N(BJ32)+N(BK32))-(N(BN32)+N(BO32))))/((AN32+BG32)/2),0) -> 0.14593613 | V32: =IFERROR((AK32-BD32)/((AN32+BG32)/2),0) -> 0.061319219 | W32: =IFERROR((N(AL32)-N(BE32))/((AN32+BG32)/2),0) -> 0 | X32: =IFERROR((AN32-N(AO32)-AP32)/AN32,0) -> 0.88301601 | Y32: =IF(COUNT(BP32,BQ32,BR32,BS32)=4,IFERROR((AD32-(AK32-BD32))/(AW32-(BD32-BP32))-1,0),0) -> 0.2473743 | Z32: =IF(COUNT(BP32,BQ32,BR32,BS32)=4,IFERROR(AH32/((AN32+BG32)/2)-BA32/((BG32+BR32)/2),0),0) -> 0.0019964891 | AA32: =IF(N(AJ32)>0,1,0) -> 1 | AB32: =Inputs!$C$24+Inputs!$C$25*U32+Inputs!$C$26*V32+Inputs!$C$27*W32+Inputs!$C$28*X32+Inputs!$C$29*Y32+Inputs!$C$30*Z32+Inputs!$C$31*AA32 -> -4.8063797 | AD32: 1361.41 | AE32: n/a | AF32: n/a | AG32: 18.49 | AH32: 48.996 | AI32: 36.123 | AJ32: 75.059 | AK32: 171.165 | AL32: n/a | AM32: 213.46 | AN32: 871.88 | AO32: 96.558 | AP32: 5.438 | AQ32: n/a | AR32: n/a | AS32: 111.35 | AT32: 371.515 | AU32: 181.702 | AV32: 10.938 | AW32: 1073.354 | AX32: n/a | AY32: n/a | AZ32: 11.108 | BA32: 37.53 | BB32: 36.723 | BC32: 97.619 | BD32: 122.947 | BE32: n/a | BF32: 165.116 | BG32: 700.808 | BH32: 68.576 | BI32: 11.908 | BJ32: n/a | BK32: n/a | BL32: 101.019 | BM32: 308.729 | BN32: 144.5 | BO32: 17 | BP32: 102.358 | BQ32: 843.627 | BR32: 543.718 | BS32: 25.871
B33: Roadrunner Transportation | C33: RRTS | D33: 2014 | E33: 42065 | F33: 1 | G33: =Inputs!$C$13+Inputs!$C$14*M33+Inputs!$C$15*N33+Inputs!$C$16*O33+Inputs!$C$17*P33+Inputs!$C$18*Q33+Inputs!$C$19*R33+Inputs!$C$20*S33+Inputs!$C$21*T33 -> -2.06807 | H33: =EXP(AB33)/(1+EXP(AB33))/Inputs!$C$32 -> 2.3032973 | I33: =IF(AND(F33=1,G33>Inputs!$C$7),1,0) -> 0 | J33: =IF(AND(F33=1,H33>Inputs!$C$8),1,0) -> 1 | K33: =MAX(I33,J33) -> 1 | L33: =I33*J33 -> 0 | M33: =IFERROR((AK33/AD33)/(BD33/AW33),1) -> 1.2077482 | N33: =IFERROR(((AW33-AX33)/AW33)/((AD33-AE33)/AD33),1) -> 1 | O33: =IFERROR((1-(AM33+AO33)/AN33)/(1-(BF33+BH33)/BG33),1) -> 0.93758639 | P33: =IFERROR(AD33/AW33,1) -> 1.3756444 | Q33: =IFERROR((AZ33/(AZ33+BH33))/(AG33/(AG33+AO33)),1) -> 0.99073983 | R33: =IFERROR((AF33/AD33)/(AY33/AW33),1) -> 1 | S33: =IFERROR((AH33-AI33)/AN33,0) -> 0.0090187785 | T33: =IFERROR(((AS33+N(AU33))/AN33)/((BL33+N(BN33))/BG33),1) -> 1.3981405 | U33: =IFERROR((((AM33-AP33-N(AQ33))-(AS33-N(AV33))+(AN33-AM33-N(AR33))-(AT33-AS33-N(AU33))+(N(AQ33)+N(AR33))-(N(AU33)+N(AV33)))-((BF33-BI33-N(BJ33))-(BL33-N(BO33))+(BG33-BF33-N(BK33))-(BM33-BL33-N(BN33))+(N(BJ33)+N(BK33))-(N(BN33)+N(BO33))))/((AN33+BG33)/2),0) -> 0.049305536 | V33: =IFERROR((AK33-BD33)/((AN33+BG33)/2),0) -> 0.1063192 | W33: =IFERROR((N(AL33)-N(BE33))/((AN33+BG33)/2),0) -> 0 | X33: =IFERROR((AN33-N(AO33)-AP33)/AN33,0) -> 0.87423081 | Y33: =IF(COUNT(BP33,BQ33,BR33,BS33)=4,IFERROR((AD33-(AK33-BD33))/(AW33-(BD33-BP33))-1,0),0) -> 0.33994267 | Z33: =IF(COUNT(BP33,BQ33,BR33,BS33)=4,IFERROR(AH33/((AN33+BG33)/2)-BA33/((BG33+BR33)/2),0),0) -> -0.013499856 | AA33: =IF(N(AJ33)>0,1,0) -> 1 | AB33: =Inputs!$C$24+Inputs!$C$25*U33+Inputs!$C$26*V33+Inputs!$C$27*W33+Inputs!$C$28*X33+Inputs!$C$29*Y33+Inputs!$C$30*Z33+Inputs!$C$31*AA33 -> -4.756522 | AD33: 1872.816 | AE33: n/a | AF33: n/a | AG33: 25.078 | AH33: 51.974 | AI33: 40.63 | AJ33: 33.75 | AK33: 284.379 | AL33: n/a | AM33: 350.989 | AN33: 1257.82 | AO33: 146.85 | AP33: 11.345 | AQ33: n/a | AR33: n/a | AS33: 171.095 | AT33: 699.045 | AU33: 420 | AV33: 10 | AW33: 1361.41 | AX33: n/a | AY33: n/a | AZ33: 16.311 | BA33: 48.996 | BB33: 36.123 | BC33: 75.059 | BD33: 171.165 | BE33: n/a | BF33: 213.46 | BG33: 871.88 | BH33: 96.558 | BI33: 5.438 | BJ33: n/a | BK33: n/a | BL33: 111.35 | BM33: 371.515 | BN33: 181.702 | BO33: 10.938 | BP33: 122.947 | BQ33: 1073.354 | BR33: 700.808 | BS33: 37.53
B34: Roadrunner Transportation | C34: RRTS | D34: 2015 | E34: 42430 | F34: 1 | G34: =Inputs!$C$13+Inputs!$C$14*M34+Inputs!$C$15*N34+Inputs!$C$16*O34+Inputs!$C$17*P34+Inputs!$C$18*Q34+Inputs!$C$19*R34+Inputs!$C$20*S34+Inputs!$C$21*T34 -> -2.5945795 | H34: =EXP(AB34)/(1+EXP(AB34))/Inputs!$C$32 -> 1.5631827 | I34: =IF(AND(F34=1,G34>Inputs!$C$7),1,0) -> 0 | J34: =IF(AND(F34=1,H34>Inputs!$C$8),1,0) -> 0 | K34: =MAX(I34,J34) -> 0 | L34: =I34*J34 -> 0 | M34: =IFERROR((AK34/AD34)/(BD34/AW34),1) -> 0.89846338 | N34: =IFERROR(((AW34-AX34)/AW34)/((AD34-AE34)/AD34),1) -> 1 | O34: =IFERROR((1-(AM34+AO34)/AN34)/(1-(BF34+BH34)/BG34),1) -> 0.97418136 | P34: =IFERROR(AD34/AW34,1) -> 1.0652509 | Q34: =IFERROR((AZ34/(AZ34+BH34))/(AG34/(AG34+AO34)),1) -> 1.038219 | R34: =IFERROR((AF34/AD34)/(AY34/AW34),1) -> 1 | S34: =IFERROR((AH34-AI34)/AN34,0) -> -0.019124894 | T34: =IFERROR(((AS34+N(AU34))/AN34)/((BL34+N(BN34))/BG34),1) -> 0.9506077 | U34: =IFERROR((((AM34-AP34-N(AQ34))-(AS34-N(AV34))+(AN34-AM34-N(AR34))-(AT34-AS34-N(AU34))+(N(AQ34)+N(AR34))-(N(AU34)+N(AV34)))-((BF34-BI34-N(BJ34))-(BL34-N(BO34))+(BG34-BF34-N(BK34))-(BM34-BL34-N(BN34))+(N(BJ34)+N(BK34))-(N(BN34)+N(BO34))))/((AN34+BG34)/2),0) -> 0.04428345 | V34: =IFERROR((AK34-BD34)/((AN34+BG34)/2),0) -> -0.0094452475 | W34: =IFERROR((N(AL34)-N(BE34))/((AN34+BG34)/2),0) -> 0 | X34: =IFERROR((AN34-N(AO34)-AP34)/AN34,0) -> 0.84435253 | Y34: =IF(COUNT(BP34,BQ34,BR34,BS34)=4,IFERROR((AD34-(AK34-BD34))/(AW34-(BD34-BP34))-1,0),0) -> 0.140725 | Z34: =IF(COUNT(BP34,BQ34,BR34,BS34)=4,IFERROR(AH34/((AN34+BG34)/2)-BA34/((BG34+BR34)/2),0),0) -> -0.011656259 | AA34: =IF(N(AJ34)>0,1,0) -> 1 | AB34: =Inputs!$C$24+Inputs!$C$25*U34+Inputs!$C$26*V34+Inputs!$C$27*W34+Inputs!$C$28*X34+Inputs!$C$29*Y34+Inputs!$C$30*Z34+Inputs!$C$31*AA34 -> -5.1468979 | AD34: 1995.019 | AE34: n/a | AF34: n/a | AG34: 32.323 | AH34: 48 | AI34: 73.362 | AJ34: 110 | AK34: 272.176 | AL34: n/a | AM34: 347.817 | AN34: 1326.125 | AO34: 197.744 | AP34: 8.664 | AQ34: n/a | AR34: n/a | AS34: 168.014 | AT34: 712.818 | AU34: 424.399 | AV34: 15 | AW34: 1872.816 | AX34: n/a | AY34: n/a | AZ34: 25.078 | BA34: 51.974 | BB34: 40.63 | BC34: 33.75 | BD34: 284.379 | BE34: n/a | BF34: 350.989 | BG34: 1257.82 | BH34: 146.85 | BI34: 11.345 | BJ34: n/a | BK34: n/a | BL34: 171.095 | BM34: 699.045 | BN34: 420 | BO34: 10 | BP34: 171.165 | BQ34: 1361.41 | BR34: 871.88 | BS34: 48.996
